Workbook

Sheet Propane Boiler BAU ReOPT
A1: Scenario | B1: Full cost (25 year) | C1: NPV savings (10 year) | D1: REopt Results: | E1: Select Technologies to Evaluate | F1: Evaluation name | G1: Site location (latitude, longitude) | H1: PV & wind space available | I1: Roofspace available (sq ft) | J1: Electricity rate | K1: Compensation type | L1: Existing heating system fuel type | M1: Annual existing heating system fuel cost ($/gallon) | N1: Upload typical electric load profile | O1: Year of load profile | P1: Upload typical heating load profile | Q1: Space heating load percent of total heating load (%) | R1: Year of load profile | S1: Existing heating system efficiency (% HHV-basis) | T1: Analysis period (years) | U1: Host discount rate, nominal (%) | V1: Electricity cost escalation rate, nominal (%/year) | W1: Existing heating system fuel cost escalation rate, nominal (%/year) | X1: Host effective tax rate (%) | Y1: Emissions | Z1: Size class | AA1: System capital cost ($/kW-DC) | AB1: Array type | AC1: Array azimuth (deg) | AD1: Array tilt (deg) | AE1: Federal Incentive based on percentage of cost (%) | AF1: MACRS schedule | AG1: MACRS bonus depreciation | AH1: REopt Results: | AI1: Optimized PV size (kW) | AJ1: Optimized ASHP size (tonnes) | AK1: Potential Life Cycle Savings | AL1: Avg. Annual Grid Serving Load (kWh) | AM1: Avg. Annual Grid Charging Battery (kWh) | AN1: Avg. Annual Grid Total Electricity Consumed (kWh) | AO1: Avg. Annual PV Serving Load (kWh) | AP1: Avg. Annual PV Charging Battery (kWh) | AQ1: Avg. Annual PV Exported to Grid (kWh) | AR1: Avg. Annual PV Curtailment (kWh) | AS1: Avg. Annual PV Total Electricity Produced (kWh) | AT1: Avg. Annual Battery Serving Load (kWh) | AU1: BAU Average Annual Energy Supplied from Grid (kWh) | AV1: System Average Annual Energy Supplied from Grid (kWh) | AW1: Difference in Avg. Annual Energy Supplied from Grid | AX1: w/PV Annual Renewable Electricity (% of electricity consumed) | AY1: PV Avoided CO2e Emissions throughout Analysis Period | AZ1: BAU Total Year 1 Elec Cost - Pre-Tax | BA1: Total Year 1 Elec Cost - Pre-Tax | BB1: Difference Total Year 1 Elec Cost | BC1: BAU Total Full Period Elec Cost | BD1: Optimized Total Full Period Elec Cost | BE1: Difference in Full Period Utility Cost | BF1: BAUTotal Life Cycle Costs | BG1: Total Life Cycle Costs | BI1: Net Present Value | BJ1: Payback Period for PV /Battery (yrs)
A2: Broken controls propane boiler, full cost | D2: Broken controls propane boiler, full cost | REopt Web Tool | REopt Energy Integration & Optimization | NLR | E2: PV (but roofspace 0) | F2: Broken controls propane boiler, full cost | G2: 47.85212, -122.56923 | H2: Roofspace only | I2: 0 | J2: PSE: 24 (General Service - Three Phase) | K2: No compensation for exports | L2: propane | M2: 2.01 | N2: https://drive.google.com/file/d/1Xl5WOtWsJzfbC-Y8nCxkp4Y4Mozirc_L/view?usp=drive_link | O2: 2024 | P2: https://drive.google.com/file/d/12MjGV739OVxdOUym7sn516wQM4dv51MR/view?usp=drive_link | Q2: 100 | R2: 2024 | S2: 83.07 | T2: 25 | U2: 2.5 | V2: 6 | W2: 7.8 | X2: 0 | Y2: - | Z2: Small Commercial | AA2: 2220 | AB2: Rooftop, Fixed | AC2: 335.4 | AD2: 10.7 | AE2: 0 | AF2: No MACRS | AG2: 0 | AH2: Broken controls propane boiler, full cost | REopt Web Tool | REopt Energy Integration & Optimization | NLR | AZ2: 355438 | BA2: 355438 | BF2: 916753 | BG2: 916753
A3: Broken controls propane boiler, free capital | D3: Broken controls propane boiler, free capital | REopt Web Tool | REopt Energy Integration & Optimization | NLR | E3: PV (but roofspace 0) | F3: Broken controls propane boiler, free capital | G3: 47.85212, -122.56923 | H3: Roofspace only | I3: 0 | J3: PSE: 24 (General Service - Three Phase) | K3: No compensation for exports | L3: propane | M3: 2.01 | N3: https://drive.google.com/file/d/1Xl5WOtWsJzfbC-Y8nCxkp4Y4Mozirc_L/view?usp=drive_link | O3: 2024 | P3: https://drive.google.com/file/d/12MjGV739OVxdOUym7sn516wQM4dv51MR/view?usp=drive_link | Q3: 100 | R3: 2024 | S3: 83.07 | T3: 10 | U3: 2.5 | V3: 6 | W3: 7.8 | X3: 0 | Y3: - | Z3: Small Commercial | AA3: 0 | AB3: Rooftop, Fixed | AC3: 335.4 | AD3: 10.7 | AE3: 0 | AF3: No MACRS | AG3: 0 | AH3: Broken controls propane boiler, free capital | REopt Web Tool | REopt Energy Integration & Optimization | NLR | AZ3: 107850 | BA3: 107850 | BF3: 316497 | BG3: 316497
A5: Fixed controls propane boiler, full cost | D5: Fixed controls propane boiler, full cost | REopt Web Tool | REopt Energy Integration & Optimization | NLR | E5: PV (but roofspace 0) | F5: Broken controls propane boiler, full cost | G5: 47.85212, -122.56923 | H5: Roofspace only | I5: 0 | J5: PSE: 24 (General Service - Three Phase) | K5: No compensation for exports | L5: propane | M5: 2.01 | N5: https://drive.google.com/file/d/1Xl5WOtWsJzfbC-Y8nCxkp4Y4Mozirc_L/view?usp=drive_link | O5: 2024 | P5: https://drive.google.com/file/d/12MjGV739OVxdOUym7sn516wQM4dv51MR/view?usp=drive_link | Q5: 100 | R5: 2024 | S5: 83.07 | T5: 25 | U5: 2.5 | V5: 6 | W5: 7.8 | X5: 0 | Y5: - | Z5: Small Commercial | AA5: 2220 | AB5: Rooftop, Fixed | AC5: 335.4 | AD5: 10.7 | AE5: 0 | AF5: No MACRS | AG5: 0 | AH5: Fixed controls propane boiler, full cost | REopt Web Tool | REopt Energy Integration & Optimization | NLR | AZ5: 355438 | BA5: 355438 | BF5: 881918 | BG5: 881918
A6: Fixed controls propane boiler, free capital | D6: Fixed controls propane boiler, free capital | REopt Web Tool | REopt Energy Integration & Optimization | NLR | E6: PV (but roofspace 0) | F6: Broken controls propane boiler, free capital | G6: 47.85212, -122.56923 | H6: Roofspace only | I6: 0 | J6: PSE: 24 (General Service - Three Phase) | K6: No compensation for exports | L6: propane | M6: 2.01 | N6: https://drive.google.com/file/d/1Xl5WOtWsJzfbC-Y8nCxkp4Y4Mozirc_L/view?usp=drive_link | O6: 2024 | P6: https://drive.google.com/file/d/12MjGV739OVxdOUym7sn516wQM4dv51MR/view?usp=drive_link | Q6: 100 | R6: 2024 | S6: 83.07 | T6: 10 | U6: 2.5 | V6: 6 | W6: 7.8 | X6: 0 | Y6: - | Z6: Small Commercial | AA6: 0 | AB6: Rooftop, Fixed | AC6: 335.4 | AD6: 10.7 | AE6: 0 | AF6: No MACRS | AG6: 0 | AH6: Fixed controls propane boiler, free capital | REopt Web Tool | REopt Energy Integration & Optimization | NLR | AZ6: 107850 | BA6: 107850 | BF6: 303549 | BG6: 303549

Sheet LT Heat Pumps
A1: Scenario | B1: Neither | C1: Net metering | D1: Net billing | E1: No PV | F1: CEC & EC PV | G1: Full cost (25 year) | H1: NPV savings (10 year) | I1: REopt Results: | J1: Select Technologies to Evaluate | K1: Air-Source Heat Pump configuration | L1: Evaluation name | M1: Site location (latitude, longitude) | N1: PV & wind space available | O1: Roofspace available (sq ft) | P1: Electricity rate | Q1: Compensation type | R1: Net metering system size limit (kW) | S1: Net billing compensation for all exports ($/kWh) | T1: Existing heating system fuel type | U1: Annual existing heating system fuel cost ($/gallon) | V1: Upload typical electric load profile | W1: Year of load profile | X1: Upload typical heating load profile | Y1: Space heating load percent of total heating load (%) | Z1: Year of load profile | AA1: Existing heating system efficiency (% HHV-basis) | AB1: Analysis period (years) | AC1: Host discount rate, nominal (%) | AD1: Electricity cost escalation rate, nominal (%/year) | AE1: Existing heating system fuel cost escalation rate, nominal (%/year) | AF1: Host effective tax rate (%) | AG1: Emissions | AH1: Size class | AI1: System capital cost ($/kW-DC) | AJ1: Array type | AK1: Array azimuth (deg) | AL1: Array tilt (deg) | AM1: Federal Incentive based on percentage of cost (%) | AN1: MACRS schedule | AO1: MACRS bonus depreciation | AP1: Energy capacity cost ($/kWh) | AQ1: Power capacity cost ($/kW) | AR1: Constant cost ($) | AS1: Minimum energy capacity (kWh) | AT1: Maximum energy capacity (kWh) | AU1: Energy capacity replacement cost ($/kWh) | AV1: Power capacity replacement cost ($/kWh) | AW1: Constant replacement cost ($) | AX1: Minimum power capacity (kW) | AY1: Maximum power capacity (kW) | AZ1: Federal Incentive based on percentage of cost (%) | BA1: MACRS schedule | BB1: MACRS bonus depreciation | BC1: Total installed cost ($/ton) | BD1: Upload COP Table | BE1: Heat pump capacity sizing factor | BF1: Resistive heating back-up temperature threshold (°F) | BG1: MACRS schedule | BH1: MACRS bonus depreciation | BI1: REopt Results: | BJ1: Optimized PV size (kW) | BK1: Optimized ASHP size (tonnes) | BL1: Optimized Battery Power and Capacity (kW/kWh) | BM1: Potential Life Cycle Savings | BN1: Avg. Annual Grid Serving Load (kWh) | BO1: Avg. Annual Grid Charging Battery (kWh) | BP1: Avg. Annual Grid Total Electricity Consumed (kWh) | BQ1: Avg. Annual PV Serving Load (kWh) | BR1: Avg. Annual PV Charging Battery (kWh) | BS1: Avg. Annual PV Exported to Grid (kWh) | BT1: Avg. Annual PV Curtailment (kWh) | BU1: Avg. Annual PV Total Electricity Produced (kWh) | BV1: Avg. Annual Battery Serving Load (kWh) | BW1: BAU Average Annual Energy Supplied from Grid (kWh) | BX1: System Average Annual Energy Supplied from Grid (kWh) | BY1: Difference in Avg. Annual Energy Supplied from Grid | BZ1: Annual Renewable Electricity (% of electricity consumed) | CA1: BAU Total Year 1 Elec Cost - Pre-Tax | CB1: Total Year 1 Elec Cost - Pre-Tax | CC1: Difference Total Year 1 Elec Cost | CD1: BAU Total Full Period Elec Cost | CE1: PV Total Full Period Elec Cost | CF1: Difference in Full Period Utility Cost | CG1: BAU Total Life Cycle Costs | CH1: PV/Battery Total Life Cycle Costs | CI1: Difference in Total life cycle costs | CJ1: w/PV/ Battery Net Present Value | CK1: Payback Period for PV /Battery (yrs)
A2: LT Heat Pumps, no PV, full cost | I2: LT Heat Pumps, no PV, full cost | J2: ASHP | K2: 2: Full replacement heating | L2: LT Heat Pumps, no PV, full cost | M2: 47.85212, -122.56923 | N2: Roofspace only | O2: 8000 | P2: PSE: 25 | Q2: N/A | R2: - | S2: - | T2: propane | U2: 2.01 | V2: https://drive.google.com/file/d/1Xl5WOtWsJzfbC-Y8nCxkp4Y4Mozirc_L/view?usp=drive_link | W2: 2024 | X2: https://drive.google.com/file/d/12MjGV739OVxdOUym7sn516wQM4dv51MR/view?usp=drive_link | Y2: 100 | Z2: 2024 | AA2: 83.07 | AB2: 25 | AC2: 2.5 | AD2: 6 | AE2: 7.8 | AF2: 0 | AG2: - | AH2: - | AI2: - | AJ2: - | AK2: - | AL2: - | AM2: - | AN2: - | AO2: - | AP2: - | AQ2: - | AR2: - | AS2: - | AT2: - | AU2: - | AV2: - | AW2: - | AX2: - | AY2: - | AZ2: - | BA2: - | BB2: - | BC2: 0 | BD2: https://drive.google.com/file/d/1jrpu40DzxTFYY6LiD8LJLWmYTYBMVds2/view?usp=drive_link | BE2: 1 | BF2: 10 | BG2: No MACRS | BH2: 0 | BI2: LT Heat Pumps, no PV, full cost | BJ2: - | BK2: 35 | BL2: - | BM2: -86028 | BN2: - | BO2: - | BP2: - | BQ2: - | BR2: - | BS2: - | BT2: - | BU2: - | BV2: - | BW2: 44197 | BX2: 132850 | BY2: =BX2-BW2 -> 88653 | BZ2: 0 | CA2: 8394 | CB2: 23773 | CC2: =CB2-CA2 -> 15379 | CD2: 334284 | CE2: 946792 | CF2: =CE2-CD2 -> 612508 | CG2: 860764 | CH2: 946792 | CI2: =CH2-CG2 -> 86028 | CJ2: -86028 | CK2: 0
A3: LT Heat Pumps, no PV, free capital | I3: LT Heat Pumps, no PV, free capital | J3: ASHP | K3: 2: Full replacement heating | L3: LT Heat Pumps, no PV, free capital | M3: 47.85212, -122.56923 | N3: Roofspace only | O3: 8000 | P3: PSE: 25 | Q3: N/A | R3: - | S3: - | T3: propane | U3: 2.01 | V3: https://drive.google.com/file/d/1Xl5WOtWsJzfbC-Y8nCxkp4Y4Mozirc_L/view?usp=drive_link | W3: 2024 | X3: https://drive.google.com/file/d/12MjGV739OVxdOUym7sn516wQM4dv51MR/view?usp=drive_link | Y3: 100 | Z3: 2024 | AA3: 83.07 | AB3: 10 | AC3: 2.5 | AD3: 6 | AE3: 7.8 | AF3: 0 | AG3: - | AH3: - | AI3: - | AJ3: - | AK3: - | AL3: - | AM3: - | AN3: - | AO3: - | AP3: - | AQ3: - | AR3: - | AS3: - | AT3: - | AU3: - | AV3: - | AW3: - | AX3: - | AY3: - | AZ3: - | BA3: - | BB3: - | BC3: 0 | BD3: https://drive.google.com/file/d/1jrpu40DzxTFYY6LiD8LJLWmYTYBMVds2/view?usp=drive_link | BE3: 1 | BF3: 10 | BG3: No MACRS | BH3: 0 | BI3: LT Heat Pumps, no PV, free capital | BJ3: - | BK3: 35 | BL3: - | BM3: 9846 | BN3: - | BO3: - | BP3: - | BQ3: - | BR3: - | BS3: - | BT3: - | BU3: - | BV3: - | BW3: 44197 | BX3: 132850 | BY3: =BX3-BW3 -> 88653 | BZ3: 0 | CA3: 8394 | CB3: 23773 | CC3: =CB3-CA3 -> 15379 | CD3: 101431 | CE3: 287284 | CF3: =CE3-CD3 -> 185853 | CG3: 297130 | CH3: 287284 | CI3: =CH3-CG3 -> -9846 | CJ3: 9846 | CK3: 0
A4: LT Heat Pumps, net metering, full cost | I4: LT Heat Pumps, net metering, full cost | J4: ASHP, PV | K4: 2: Full replacement heating | L4: LT Heat Pumps, net metering, full cost | M4: 47.85212, -122.56923 | N4: Roofspace only | O4: 8000 | P4: PSE: 25 | Q4: Net metering | R4: 100 | S4: - | T4: propane | U4: 2.01 | V4: https://drive.google.com/file/d/1Xl5WOtWsJzfbC-Y8nCxkp4Y4Mozirc_L/view?usp=drive_link | W4: 2024 | X4: https://drive.google.com/file/d/12MjGV739OVxdOUym7sn516wQM4dv51MR/view?usp=drive_link | Y4: 100 | Z4: 2024 | AA4: 83.07 | AB4: 25 | AC4: 2.5 | AD4: 6 | AE4: 7.8 | AF4: 0 | AG4: - | AH4: Small Commercial | AI4: 2220 | AJ4: Rooftop, Fixed | AK4: 335.4 | AL4: 10.7 | AM4: 0 | AN4: No MACRS | AO4: 0 | AP4: - | AQ4: - | AR4: - | AS4: - | AT4: - | AU4: - | AV4: - | AW4: - | AX4: - | AY4: - | AZ4: - | BA4: - | BB4: - | BC4: 0 | BD4: https://drive.google.com/file/d/1jrpu40DzxTFYY6LiD8LJLWmYTYBMVds2/view?usp=drive_link | BE4: 1 | BF4: 10 | BG4: No MACRS | BH4: 0 | BI4: LT Heat Pumps, net metering, full cost | BJ4: 80 | BK4: 35 | BL4: - | BM4: 74069 | BN4: 105036 | BO4: 0 | BP4: =BN4-BO4 -> 105036 | BQ4: 27815 | BR4: 0 | BS4: 34023 | BT4: 0 | BU4: =BQ4+BR4+BS4+BT4 -> 61838 | BV4: - | BW4: 44197 | BX4: =BP4 -> 105036 | BY4: =BX4-BW4 -> 60839 | BZ4: 0.47 | CA4: 8394 | CB4: 13988 | CC4: =CB4-CA4 -> 5594 | CD4: 334284 | CE4: 557095 | CF4: =CE4-CD4 -> 222811 | CG4: 860764 | CH4: 786695 | CI4: =CH4-CG4 -> -74069 | CJ4: 74069 | CK4: 13.88
A5: LT Heat Pumps, net metering, free capital | I5: LT Heat Pumps, net metering, free capital | J5: ASHP, PV | K5: 2: Full replacement heating | L5: LT Heat Pumps, net metering, free capital | M5: 47.85212, -122.56923 | N5: Roofspace only | O5: 8000 | P5: PSE: 25 | Q5: Net metering | R5: 100 | S5: - | T5: propane | U5: 2.01 | V5: https://drive.google.com/file/d/1Xl5WOtWsJzfbC-Y8nCxkp4Y4Mozirc_L/view?usp=drive_link | W5: 2024 | X5: https://drive.google.com/file/d/12MjGV739OVxdOUym7sn516wQM4dv51MR/view?usp=drive_link | Y5: 100 | Z5: 2024 | AA5: 83.07 | AB5: 10 | AC5: 2.5 | AD5: 6 | AE5: 7.8 | AF5: 0 | AG5: - | AH5: Small Commercial | AI5: 0 | AJ5: Rooftop, Fixed | AK5: 335.4 | AL5: 10.7 | AM5: 0 | AN5: No MACRS | AO5: 0 | AP5: - | AQ5: - | AR5: - | AS5: - | AT5: - | AU5: - | AV5: - | AW5: - | AX5: - | AY5: - | AZ5: - | BA5: - | BB5: - | BC5: 0 | BD5: https://drive.google.com/file/d/1jrpu40DzxTFYY6LiD8LJLWmYTYBMVds2/view?usp=drive_link | BE5: 1 | BF5: 10 | BG5: No MACRS | BH5: 0 | BI5: LT Heat Pumps, net metering, free capital | BJ5: 80 | BK5: 35 | BL5: - | BM5: 112478 | BN5: 104535 | BO5: 0 | BP5: =BN5-BO5 -> 104535 | BQ5: 28315 | BR5: 0 | BS5: 36325 | BT5: 0 | BU5: =BQ5+BR5+BS5+BT5+1 -> 64641 | BV5: - | BW5: 44197 | BX5: =BP5 -> 104535 | BY5: =BX5-BW5 -> 60338 | BZ5: 0.49 | CA5: 8394 | CB5: 13559 | CC5: =CB5-CA5 -> 5165 | CD5: 101431 | CE5: 163852 | CF5: =CE5-CD5 -> 62421 | CG5: 297130 | CH5: 184652 | CI5: =CH5-CG5 -> -112478 | CJ5: 112478 | CK5: 0
A6: LT Heat Pumps, net billing, full cost | I6: LT Heat Pumps, net billing, full cost | J6: ASHP, PV | K6: 2: Full replacement heating | L6: LT Heat Pumps, net billing, full cost | M6: 47.85212, -122.56923 | N6: Roofspace only | O6: 8000 | P6: PSE: 25 | Q6: Net billing | R6: - | S6: 0.06713 | T6: propane | U6: 2.01 | V6: https://drive.google.com/file/d/1Xl5WOtWsJzfbC-Y8nCxkp4Y4Mozirc_L/view?usp=drive_link | W6: 2024 | X6: https://drive.google.com/file/d/12MjGV739OVxdOUym7sn516wQM4dv51MR/view?usp=drive_link | Y6: 100 | Z6: 2024 | AA6: 83.07 | AB6: 25 | AC6: 2.5 | AD6: 6 | AE6: 7.8 | AF6: 0 | AG6: - | AH6: Small Commercial | AI6: 2220 | AJ6: Rooftop, Fixed | AK6: 335.4 | AL6: 10.7 | AM6: 0 | AN6: No MACRS | AO6: 0 | AP6: - | AQ6: - | AR6: - | AS6: - | AT6: - | AU6: - | AV6: - | AW6: - | AX6: - | AY6: - | AZ6: - | BA6: - | BB6: - | BC6: 0 | BD6: https://drive.google.com/file/d/1jrpu40DzxTFYY6LiD8LJLWmYTYBMVds2/view?usp=drive_link | BE6: 1 | BF6: 10 | BG6: No MACRS | BH6: 0 | BI6: LT Heat Pumps, net billing, full cost | BJ6: 55 | BK6: 35 | BL6: - | BM6: -33927 | BN6: 109169 | BO6: 0 | BP6: =BN6-BO6 -> 109169 | BQ6: 23682 | BR6: 0 | BS6: 18814 | BT6: 0 | BU6: =BQ6+BR6+BS6+BT6 -> 42496 | BV6: - | BW6: 44197 | BX6: =BP6 -> 109169 | BY6: =BX6-BW6 -> 64972 | BZ6: 0.32 | CA6: 8394 | CB6: 18503 | CC6: =CB6-CA6 -> 10109 | CD6: 334284 | CE6: 736908 | CF6: =CE6-CD6 -> 402624 | CG6: 860764 | CH6: 894691 | CI6: =CH6-CG6 -> 33927 | CJ6: -33927 | CK6: 0
A7: LT Heat Pumps, net billing, free capital | I7: LT Heat Pumps, net billing, free capital | J7: ASHP, PV | K7: 2: Full replacement heating | L7: LT Heat Pumps, net billing, free capital | M7: 47.85212, -122.56923 | N7: Roofspace only | O7: 8000 | P7: PSE: 25 | Q7: Net billing | R7: - | S7: 0.06713 | T7: propane | U7: 2.01 | V7: https://drive.google.com/file/d/1Xl5WOtWsJzfbC-Y8nCxkp4Y4Mozirc_L/view?usp=drive_link | W7: 2024 | X7: https://drive.google.com/file/d/12MjGV739OVxdOUym7sn516wQM4dv51MR/view?usp=drive_link | Y7: 100 | Z7: 2024 | AA7: 83.07 | AB7: 10 | AC7: 2.5 | AD7: 6 | AE7: 7.8 | AF7: 0 | AG7: - | AH7: Small Commercial | AI7: 0 | AJ7: Rooftop, Fixed | AK7: 335.4 | AL7: 10.7 | AM7: 0 | AN7: No MACRS | AO7: 0 | AP7: - | AQ7: - | AR7: - | AS7: - | AT7: - | AU7: - | AV7: - | AW7: - | AX7: - | AY7: - | AZ7: - | BA7: - | BB7: - | BC7: 0 | BD7: https://drive.google.com/file/d/1jrpu40DzxTFYY6LiD8LJLWmYTYBMVds2/view?usp=drive_link | BE7: 1 | BF7: 10 | BG7: No MACRS | BH7: 0 | BI7: LT Heat Pumps, net billing, free capital | BJ7: 80 | BK7: 35 | BL7: - | BM7: 76572 | BN7: 104535 | BO7: 0 | BP7: =BN7-BO7 -> 104535 | BQ7: 28315 | BR7: 0 | BS7: 36325 | BT7: 0 | BU7: =BQ7+BR7+BS7+BT7 -> 64640 | BV7: - | BW7: 44197 | BX7: =BP7 -> 104535 | BY7: =BX7-BW7 -> 60338 | BZ7: 0.49 | CA7: 8394 | CB7: 16530 | CC7: =CB7-CA7 -> 8136 | CD7: 101431 | CE7: 199758 | CF7: =CE7-CD7 -> 98327 | CG7: 297130 | CH7: 220558 | CI7: =CH7-CG7 -> -76572 | CJ7: 76572 | CK7: 0
A9: Peak demand: 51.0 kW
A10: LTHP Sims done 5.18.26 (Marion)
C12: Added Life Cycle Cost | D12: Year 1 Added Elec Cost | E12: Annual %
A13: LT Heat Pumps, no PV, full cost | B13: No PV, Full cost | C13: 86028 | D13: 15379 | E13: 0
A14: LT Heat Pumps, no PV, free capital | B14: No PV, NPV | C14: -9846 | D14: 15379 | E14: 0
A15: LT Heat Pumps, net metering, full cost | B15: Net metering, Full cost | C15: -74069 | D15: 5594 | E15: 0.47
A16: LT Heat Pumps, net metering, free capital | B16: Net metering, NPV | C16: -112478 | D16: 5165 | E16: 0.49
A17: LT Heat Pumps, net billing, full cost | B17: Net billing, Full cost | C17: 33927 | D17: 10109 | E17: 0.32
A18: LT Heat Pumps, net billing, free capital | B18: Net billing, NPV | C18: -76572 | D18: 8136 | E18: 0.49
C20: Added Life Cycle Cost | D20: Year 1 Added Elec Cost | E20: Annual % | F20: Life Cycle Cost
B21: Propane: Fixed Controls | F21: 860764
A22: LT Heat Pumps, no PV, full cost | B22: No PV | C22: 86028 | D22: 15379 | E22: 0 | F22: 946792
A23: LT Heat Pumps, net metering, full cost | B23: Net metering | C23: -74069 | D23: 5594 | E23: 0.47 | F23: 786695
A24: LT Heat Pumps, net billing, full cost | B24: Net billing | C24: 33927 | D24: 10109 | E24: 0.32 | F24: 894691
C26: Added Life Cycle Cost | D26: Year 1 Added Elec Cost | E26: Annual % | F26: Life Cycle Cost
B27: Fixed Controls | F27: 297130
A28: LT Heat Pumps, no PV, full cost | B28: No PV | C28: -9846 | D28: 15379 | E28: 0 | F28: 287284
A29: LT Heat Pumps, net metering, full cost | B29: Net metering | C29: -112478 | D29: 5165 | E29: 0.49 | F29: 184652
A30: LT Heat Pumps, net billing, full cost | B30: Net billing | C30: -76572 | D30: 8136 | E30: 0.49 | F30: 220558

Sheet HT Heat Pumps
A1: Scenario | B1: Neither | C1: Net metering | D1: Net billing | E1: No PV | F1: CEC & EC PV | G1: Full cost (25 year) | H1: NPV savings (10 year) | I1: REopt Results: | J1: Select Technologies to Evaluate | K1: Air-Source Heat Pump configuration | L1: Evaluation name | M1: Site location (latitude, longitude) | N1: PV & wind space available | O1: Roofspace available (sq ft) | P1: Electricity rate | Q1: Compensation type | R1: Net metering system size limit (kW) | S1: Net billing compensation for all exports ($/kWh) | T1: Existing heating system fuel type | U1: Annual existing heating system fuel cost ($/gallon) | V1: Upload typical electric load profile | W1: Year of load profile | X1: Upload typical heating load profile | Y1: Space heating load percent of total heating load (%) | Z1: Year of load profile | AA1: Existing heating system efficiency (% HHV-basis) | AB1: Analysis period (years) | AC1: Host discount rate, nominal (%) | AD1: Electricity cost escalation rate, nominal (%/year) | AE1: Existing heating system fuel cost escalation rate, nominal (%/year) | AF1: Host effective tax rate (%) | AG1: Emissions | AH1: Size class | AI1: System capital cost ($/kW-DC) | AJ1: Array type | AK1: Array azimuth (deg) | AL1: Array tilt (deg) | AM1: Federal Incentive based on percentage of cost (%) | AN1: MACRS schedule | AO1: MACRS bonus depreciation | AP1: Energy capacity cost ($/kWh) | AQ1: Power capacity cost ($/kW) | AR1: Constant cost ($) | AS1: Minimum energy capacity (kWh) | AT1: Maximum energy capacity (kWh) | AU1: Energy capacity replacement cost ($/kWh) | AV1: Power capacity replacement cost ($/kWh) | AW1: Constant replacement cost ($) | AX1: Minimum power capacity (kW) | AY1: Maximum power capacity (kW) | AZ1: Federal Incentive based on percentage of cost (%) | BA1: MACRS schedule | BB1: MACRS bonus depreciation | BC1: Total installed cost ($/ton) | BD1: Upload COP Table | BE1: Heat pump capacity sizing factor | BF1: Resistive heating back-up temperature threshold (°F) | BG1: MACRS schedule | BH1: MACRS bonus depreciation | BI1: REopt Results: | BJ1: Optimized PV size (kW) | BK1: Optimized ASHP size (tonnes) | BL1: Potential Life Cycle Savings | BM1: Avg. Annual Grid Serving Load (kWh) | BN1: Avg. Annual Grid Charging Battery (kWh) | BO1: Avg. Annual Grid Total Electricity Consumed (kWh) | BP1: Avg. Annual PV Serving Load (kWh) | BQ1: Avg. Annual PV Charging Battery (kWh) | BR1: Avg. Annual PV Exported to Grid (kWh) | BS1: Avg. Annual PV Curtailment (kWh) | BT1: Avg. Annual PV Total Electricity Produced (kWh) | BU1: Avg. Annual Battery Serving Load (kWh) | BV1: BAU Average Annual Energy Supplied from Grid (kWh) | BW1: System Average Annual Energy Supplied from Grid (kWh) | BX1: Difference in Avg. Annual Energy Supplied from Grid | BY1: w/PV Annual Renewable Electricity (% of electricity consumed) | BZ1: BAU Total Year 1 Elec Cost - Pre-Tax | CA1: Total Year 1 Elec Cost - Pre-Tax | CB1: Difference Total Year 1 Elec Cost | CC1: BAU Total Full Period Elec Cost | CD1: Optimized Total Full Period Elec Cost | CE1: Difference in Full Period Utility Cost | CF1: BAUTotal Life Cycle Costs | CG1: Total Life Cycle Costs | CI1: Net Present Value | CJ1: Payback Period for PV /Battery (yrs)
A2: HT Heat Pumps, no PV, full cost | I2: HT Heat Pumps, no PV, full cost | REopt Web Tool | REopt Energy Integration & Optimization | NLR | J2: ASHP | K2: 2: Full replacement heating | L2: HT Heat Pumps, no PV, full cost | M2: 47.85212, -122.56923 | N2: Roofspace only | O2: 8000 | P2: PSE: 25 | Q2: N/A | R2: - | S2: - | T2: propane | U2: 2.01 | V2: https://drive.google.com/file/d/1Xl5WOtWsJzfbC-Y8nCxkp4Y4Mozirc_L/view?usp=drive_link | W2: 2024 | X2: https://drive.google.com/file/d/12MjGV739OVxdOUym7sn516wQM4dv51MR/view?usp=drive_link | Y2: 100 | Z2: 2024 | AA2: 83.07 | AB2: 25 | AC2: 2.5 | AD2: 6 | AE2: 7.8 | AF2: 0 | AG2: - | AH2: - | AI2: - | AJ2: - | AK2: - | AL2: - | AM2: - | AN2: - | AO2: - | AP2: - | AQ2: - | AR2: - | AS2: - | AT2: - | AU2: - | AV2: - | AW2: - | AX2: - | AY2: - | AZ2: - | BA2: - | BB2: - | BC2: 0 | BD2: https://drive.google.com/file/d/16UAUdtQOC8qioWbnM096MsZ4fLvZ1Viy/view?usp=drive_link | BE2: 1 | BF2: 30 | BG2: No MACRS | BH2: 0 | BI2: HT Heat Pumps, no PV, full cost | REopt Web Tool | REopt Energy Integration & Optimization | NLR | BJ2: 0 | BK2: 38 | BL2: -322823 | BM2: 166778 | BN2: 0 | BO2: 166778 | BP2: 0 | BQ2: 0 | BR2: 0 | BS2: 0 | BT2: 0 | BU2: 0 | BV2: 44197 | BW2: 166778 | BX2: 122581 | BY2: 0 | BZ2: 8394 | CA2: 29719 | CB2: 21326 | CC2: 334284 | CD2: 1183586 | CE2: 849302 | CF2: 860764 | CG2: 1183586 | CH2: =-1*CI2 -> 322822 | CI2: =CF2-CG2 -> -322822
A3: HT Heat Pumps, no PV, free capital | I3: HT Heat Pumps, no PV, free capital | REopt Web Tool | REopt Energy Integration & Optimization | NLR | J3: ASHP | K3: 2: Full replacement heating | L3: HT Heat Pumps, no PV, free capital | M3: 47.85212, -122.56923 | N3: Roofspace only | O3: 8000 | P3: PSE: 25 | Q3: N/A | R3: - | S3: - | T3: propane | U3: 2.01 | V3: https://drive.google.com/file/d/1Xl5WOtWsJzfbC-Y8nCxkp4Y4Mozirc_L/view?usp=drive_link | W3: 2024 | X3: https://drive.google.com/file/d/12MjGV739OVxdOUym7sn516wQM4dv51MR/view?usp=drive_link | Y3: 100 | Z3: 2024 | AA3: 83.07 | AB3: 10 | AC3: 2.5 | AD3: 6 | AE3: 7.8 | AF3: 0 | AG3: - | AH3: - | AI3: - | AJ3: - | AK3: - | AL3: - | AM3: - | AN3: - | AO3: - | AP3: - | AQ3: - | AR3: - | AS3: - | AT3: - | AU3: - | AV3: - | AW3: - | AX3: - | AY3: - | AZ3: - | BA3: - | BB3: - | BC3: 0 | BD3: https://drive.google.com/file/d/16UAUdtQOC8qioWbnM096MsZ4fLvZ1Viy/view?usp=drive_link | BE3: 1 | BF3: 30 | BG3: No MACRS | BH3: 0 | BI3: HT Heat Pumps, no PV, free capital | REopt Web Tool | REopt Energy Integration & Optimization | NLR | BJ3: 0 | BK3: 38 | BL3: -62004 | BM3: 166778 | BN3: 0 | BO3: 166778 | BP3: 0 | BQ3: 0 | BR3: 0 | BS3: 0 | BT3: 0 | BU3: 0 | BV3: 44197 | BW3: 166778 | BX3: 122581 | BY3: 0 | BZ3: 8394 | CA3: 29719 | CB3: =CA3-BZ3 -> 21325 | CC3: 101431 | CD3: 359134 | CE3: 257703 | CF3: 297130 | CG3: 359134 | CH3: =-1*CI3 -> 62004 | CI3: =CF3-CG3 -> -62004
A4: HT Heat Pumps, net metering, full cost | I4: HT Heat Pumps, net metering, Full cost | REopt Web Tool | REopt Energy Integration & Optimization | NLR | J4: ASHP, PV | K4: 2: Full replacement heating | L4: HT Heat Pumps, net metering, full cost | M4: 47.85212, -122.56923 | N4: Roofspace only | O4: 8000 | P4: PSE: 25 | Q4: Net metering | R4: 100 | S4: - | T4: propane | U4: 2.01 | V4: https://drive.google.com/file/d/1Xl5WOtWsJzfbC-Y8nCxkp4Y4Mozirc_L/view?usp=drive_link | W4: 2024 | X4: https://drive.google.com/file/d/12MjGV739OVxdOUym7sn516wQM4dv51MR/view?usp=drive_link | Y4: 100 | Z4: 2024 | AA4: 83.07 | AB4: 25 | AC4: 2.5 | AD4: 6 | AE4: 7.8 | AF4: 0 | AG4: - | AH4: Small Commercial | AI4: 2220 | AJ4: Rooftop, Fixed | AK4: 335.4 | AL4: 10.7 | AM4: 0 | AN4: No MACRS | AO4: 0 | AP4: - | AQ4: - | AR4: - | AS4: - | AT4: - | AU4: - | AV4: - | AW4: - | AX4: - | AY4: - | AZ4: - | BA4: - | BB4: - | BC4: 0 | BD4: https://drive.google.com/file/d/16UAUdtQOC8qioWbnM096MsZ4fLvZ1Viy/view?usp=drive_link | BE4: 1 | BF4: 30 | BG4: No MACRS | BH4: 0 | BI4: HT Heat Pumps, net metering, Full cost | REopt Web Tool | REopt Energy Integration & Optimization | NLR | BJ4: 80 | BK4: 38 | BL4: -165234 | BM4: 136956 | BN4: 0 | BO4: 136956 | BP4: 29822 | BQ4: 0 | BR4: 32016 | BS4: 0 | BT4: 61838 | BU4: 0 | BV4: 44197 | BW4: 136956 | BX4: =BW4-BV4 -> 92759 | BY4: 0.37 | BZ4: 8394 | CA4: 19997 | CB4: 11603 | CC4: 334284 | CD4: 796398 | CE4: 462113 | CF4: 860764 | CG4: 1025998 | CH4: =-1*CI4 -> 165234 | CI4: =CF4-CG4 -> -165234
A5: HT Heat Pumps, net metering, free capital | I5: HT Heat Pumps, net metering, free capital | REopt Web Tool | REopt Energy Integration & Optimization | NLR | J5: ASHP, PV | K5: 2: Full replacement heating | L5: HT Heat Pumps, net metering, free capital | M5: 47.85212, -122.56923 | N5: Roofspace only | O5: 8000 | P5: PSE: 25 | Q5: Net metering | R5: 100 | S5: - | T5: propane | U5: 2.01 | V5: https://drive.google.com/file/d/1Xl5WOtWsJzfbC-Y8nCxkp4Y4Mozirc_L/view?usp=drive_link | W5: 2024 | X5: https://drive.google.com/file/d/12MjGV739OVxdOUym7sn516wQM4dv51MR/view?usp=drive_link | Y5: 100 | Z5: 2024 | AA5: 83.07 | AB5: 10 | AC5: 2.5 | AD5: 6 | AE5: 7.8 | AF5: 0 | AG5: - | AH5: Small Commercial | AI5: 0 | AJ5: Rooftop, Fixed | AK5: 335.4 | AL5: 10.7 | AM5: 0 | AN5: No MACRS | AO5: 0 | AP5: - | AQ5: - | AR5: - | AS5: - | AT5: - | AU5: - | AV5: - | AW5: - | AX5: - | AY5: - | AZ5: - | BA5: - | BB5: - | BC5: 0 | BD5: https://drive.google.com/file/d/16UAUdtQOC8qioWbnM096MsZ4fLvZ1Viy/view?usp=drive_link | BE5: 1 | BF5: 30 | BG5: No MACRS | BH5: 0 | BI5: HT Heat Pumps, net metering, free capital | REopt Web Tool | REopt Energy Integration & Optimization | NLR | BJ5: 80 | BK5: 38 | BL5: 39866 | BM5: 136352 | BN5: 0 | BO5: 136352 | BP5: 30426 | BQ5: 0 | BR5: 34215 | BS5: 0 | BT5: 64641 | BU5: 0 | BV5: 44197 | BW5: 136352 | BX5: =BW5-BV5 -> 92155 | BY5: 0.39 | BZ5: 8394 | CA5: 19568 | CB5: =CA5-BZ5 -> 11174 | CC5: 101431 | CD5: 236464 | CE5: =CD5-CC5 -> 135033 | CF5: 297130 | CG5: 257264 | CH5: =-1*CI5 -> -39866 | CI5: =CF5-CG5 -> 39866
A6: HT Heat Pumps, net billing, full cost | I6: HT Heat Pumps, net billing, full cost | REopt Web Tool | REopt Energy Integration & Optimization | NLR | J6: ASHP, PV | K6: 2: Full replacement heating | L6: HT Heat Pumps, net billing, full cost | M6: 47.85212, -122.56923 | N6: Roofspace only | O6: 8000 | P6: PSE: 25 | Q6: Net billing | R6: - | S6: 0.06713 | T6: propane | U6: 2.01 | V6: https://drive.google.com/file/d/1Xl5WOtWsJzfbC-Y8nCxkp4Y4Mozirc_L/view?usp=drive_link | W6: 2024 | X6: https://drive.google.com/file/d/12MjGV739OVxdOUym7sn516wQM4dv51MR/view?usp=drive_link | Y6: 100 | Z6: 2024 | AA6: 83.07 | AB6: 25 | AC6: 2.5 | AD6: 6 | AE6: 7.8 | AF6: 0 | AG6: - | AH6: Small Commercial | AI6: 2220 | AJ6: Rooftop, Fixed | AK6: 335.4 | AL6: 10.7 | AM6: 0 | AN6: No MACRS | AO6: 0 | AP6: - | AQ6: - | AR6: - | AS6: - | AT6: - | AU6: - | AV6: - | AW6: - | AX6: - | AY6: - | AZ6: - | BA6: - | BB6: - | BC6: 0 | BD6: https://drive.google.com/file/d/16UAUdtQOC8qioWbnM096MsZ4fLvZ1Viy/view?usp=drive_link | BE6: 1 | BF6: 30 | BG6: No MACRS | BH6: 0 | BI6: HT Heat Pumps, net billing, full cost | REopt Web Tool | REopt Energy Integration & Optimization | NLR | BJ6: 66 | BK6: 38 | BL6: -268592 | BM6: 139510 | BN6: 0 | BO6: =BM6 -> 139510 | BP6: 27268 | BQ6: 0 | BR6: 23752 | BS6: 0 | BT6: 51020 | BU6: 0 | BV6: 44197 | BW6: 139510 | BX6: =BW6-BV6 -> 95313 | BY6: 0.31 | BZ6: 8394 | CA6: 23601 | CB6: =CA6-BZ6 -> 15207 | CC6: 334284 | CD6: 939924 | CE6: =CD6-CC6 -> 605640 | CF6: 860764 | CG6: 1129356 | CH6: =-1*CI6 -> 268592 | CI6: =CF6-CG6 -> -268592
A7: HT Heat Pumps, net billing, free capital | I7: HT Heat Pumps, net billing, free capital | REopt Web Tool | REopt Energy Integration & Optimization | NLR | J7: ASHP, PV | K7: 2: Full replacement heating | L7: HT Heat Pumps, net billing, free capital | M7: 47.85212, -122.56923 | N7: Roofspace only | O7: 8000 | P7: PSE: 25 | Q7: Net billing | R7: - | S7: 0.06713 | T7: propane | U7: 2.01 | V7: https://drive.google.com/file/d/1Xl5WOtWsJzfbC-Y8nCxkp4Y4Mozirc_L/view?usp=drive_link | W7: 2024 | X7: https://drive.google.com/file/d/12MjGV739OVxdOUym7sn516wQM4dv51MR/view?usp=drive_link | Y7: 100 | Z7: 2024 | AA7: 83.07 | AB7: 10 | AC7: 2.5 | AD7: 6 | AE7: 7.8 | AF7: 0 | AG7: - | AH7: Small Commercial | AI7: 0 | AJ7: Rooftop, Fixed | AK7: 335.4 | AL7: 10.7 | AM7: 0 | AN7: No MACRS | AO7: 0 | AP7: - | AQ7: - | AR7: - | AS7: - | AT7: - | AU7: - | AV7: - | AW7: - | AX7: - | AY7: - | AZ7: - | BA7: - | BB7: - | BC7: 0 | BD7: https://drive.google.com/file/d/16UAUdtQOC8qioWbnM096MsZ4fLvZ1Viy/view?usp=drive_link | BE7: 1 | BF7: 30 | BG7: No MACRS | BH7: 0 | BI7: HT Heat Pumps, net billing, free capital | REopt Web Tool | REopt Energy Integration & Optimization | NLR | BJ7: 80 | BK7: 38 | BL7: 6047 | BM7: 136352 | BN7: 0 | BO7: 136352 | BP7: 30426 | BQ7: 0 | BR7: 34215 | BS7: 0 | BT7: 64641 | BU7: 0 | BV7: 44197 | BW7: 136352 | BX7: =BW7-BV7 -> 92155 | BY7: 0.39 | BZ7: 8394 | CA7: 22366 | CB7: =CA7-BZ7 -> 13972 | CC7: 101431 | CD7: 270283 | CE7: =CD7-CC7 -> 168852 | CF7: 297130 | CG7: 291084 | CH7: =-1*CI7 -> -6046 | CI7: =CF7-CG7 -> 6046
A9: Peak demand: 66.9 kW

Sheet Electric Boiler
A1: Scenario | B1: Neither | C1: Net metering | D1: Net billing | E1: No PV | F1: CEC & EC PV | G1: Full cost (25 year) | H1: NPV savings (10 year) | I1: REopt Results: | J1: Select Technologies to Evaluate | K1: Air-Source Heat Pump configuration | L1: Evaluation name | M1: Site location (latitude, longitude) | N1: PV & wind space available | O1: Roofspace available (sq ft) | P1: Electricity rate | Q1: Compensation type | R1: Net metering system size limit (kW) | S1: Net billing compensation for all exports ($/kWh) | T1: Existing heating system fuel type | U1: Annual existing heating system fuel cost ($/gallon) | V1: Upload typical electric load profile | W1: Year of load profile | X1: Upload typical heating load profile | Y1: Space heating load percent of total heating load (%) | Z1: Year of load profile | AA1: Existing heating system efficiency (% HHV-basis) | AB1: Analysis period (years) | AC1: Host discount rate, nominal (%) | AD1: Electricity cost escalation rate, nominal (%/year) | AE1: Existing heating system fuel cost escalation rate, nominal (%/year) | AF1: Host effective tax rate (%) | AG1: Emissions | AH1: Size class | AI1: System capital cost ($/kW-DC) | AJ1: Array type | AK1: Array azimuth (deg) | AL1: Array tilt (deg) | AM1: Federal Incentive based on percentage of cost (%) | AN1: MACRS schedule | AO1: MACRS bonus depreciation | AP1: Energy capacity cost ($/kWh) | AQ1: Power capacity cost ($/kW) | AR1: Constant cost ($) | AS1: Minimum energy capacity (kWh) | AT1: Maximum energy capacity (kWh) | AU1: Energy capacity replacement cost ($/kWh) | AV1: Power capacity replacement cost ($/kWh) | AW1: Constant replacement cost ($) | AX1: Minimum power capacity (kW) | AY1: Maximum power capacity (kW) | AZ1: Federal Incentive based on percentage of cost (%) | BA1: MACRS schedule | BB1: MACRS bonus depreciation | BC1: Total installed cost ($/ton) | BD1: Upload COP Table | BE1: Heat pump capacity sizing factor | BF1: Resistive heating back-up temperature threshold (°F) | BG1: MACRS schedule | BH1: MACRS bonus depreciation | BI1: REopt Results: | BJ1: Optimized PV size (kW) | BK1: Optimized ASHP size (tonnes) | BL1: Optimized Battery Power and Capacity (kW/kWh) | BM1: Potential Life Cycle Savings | BN1: Avg. Annual Grid Serving Load (kWh) | BO1: Avg. Annual Grid Charging Battery (kWh) | BP1: Avg. Annual Grid Total Electricity Consumed (kWh) | BQ1: Avg. Annual PV Serving Load (kWh) | BR1: Avg. Annual PV Charging Battery (kWh) | BS1: Avg. Annual PV Exported to Grid (kWh) | BT1: Avg. Annual PV Curtailment (kWh) | BU1: Avg. Annual PV Total Electricity Produced (kWh) | BV1: Avg. Annual Battery Serving Load (kWh) | BW1: BAU Average Annual Energy Supplied from Grid (kWh) | BX1: New System Average Annual Energy Supplied from Grid (kWh) | BY1: Difference in Avg. Annual Energy Supplied from Grid | BZ1: Annual Renewable Electricity (% of electricity consumed) | CA1: Avoided CO2e Emissions throughout Analysis Period | CB1: BAU Total Year 1 Elec Cost - Pre-Tax | CC1: New Total Year 1 Elec Cost - Pre-Tax | CD1: Difference Total Year 1 Elec Cost | CE1: BAU Total Full Period Elec Cost | CF1: New Total Full Period Elec Cost | CG1: Difference in Full Period Utility Cost | CH1: BAU Total Life Cycle Costs | CI1: New Total Life Cycle Costs | CJ1: Difference in Total life cycle costs | CK1: New System Net Present Value | CL1: Payback Period for PV/ASHP (yrs)
A2: Electric Boiler, no PV, full cost | I2: Electric Boiler, no PV, full cost | REopt Web Tool | REopt Energy | J2: ASHP | K2: 2: Full replacement heating | L2: Electric Boiler, no PV, full cost | M2: 47.85212, -122.56923 | N2: Roofspace only | O2: 8000 | P2: PSE: 25 | Q2: N/A | R2: - | S2: - | T2: propane | U2: 2.01 | V2: https://drive.google.com/file/d/1Xl5WOtWsJzfbC-Y8nCxkp4Y4Mozirc_L/view?usp=drive_link | W2: 2024 | X2: https://drive.google.com/file/d/12MjGV739OVxdOUym7sn516wQM4dv51MR/view?usp=drive_link | Y2: 100 | Z2: 2024 | AA2: 83.07 | AB2: 25 | AC2: 2.5 | AD2: 6 | AE2: 7.8 | AF2: 0 | AG2: - | AH2: - | AI2: - | AJ2: - | AK2: - | AL2: - | AM2: - | AN2: - | AO2: - | AP2: - | AQ2: - | AR2: - | AS2: - | AT2: - | AU2: - | AV2: - | AW2: - | AX2: - | AY2: - | AZ2: - | BA2: - | BB2: - | BC2: 0 | BD2: https://drive.google.com/file/d/1ierMR5pp-9e4Oh1RndrdR-TIpi-DdJ91/view?usp=drive_link | BE2: 1 | BF2: 10 | BG2: No MACRS | BH2: 0 | BI2: Electric Boiler, no PV, full cost | REopt Web Tool | REopt Energy | BJ2: - | BK2: 26 | BL2: - | BM2: -913453 | BN2: - | BO2: - | BP2: - | BQ2: - | BR2: - | BS2: - | BT2: - | BU2: - | BV2: - | BW2: 44197 | BX2: 249593 | BY2: 205396 | BZ2: 0 | CA2: 1137 | CB2: 8394 | CC2: 44550 | CD2: 36156 | CE2: 334284 | CF2: 1774216 | CG2: 1439932 | CH2: 860764 | CI2: 1774216 | CJ2: 913453 | CK2: -913453 | CL2: 0
A3: Electric Boiler, no PV, free capital | I3: Electric Boiler, no PV, free capital | REopt Web Tool | REopt Energy | J3: ASHP | K3: 2: Full replacement heating | L3: Electric Boiler, no PV, free capital | M3: 47.85212, -122.56923 | N3: Roofspace only | O3: 8000 | P3: PSE: 25 | Q3: N/A | R3: - | S3: - | T3: propane | U3: 2.01 | V3: https://drive.google.com/file/d/1Xl5WOtWsJzfbC-Y8nCxkp4Y4Mozirc_L/view?usp=drive_link | W3: 2024 | X3: https://drive.google.com/file/d/12MjGV739OVxdOUym7sn516wQM4dv51MR/view?usp=drive_link | Y3: 100 | Z3: 2024 | AA3: 83.07 | AB3: 10 | AC3: 2.5 | AD3: 6 | AE3: 7.8 | AF3: 0 | AG3: - | AH3: - | AI3: - | AJ3: - | AK3: - | AL3: - | AM3: - | AN3: - | AO3: - | AP3: - | AQ3: - | AR3: - | AS3: - | AT3: - | AU3: - | AV3: - | AW3: - | AX3: - | AY3: - | AZ3: - | BA3: - | BB3: - | BC3: 0 | BD3: https://drive.google.com/file/d/1ierMR5pp-9e4Oh1RndrdR-TIpi-DdJ91/view?usp=drive_link | BE3: 1 | BF3: 10 | BG3: No MACRS | BH3: 0 | BI3: Electric Boiler, no PV, free capital | REopt Web Tool | REopt Energy | BJ3: - | BK3: 26 | BL3: - | BM3: -241218 | BN3: - | BO3: - | BP3: - | BQ3: - | BR3: - | BS3: - | BT3: - | BU3: - | BV3: - | BW3: 44197 | BX3: 249593 | BY3: 205396 | BZ3: 0 | CA3: 434 | CB3: 8394 | CC3: 44550 | CD3: 36156 | CE3: 101431 | CF3: 538348 | CG3: 436917 | CH3: 297130 | CI3: 538348 | CJ3: 241218 | CK3: -241218 | CL3: 0
A4: Electric Boiler, net metering, full cost | I4: Electric Boiler, net metering, full cost | REopt Web Tool | REopt Energy | J4: ASHP, PV | K4: 2: Full replacement heating | L4: Electric Boiler, net metering, full cost | M4: 47.85212, -122.56923 | N4: Roofspace only | O4: 8000 | P4: PSE: 25 | Q4: Net metering | R4: 100 | S4: - | T4: propane | U4: 2.01 | V4: https://drive.google.com/file/d/1Xl5WOtWsJzfbC-Y8nCxkp4Y4Mozirc_L/view?usp=drive_link | W4: 2024 | X4: https://drive.google.com/file/d/12MjGV739OVxdOUym7sn516wQM4dv51MR/view?usp=drive_link | Y4: 100 | Z4: 2024 | AA4: 83.07 | AB4: 25 | AC4: 2.5 | AD4: 6 | AE4: 7.8 | AF4: 0 | AG4: - | AH4: Small Commercial | AI4: 2220 | AJ4: Rooftop, Fixed | AK4: 335.4 | AL4: 10.7 | AM4: 0 | AN4: No MACRS | AO4: 0 | AP4: - | AQ4: - | AR4: - | AS4: - | AT4: - | AU4: - | AV4: - | AW4: - | AX4: - | AY4: - | AZ4: - | BA4: - | BB4: - | BC4: 0 | BD4: https://drive.google.com/file/d/1ierMR5pp-9e4Oh1RndrdR-TIpi-DdJ91/view?usp=drive_link | BE4: 1 | BF4: 10 | BG4: No MACRS | BH4: 0 | BI4: Electric Boiler, net metering, full cost | REopt Web Tool | REopt Energy | BJ4: 80 | BK4: 26 | BL4: - | BM4: -760007 | BN4: 216069 | BO4: - | BP4: 216069 | BQ4: 33524 | BR4: - | BS4: 28314 | BT4: 0 | BU4: 61838 | BV4: - | BW4: 44197 | BX4: 216069 | BY4: 171872 | BZ4: 0.25 | CA4: 1182 | CB4: 8394 | CC4: 34931 | CD4: 26538 | CE4: 334284 | CF4: 1391171 | CG4: 1056887 | CH4: 860764 | CI4: 1620771 | CJ4: 760007 | CK4: -760007 | CL4: 0
A5: Electric Boiler, net metering, free capital | I5: Electric Boiler, net metering, free capital | REopt Web Tool | REopt Energy Integration & Optimization | NLR | J5: ASHP, PV | K5: 2: Full replacement heating | L5: Electric Boiler, net metering, free capital | M5: 47.85212, -122.56923 | N5: Roofspace only | O5: 8000 | P5: PSE: 25 | Q5: Net metering | R5: 100 | S5: - | T5: propane | U5: 2.01 | V5: https://drive.google.com/file/d/1Xl5WOtWsJzfbC-Y8nCxkp4Y4Mozirc_L/view?usp=drive_link | W5: 2024 | X5: https://drive.google.com/file/d/12MjGV739OVxdOUym7sn516wQM4dv51MR/view?usp=drive_link | Y5: 100 | Z5: 2024 | AA5: 83.07 | AB5: 10 | AC5: 2.5 | AD5: 6 | AE5: 7.8 | AF5: 0 | AG5: - | AH5: Small Commercial | AI5: 0 | AJ5: Rooftop, Fixed | AK5: 335.4 | AL5: 10.7 | AM5: 0 | AN5: No MACRS | AO5: 0 | AP5: - | AQ5: - | AR5: - | AS5: - | AT5: - | AU5: - | AV5: - | AW5: - | AX5: - | AY5: - | AZ5: - | BA5: - | BB5: - | BC5: 0 | BD5: https://drive.google.com/file/d/1ierMR5pp-9e4Oh1RndrdR-TIpi-DdJ91/view?usp=drive_link | BE5: 1 | BF5: 10 | BG5: No MACRS | BH5: 0 | BI5: Electric Boiler, net metering, free capital | REopt Web Tool | REopt Energy Integration & Optimization | NLR | BJ5: 80 | BK5: 26 | BL5: - | BM5: -140615 | BN5: 215242 | BO5: - | BP5: 215242 | BQ5: 34351 | BR5: - | BS5: 30289 | BT5: 0 | BU5: 64641 | BV5: - | BW5: 44197 | BX5: 215242 | BY5: 171045 | BZ5: 0.26 | CA5: 470 | CB5: 8394 | CC5: 34503 | CD5: 26109 | CE5: 101431 | CF5: 416945 | CG5: 315514 | CH5: 297130 | CI5: 437745 | CJ5: 140615 | CK5: -140615 | CL5: 0
A6: Electric Boiler, net billing, full cost | I6: Electric Boiler, net billing, full cost | REopt Web Tool | REopt Energy Integration & Optimization | NLR | J6: ASHP, PV | K6: 2: Full replacement heating | L6: Electric Boiler, net billing, full cost | M6: 47.85212, -122.56923 | N6: Roofspace only | O6: 8000 | P6: PSE: 25 | Q6: Net billing | R6: - | S6: 0.06713 | T6: propane | U6: 2.01 | V6: https://drive.google.com/file/d/1Xl5WOtWsJzfbC-Y8nCxkp4Y4Mozirc_L/view?usp=drive_link | W6: 2024 | X6: https://drive.google.com/file/d/12MjGV739OVxdOUym7sn516wQM4dv51MR/view?usp=drive_link | Y6: 100 | Z6: 2024 | AA6: 83.07 | AB6: 25 | AC6: 2.5 | AD6: 6 | AE6: 7.8 | AF6: 0 | AG6: - | AH6: Small Commercial | AI6: 2220 | AJ6: Rooftop, Fixed | AK6: 335.4 | AL6: 10.7 | AM6: 0 | AN6: No MACRS | AO6: 0 | AP6: - | AQ6: - | AR6: - | AS6: - | AT6: - | AU6: - | AV6: - | AW6: - | AX6: - | AY6: - | AZ6: - | BA6: - | BB6: - | BC6: 0 | BD6: https://drive.google.com/file/d/1ierMR5pp-9e4Oh1RndrdR-TIpi-DdJ91/view?usp=drive_link | BE6: 1 | BF6: 10 | BG6: No MACRS | BH6: 0 | BI6: Electric Boiler, net billing, full cost | REopt Web Tool | REopt Energy Integration & Optimization | NLR | BJ6: 80 | BK6: 26 | BL6: - | BM6: -852242 | BN6: 216069 | BO6: - | BP6: 216069 | BQ6: 33524 | BR6: - | BS6: 28314 | BT6: 0 | BU6: 61838 | BV6: - | BW6: 44197 | BX6: 216069 | BY6: 171872 | BZ6: 0.25 | CA6: 1182 | CB6: 8394 | CC6: 37247 | CD6: 28854 | CE6: 334284 | CF6: 1483406 | CG6: 1149122 | CH6: 860764 | CI6: 1713006 | CJ6: 852242 | CK6: -852242 | CL6: 0
A7: Electric Boiler, net billing, free capital | I7: Electric Boiler, net billing, free capital | REopt Web Tool | REopt Energy Integration & Optimization | NLR | J7: ASHP, PV | K7: 2: Full replacement heating | L7: Electric Boiler, net billing, free capital | M7: 47.85212, -122.56923 | N7: Roofspace only | O7: 8000 | P7: PSE: 25 | Q7: Net billing | R7: - | S7: 0.06713 | T7: propane | U7: 2.01 | V7: https://drive.google.com/file/d/1Xl5WOtWsJzfbC-Y8nCxkp4Y4Mozirc_L/view?usp=drive_link | W7: 2024 | X7: https://drive.google.com/file/d/12MjGV739OVxdOUym7sn516wQM4dv51MR/view?usp=drive_link | Y7: 100 | Z7: 2024 | AA7: 83.07 | AB7: 10 | AC7: 2.5 | AD7: 6 | AE7: 7.8 | AF7: 0 | AG7: - | AH7: Small Commercial | AI7: 0 | AJ7: Rooftop, Fixed | AK7: 335.4 | AL7: 10.7 | AM7: 0 | AN7: No MACRS | AO7: 0 | AP7: - | AQ7: - | AR7: - | AS7: - | AT7: - | AU7: - | AV7: - | AW7: - | AX7: - | AY7: - | AZ7: - | BA7: - | BB7: - | BC7: 0 | BD7: https://drive.google.com/file/d/1ierMR5pp-9e4Oh1RndrdR-TIpi-DdJ91/view?usp=drive_link | BE7: 1 | BF7: 10 | BG7: No MACRS | BH7: 0 | BI7: Electric Boiler, net billing, free capital | REopt Web Tool | REopt Energy Integration & Optimization | NLR | BJ7: 80 | BK7: 26 | BL7: - | BM7: -170554 | BN7: 215242 | BO7: - | BP7: 215242 | BQ7: 34351 | BR7: - | BS7: 30289 | BT7: 0 | BU7: 64641 | BV7: - | BW7: 44197 | BX7: 215242 | BY7: 171045 | BZ7: 0.26 | CA7: 470 | CB7: 8394 | CC7: 36981 | CD7: 28587 | CE7: 101431 | CF7: 446884 | CG7: 345453 | CH7: 297130 | CI7: 467684 | CJ7: 170554 | CK7: -170554 | CL7: 0
A9: Peak demand: 100.5 kW
C11: Added Life Cycle Cost | D11: Year 1 Added Elec Cost | E11: Annual %
A12: Electric Boiler, no PV, full cost | B12: No PV, Full cost | C12: 913453 | D12: 36156 | E12: 0
A13: Electric Boiler, no PV, free capital | B13: No PV, NPV | C13: 241218 | D13: 36156 | E13: 0
A14: Electric Boiler, net metering, full cost | B14: Net metering, Full cost | C14: 760007 | D14: 26538 | E14: 0.25
A15: Electric Boiler, net billing, full cost | B15: Net billing, Full cost | C15: 852242 | D15: 28854 | E15: 0.25
A16: Electric Boiler, net billing, free capital | B16: Net billing, NPV | C16: 170554 | D16: 28587 | E16: 0.26
C18: Added Life Cycle Cost | D18: Year 1 Added Elec Cost | E18: Annual % | F18: Full Life Cycle Cost
A19: Electric Boiler, no PV, full cost | B19: No PV | C19: 913453 | D19: 36156 | E19: 0
A20: Electric Boiler, net metering, full cost | B20: Net metering | C20: 760007 | D20: 26538 | E20: 0.25
A21: Electric Boiler, net billing, full cost | B21: Net billing | C21: 852242 | D21: 28854 | E21: 0.25
C23: Added Life Cycle Cost | D23: Year 1 Added Elec Cost | E23: Annual %
A24: Electric Boiler, no PV, full cost | B24: No PV | C24: 241218 | D24: 36156 | E24: 0
A25: Electric Boiler, net metering, full cost | B25: Net metering | C25: 140615 | D25: 26109 | E25: 0.26
A26: Electric Boiler, net billing, full cost | B26: Net billing | C26: 170554 | D26: 28587 | E26: 0.26

Sheet LT Heat Pumps with Battery
A1: Scenario | B1: 1-hour Battery | C1: 2-hour Battery | D1: 4-hour Battery | E1: Net metering | F1: Net billing | G1: Full cost (25 year) | H1: NPV savings (10 year) | I1: REopt Results: | J1: Select Technologies to Evaluate | K1: Air-Source Heat Pump configuration | L1: Evaluation name | M1: Site location (latitude, longitude) | N1: PV & wind space available | O1: Roofspace available (sq ft) | P1: Electricity rate | Q1: Compensation type | R1: Net metering system size limit (kW) | S1: Net billing compensation for all exports ($/kWh) | T1: Existing heating system fuel type | U1: Annual existing heating system fuel cost ($/gallon) | V1: Upload typical electric load profile | W1: Year of load profile | X1: Upload typical heating load profile | Y1: Space heating load percent of total heating load (%) | Z1: Year of load profile | AA1: Existing heating system efficiency (% HHV-basis) | AB1: Analysis period (years) | AC1: Host discount rate, nominal (%) | AD1: Electricity cost escalation rate, nominal (%/year) | AE1: Existing heating system fuel cost escalation rate, nominal (%/year) | AF1: Host effective tax rate (%) | AG1: Emissions | AH1: Size class | AI1: System capital cost ($/kW-DC) | AJ1: Array type | AK1: Array azimuth (deg) | AL1: Array tilt (deg) | AM1: Federal Incentive based on percentage of cost (%) | AN1: MACRS schedule | AO1: MACRS bonus depreciation | AP1: Energy capacity cost ($/kWh) | AQ1: Power capacity cost ($/kW) | AR1: Constant cost ($) | AS1: Minimum energy capacity (kWh) | AT1: Maximum energy capacity (kWh) | AU1: Energy capacity replacement cost ($/kWh) | AV1: Power capacity replacement cost ($/kWh) | AW1: Constant replacement cost ($) | AX1: Minimum power capacity (kW) | AY1: Maximum power capacity (kW) | AZ1: Federal Incentive based on percentage of cost (%) | BA1: MACRS schedule | BB1: MACRS bonus depreciation | BC1: Total installed cost ($/ton) | BD1: Upload COP Table | BE1: Heat pump capacity sizing factor | BF1: Resistive heating back-up temperature threshold (°F) | BG1: MACRS schedule | BH1: MACRS bonus depreciation | BI1: REopt Results: | BJ1: Optimized PV size (kW) | BK1: Optimized ASHP size (tonnes) | BL1: Optimized Battery Power and Capacity (kW/kWh) | BM1: Potential Life Cycle Savings | BN1: Avg. Annual Grid Serving Load (kWh) | BO1: Avg. Annual Grid Charging Battery (kWh) | BP1: Avg. Annual Grid Total Electricity Consumed (kWh) | BQ1: Avg. Annual PV Serving Load (kWh) | BR1: Avg. Annual PV Charging Battery (kWh) | BS1: Avg. Annual PV Exported to Grid (kWh) | BT1: Avg. Annual PV Curtailment (kWh) | BU1: Avg. Annual PV Total Electricity Produced (kWh) | BV1: Avg. Annual Battery Serving Load (kWh) | BW1: BAU Average Annual Energy Supplied from Grid (kWh) | BX1: New System Average Annual Energy Supplied from Grid (kWh) | BY1: Difference in Avg. Annual Energy Supplied from Grid | BZ1: BAU Annual Renewable Electricity (% of electricity consumed) | CA1: Avoided CO2e Emissions throughout Analysis Period | CB1: BAU Total Year 1 Elec Cost - Pre-Tax | CC1: New Total Year 1 Elec Cost - Pre-Tax | CD1: Difference Total Year 1 Elec Cost | CE1: BAU Total Full Period Elec Cost | CF1: New Total Full Period Elec Cost | CG1: Difference in Full Period Utility Cost | CH1: BAU Total Life Cycle Costs | CI1: New Total Life Cycle Costs | CJ1: Difference in Total life cycle costs | CK1: New System Net Present Value | CL1: Payback Period for PV/ASHP (yrs)
A2: LT Heat Pumps, net metering, 1 hour battery, full cost | I2: LT Heat Pumps, net metering, 1 hour battery, full cost | REopt Web Tool | REopt Energy Integration & Optimization | NLR | J2: ASHP, Battery, PV | K2: 2: Full replacement heating | L2: LT Heat Pumps, net metering, 1 hour battery, full cost | M2: 47.85212, -122.56923 | N2: Roofspace only | O2: 8000 | P2: PSE: 25 | Q2: Net metering | R2: 100 | S2: - | T2: propane | U2: 2.01 | V2: https://drive.google.com/file/d/1Xl5WOtWsJzfbC-Y8nCxkp4Y4Mozirc_L/view?usp=drive_link | W2: 2024 | X2: https://drive.google.com/file/d/12MjGV739OVxdOUym7sn516wQM4dv51MR/view?usp=drive_link | Y2: 100 | Z2: 2024 | AA2: 83.07 | AB2: 25 | AC2: 2.5 | AD2: 6 | AE2: 7.8 | AF2: 0 | AG2: - | AH2: Small Commercial | AI2: 2220 | AJ2: Rooftop, Fixed | AK2: 335.4 | AL2: 10.7 | AM2: 0 | AN2: No MACRS | AO2: 0 | AP2: 495 | AQ2: 665 | AR2: 8066 | AS2: 10 | AT2: 10 | AU2: =0.7*AP2 -> 346.5 | AV2: =0.7*AQ2 -> 465.5 | AW2: =0.7*AR2 -> 5646.2 | AX2: 10 | AY2: 10 | AZ2: 0 | BA2: No MACRS | BB2: 0 | BC2: 0 | BD2: https://drive.google.com/file/d/1jrpu40DzxTFYY6LiD8LJLWmYTYBMVds2/view?usp=drive_link | BE2: 1 | BF2: 10 | BG2: No MACRS | BH2: 0 | BI2: LT Heat Pumps, net metering, 1 hour battery, full cost | REopt Web Tool | REopt Energy Integration & Optimization | NLR | BM2: 32224
A3: LT Heat Pumps, net metering, 1 hour battery, free capital | I3: LT Heat Pumps, net metering, 1 hour battery, free capital | REopt Web Tool | REopt Energy Integration & Optimization | NLR | J3: ASHP, Battery, PV | K3: 2: Full replacement heating | L3: LT Heat Pumps, net metering, 1 hour battery, free capital | M3: 47.85212, -122.56923 | N3: Roofspace only | O3: 8000 | P3: PSE: 25 | Q3: Net metering | R3: 100 | S3: - | T3: propane | U3: 2.01 | V3: https://drive.google.com/file/d/1Xl5WOtWsJzfbC-Y8nCxkp4Y4Mozirc_L/view?usp=drive_link | W3: 2024 | X3: https://drive.google.com/file/d/12MjGV739OVxdOUym7sn516wQM4dv51MR/view?usp=drive_link | Y3: 100 | Z3: 2024 | AA3: 83.07 | AB3: 10 | AC3: 2.5 | AD3: 6 | AE3: 7.8 | AF3: 0 | AG3: - | AH3: Small Commercial | AI3: 0 | AJ3: Rooftop, Fixed | AK3: 335.4 | AL3: 10.7 | AM3: 0 | AN3: No MACRS | AO3: 0 | AP3: 0 | AQ3: 0 | AR3: 0 | AS3: 10 | AT3: 10 | AU3: =0.7*AP3 -> 0 | AV3: =0.7*AQ3 -> 0 | AW3: =0.7*AR3 -> 0 | AX3: 10 | AY3: 10 | AZ3: 0 | BA3: No MACRS | BB3: 0 | BC3: 0 | BD3: https://drive.google.com/file/d/1jrpu40DzxTFYY6LiD8LJLWmYTYBMVds2/view?usp=drive_link | BE3: 1 | BF3: 10 | BG3: No MACRS | BH3: 0 | BI3: LT Heat Pumps, net metering, 1 hour battery, free capital | REopt Web Tool | REopt Energy Integration & Optimization | NLR | BM3: 112746
A4: LT Heat Pumps, net billing, 1 hour battery, full cost | I4: LT Heat Pumps, net billing, 1 hour battery, full cost | REopt Web Tool | REopt Energy Integration & Optimization | NLR | J4: ASHP, Battery, PV | K4: 2: Full replacement heating | L4: LT Heat Pumps, net billing, 1 hour battery, full cost | M4: 47.85212, -122.56923 | N4: Roofspace only | O4: 8000 | P4: PSE: 25 | Q4: Net billing | R4: - | S4: 0.06713 | T4: propane | U4: 2.01 | V4: https://drive.google.com/file/d/1Xl5WOtWsJzfbC-Y8nCxkp4Y4Mozirc_L/view?usp=drive_link | W4: 2024 | X4: https://drive.google.com/file/d/12MjGV739OVxdOUym7sn516wQM4dv51MR/view?usp=drive_link | Y4: 100 | Z4: 2024 | AA4: 83.07 | AB4: 25 | AC4: 2.5 | AD4: 6 | AE4: 7.8 | AF4: 0 | AG4: - | AH4: Small Commercial | AI4: 2220 | AJ4: Rooftop, Fixed | AK4: 335.4 | AL4: 10.7 | AM4: 0 | AN4: No MACRS | AO4: 0 | AP4: 495 | AQ4: 665 | AR4: 8066 | AS4: 10 | AT4: 10 | AU4: =0.7*AP4 -> 346.5 | AV4: =0.7*AQ4 -> 465.5 | AW4: =0.7*AR4 -> 5646.2 | AX4: 10 | AY4: 10 | AZ4: 0 | BA4: No MACRS | BB4: 0 | BC4: 0 | BD4: https://drive.google.com/file/d/1jrpu40DzxTFYY6LiD8LJLWmYTYBMVds2/view?usp=drive_link | BE4: 1 | BF4: 10 | BG4: No MACRS | BH4: 0 | BI4: LT Heat Pumps, net billing, 1 hour battery, full cost | REopt Web Tool | REopt Energy Integration & Optimization | NLR | BM4: -69986
A5: LT Heat Pumps, net billing, 1 hour battery, free capital | I5: LT Heat Pumps, net billing, 1 hour battery, free capital | REopt Web Tool | REopt Energy Integration & Optimization | NLR | J5: ASHP, Battery, PV | K5: 2: Full replacement heating | L5: LT Heat Pumps, net billing, 1 hour battery, free capital | M5: 47.85212, -122.56923 | N5: Roofspace only | O5: 8000 | P5: PSE: 25 | Q5: Net billing | R5: - | S5: 0.06713 | T5: propane | U5: 2.01 | V5: https://drive.google.com/file/d/1Xl5WOtWsJzfbC-Y8nCxkp4Y4Mozirc_L/view?usp=drive_link | W5: 2024 | X5: https://drive.google.com/file/d/12MjGV739OVxdOUym7sn516wQM4dv51MR/view?usp=drive_link | Y5: 100 | Z5: 2024 | AA5: 83.07 | AB5: 10 | AC5: 2.5 | AD5: 6 | AE5: 7.8 | AF5: 0 | AG5: - | AH5: Small Commercial | AI5: 0 | AJ5: Rooftop, Fixed | AK5: 335.4 | AL5: 10.7 | AM5: 0 | AN5: No MACRS | AO5: 0 | AP5: 0 | AQ5: 0 | AR5: 0 | AS5: 10 | AT5: 10 | AU5: =0.7*AP5 -> 0 | AV5: =0.7*AQ5 -> 0 | AW5: =0.7*AR5 -> 0 | AX5: 10 | AY5: 10 | AZ5: 0 | BA5: No MACRS | BB5: 0 | BC5: 0 | BD5: https://drive.google.com/file/d/1jrpu40DzxTFYY6LiD8LJLWmYTYBMVds2/view?usp=drive_link | BE5: 1 | BF5: 10 | BG5: No MACRS | BH5: 0 | BI5: LT Heat Pumps, net billing, 1 hour battery, free capital | REopt Web Tool | REopt Energy Integration & Optimization | NLR | BM5: 78825
A6: LT Heat Pumps, net metering, 2 hour battery, full cost | I6: LT Heat Pumps, net metering, 2 hour battery, full cost | REopt Web Tool | REopt Energy Integration & Optimization | NLR | J6: ASHP, Battery, PV | K6: 2: Full replacement heating | L6: LT Heat Pumps, net metering, 2 hour battery, full cost | M6: 47.85212, -122.56923 | N6: Roofspace only | O6: 8000 | P6: PSE: 25 | Q6: Net metering | R6: 100 | S6: - | T6: propane | U6: 2.01 | V6: https://drive.google.com/file/d/1Xl5WOtWsJzfbC-Y8nCxkp4Y4Mozirc_L/view?usp=drive_link | W6: 2024 | X6: https://drive.google.com/file/d/12MjGV739OVxdOUym7sn516wQM4dv51MR/view?usp=drive_link | Y6: 100 | Z6: 2024 | AA6: 83.07 | AB6: 25 | AC6: 2.5 | AD6: 6 | AE6: 7.8 | AF6: 0 | AG6: - | AH6: Small Commercial | AI6: 2220 | AJ6: Rooftop, Fixed | AK6: 335.4 | AL6: 10.7 | AM6: 0 | AN6: No MACRS | AO6: 0 | AP6: 495 | AQ6: 665 | AR6: 8066 | AS6: 20 | AT6: 20 | AU6: =0.7*AP6 -> 346.5 | AV6: =0.7*AQ6 -> 465.5 | AW6: =0.7*AR6 -> 5646.2 | AX6: 10 | AY6: 10 | AZ6: 0 | BA6: No MACRS | BB6: 0 | BC6: 0 | BD6: https://drive.google.com/file/d/1jrpu40DzxTFYY6LiD8LJLWmYTYBMVds2/view?usp=drive_link | BE6: 1 | BF6: 10 | BG6: No MACRS | BH6: 0 | BI6: LT Heat Pumps, net metering, 2 hour battery, full cost | REopt Web Tool | REopt Energy Integration & Optimization | NLR | BM6: 21612
A7: LT Heat Pumps, net metering, 2 hour battery, free capital | I7: LT Heat Pumps, net metering, 2 hour battery, free capital | REopt Web Tool | REopt Energy Integration & Optimization | NLR | J7: ASHP, Battery, PV | K7: 2: Full replacement heating | L7: LT Heat Pumps, net metering, 2 hour battery, free capital | M7: 47.85212, -122.56923 | N7: Roofspace only | O7: 8000 | P7: PSE: 25 | Q7: Net metering | R7: 100 | S7: - | T7: propane | U7: 2.01 | V7: https://drive.google.com/file/d/1Xl5WOtWsJzfbC-Y8nCxkp4Y4Mozirc_L/view?usp=drive_link | W7: 2024 | X7: https://drive.google.com/file/d/12MjGV739OVxdOUym7sn516wQM4dv51MR/view?usp=drive_link | Y7: 100 | Z7: 2024 | AA7: 83.07 | AB7: 10 | AC7: 2.5 | AD7: 6 | AE7: 7.8 | AF7: 0 | AG7: - | AH7: Small Commercial | AI7: 0 | AJ7: Rooftop, Fixed | AK7: 335.4 | AL7: 10.7 | AM7: 0 | AN7: No MACRS | AO7: 0 | AP7: 0 | AQ7: 0 | AR7: 0 | AS7: 20 | AT7: 20 | AU7: =0.7*AP7 -> 0 | AV7: =0.7*AQ7 -> 0 | AW7: =0.7*AR7 -> 0 | AX7: 10 | AY7: 10 | AZ7: 0 | BA7: No MACRS | BB7: 0 | BC7: 0 | BD7: https://drive.google.com/file/d/1jrpu40DzxTFYY6LiD8LJLWmYTYBMVds2/view?usp=drive_link | BE7: 1 | BF7: 10 | BG7: No MACRS | BH7: 0 | BI7: LT Heat Pumps, net metering, 2 hour battery, free capital | REopt Web Tool | REopt Energy Integration & Optimization | NLR | BM7: 112791
A8: LT Heat Pumps, net billing, 2 hour battery, full cost | I8: LT Heat Pumps, net billing, 2 hour battery, full cost | REopt Web Tool | REopt Energy Integration & Optimization | NLR | J8: ASHP, Battery, PV | K8: 2: Full replacement heating | L8: LT Heat Pumps, net billing, 2 hour battery, full cost | M8: 47.85212, -122.56923 | N8: Roofspace only | O8: 8000 | P8: PSE: 25 | Q8: Net billing | R8: - | S8: 0.06713 | T8: propane | U8: 2.01 | V8: https://drive.google.com/file/d/1Xl5WOtWsJzfbC-Y8nCxkp4Y4Mozirc_L/view?usp=drive_link | W8: 2024 | X8: https://drive.google.com/file/d/12MjGV739OVxdOUym7sn516wQM4dv51MR/view?usp=drive_link | Y8: 100 | Z8: 2024 | AA8: 83.07 | AB8: 25 | AC8: 2.5 | AD8: 6 | AE8: 7.8 | AF8: 0 | AG8: - | AH8: Small Commercial | AI8: 2220 | AJ8: Rooftop, Fixed | AK8: 335.4 | AL8: 10.7 | AM8: 0 | AN8: No MACRS | AO8: 0 | AP8: 495 | AQ8: 665 | AR8: 8066 | AS8: 20 | AT8: 20 | AU8: =0.7*AP8 -> 346.5 | AV8: =0.7*AQ8 -> 465.5 | AW8: =0.7*AR8 -> 5646.2 | AX8: 10 | AY8: 10 | AZ8: 0 | BA8: No MACRS | BB8: 0 | BC8: 0 | BD8: https://drive.google.com/file/d/1jrpu40DzxTFYY6LiD8LJLWmYTYBMVds2/view?usp=drive_link | BE8: 1 | BF8: 10 | BG8: No MACRS | BH8: 0 | BI8: LT Heat Pumps, net billing, 2 hour battery, full cost | REopt Web Tool | REopt Energy Integration & Optimization | NLR | BM8: -75364
A9: LT Heat Pumps, net billing, 2 hour battery, free capital | I9: LT Heat Pumps, net billing, 2 hour battery, free capital | REopt Web Tool | REopt Energy Integration & Optimization | NLR | J9: ASHP, Battery, PV | K9: 2: Full replacement heating | L9: LT Heat Pumps, net billing, 2 hour battery, free capital | M9: 47.85212, -122.56923 | N9: Roofspace only | O9: 8000 | P9: PSE: 25 | Q9: Net billing | R9: - | S9: 0.06713 | T9: propane | U9: 2.01 | V9: https://drive.google.com/file/d/1Xl5WOtWsJzfbC-Y8nCxkp4Y4Mozirc_L/view?usp=drive_link | W9: 2024 | X9: https://drive.google.com/file/d/12MjGV739OVxdOUym7sn516wQM4dv51MR/view?usp=drive_link | Y9: 100 | Z9: 2024 | AA9: 83.07 | AB9: 10 | AC9: 2.5 | AD9: 6 | AE9: 7.8 | AF9: 0 | AG9: - | AH9: Small Commercial | AI9: 0 | AJ9: Rooftop, Fixed | AK9: 335.4 | AL9: 10.7 | AM9: 0 | AN9: No MACRS | AO9: 0 | AP9: 0 | AQ9: 0 | AR9: 0 | AS9: 20 | AT9: 20 | AU9: =0.7*AP9 -> 0 | AV9: =0.7*AQ9 -> 0 | AW9: =0.7*AR9 -> 0 | AX9: 10 | AY9: 10 | AZ9: 0 | BA9: No MACRS | BB9: 0 | BC9: 0 | BD9: https://drive.google.com/file/d/1jrpu40DzxTFYY6LiD8LJLWmYTYBMVds2/view?usp=drive_link | BE9: 1 | BF9: 10 | BG9: No MACRS | BH9: 0 | BI9: LT Heat Pumps, net billing, 2 hour battery, free capital | REopt Web Tool | REopt Energy Integration & Optimization | NLR | BM9: 80636
A10: LT Heat Pumps, net metering, 4 hour battery, full cost | I10: LT Heat Pumps, net metering, 4 hour battery, full cost | REopt Web Tool | REopt Energy Integration & Optimization | NLR | J10: ASHP, Battery, PV | K10: 2: Full replacement heating | L10: LT Heat Pumps, net metering, 4 hour battery, full cost | M10: 47.85212, -122.56923 | N10: Roofspace only | O10: 8000 | P10: PSE: 25 | Q10: Net metering | R10: 100 | S10: - | T10: propane | U10: 2.01 | V10: https://drive.google.com/file/d/1Xl5WOtWsJzfbC-Y8nCxkp4Y4Mozirc_L/view?usp=drive_link | W10: 2024 | X10: https://drive.google.com/file/d/12MjGV739OVxdOUym7sn516wQM4dv51MR/view?usp=drive_link | Y10: 100 | Z10: 2024 | AA10: 83.07 | AB10: 25 | AC10: 2.5 | AD10: 6 | AE10: 7.8 | AF10: 0 | AG10: - | AH10: Small Commercial | AI10: 2220 | AJ10: Rooftop, Fixed | AK10: 335.4 | AL10: 10.7 | AM10: 0 | AN10: No MACRS | AO10: 0 | AP10: 495 | AQ10: 665 | AR10: 8066 | AS10: 40 | AT10: 40 | AU10: =0.7*AP10 -> 346.5 | AV10: =0.7*AQ10 -> 465.5 | AW10: =0.7*AR10 -> 5646.2 | AX10: 10 | AY10: 10 | AZ10: 0 | BA10: No MACRS | BB10: 0 | BC10: 0 | BD10: https://drive.google.com/file/d/1jrpu40DzxTFYY6LiD8LJLWmYTYBMVds2/view?usp=drive_link | BE10: 1 | BF10: 10 | BG10: No MACRS | BH10: 0 | BI10: LT Heat Pumps, net metering, 4 hour battery, full cost | REopt Web Tool | REopt Energy Integration & Optimization | NLR | BM10: 353
A11: LT Heat Pumps, net metering, 4 hour battery, free capital | I11: LT Heat Pumps, net metering, 4 hour battery, free capital | REopt Web Tool | REopt Energy Integration & Optimization | NLR | J11: ASHP, Battery, PV | K11: 2: Full replacement heating | L11: LT Heat Pumps, net metering, 4 hour battery, free capital | M11: 47.85212, -122.56923 | N11: Roofspace only | O11: 8000 | P11: PSE: 25 | Q11: Net metering | R11: 100 | S11: - | T11: propane | U11: 2.01 | V11: https://drive.google.com/file/d/1Xl5WOtWsJzfbC-Y8nCxkp4Y4Mozirc_L/view?usp=drive_link | W11: 2024 | X11: https://drive.google.com/file/d/12MjGV739OVxdOUym7sn516wQM4dv51MR/view?usp=drive_link | Y11: 100 | Z11: 2024 | AA11: 83.07 | AB11: 10 | AC11: 2.5 | AD11: 6 | AE11: 7.8 | AF11: 0 | AG11: - | AH11: Small Commercial | AI11: 0 | AJ11: Rooftop, Fixed | AK11: 335.4 | AL11: 10.7 | AM11: 0 | AN11: No MACRS | AO11: 0 | AP11: 0 | AQ11: 0 | AR11: 0 | AS11: 40 | AT11: 40 | AU11: =0.7*AP11 -> 0 | AV11: =0.7*AQ11 -> 0 | AW11: =0.7*AR11 -> 0 | AX11: 10 | AY11: 10 | AZ11: 0 | BA11: No MACRS | BB11: 0 | BC11: 0 | BD11: https://drive.google.com/file/d/1jrpu40DzxTFYY6LiD8LJLWmYTYBMVds2/view?usp=drive_link | BE11: 1 | BF11: 10 | BG11: No MACRS | BH11: 0 | BI11: LT Heat Pumps, net metering, 4 hour battery, free capital | REopt Web Tool | REopt Energy Integration & Optimization | NLR | BM11: 112869
A12: LT Heat Pumps, net billing, 4 hour battery, full cost | I12: LT Heat Pumps, net billing, 4 hour battery, full cost | REopt Web Tool | REopt Energy Integration & Optimization | NLR | J12: ASHP, Battery, PV | K12: 2: Full replacement heating | L12: LT Heat Pumps, net billing, 4 hour battery, full cost | M12: 47.85212, -122.56923 | N12: Roofspace only | O12: 8000 | P12: PSE: 25 | Q12: Net billing | R12: - | S12: 0.06713 | T12: propane | U12: 2.01 | V12: https://drive.google.com/file/d/1Xl5WOtWsJzfbC-Y8nCxkp4Y4Mozirc_L/view?usp=drive_link | W12: 2024 | X12: https://drive.google.com/file/d/12MjGV739OVxdOUym7sn516wQM4dv51MR/view?usp=drive_link | Y12: 100 | Z12: 2024 | AA12: 83.07 | AB12: 25 | AC12: 2.5 | AD12: 6 | AE12: 7.8 | AF12: 0 | AG12: - | AH12: Small Commercial | AI12: 2220 | AJ12: Rooftop, Fixed | AK12: 335.4 | AL12: 10.7 | AM12: 0 | AN12: No MACRS | AO12: 0 | AP12: 495 | AQ12: 665 | AR12: 8066 | AS12: 40 | AT12: 40 | AU12: =0.7*AP12 -> 346.5 | AV12: =0.7*AQ12 -> 465.5 | AW12: =0.7*AR12 -> 5646.2 | AX12: 10 | AY12: 10 | AZ12: 0 | BA12: No MACRS | BB12: 0 | BC12: 0 | BD12: https://drive.google.com/file/d/1jrpu40DzxTFYY6LiD8LJLWmYTYBMVds2/view?usp=drive_link | BE12: 1 | BF12: 10 | BG12: No MACRS | BH12: 0 | BI12: LT Heat Pumps, net billing, 4 hour battery, full cost | REopt Web Tool | REopt Energy Integration & Optimization | NLR | BM12: -86712
A13: LT Heat Pumps, net billing, 4 hour battery, free capital | I13: LT Heat Pumps, net billing, 4 hour battery, free capital | REopt Web Tool | REopt Energy Integration & Optimization | NLR | J13: ASHP, Battery, PV | K13: 2: Full replacement heating | L13: LT Heat Pumps, net billing, 4 hour battery, free capital | M13: 47.85212, -122.56923 | N13: Roofspace only | O13: 8000 | P13: PSE: 25 | Q13: Net billing | R13: - | S13: 0.06713 | T13: propane | U13: 2.01 | V13: https://drive.google.com/file/d/1Xl5WOtWsJzfbC-Y8nCxkp4Y4Mozirc_L/view?usp=drive_link | W13: 2024 | X13: https://drive.google.com/file/d/12MjGV739OVxdOUym7sn516wQM4dv51MR/view?usp=drive_link | Y13: 100 | Z13: 2024 | AA13: 83.07 | AB13: 10 | AC13: 2.5 | AD13: 6 | AE13: 7.8 | AF13: 0 | AG13: - | AH13: Small Commercial | AI13: 0 | AJ13: Rooftop, Fixed | AK13: 335.4 | AL13: 10.7 | AM13: 0 | AN13: No MACRS | AO13: 0 | AP13: 0 | AQ13: 0 | AR13: 0 | AS13: 40 | AT13: 40 | AU13: =0.7*AP13 -> 0 | AV13: =0.7*AQ13 -> 0 | AW13: =0.7*AR13 -> 0 | AX13: 10 | AY13: 10 | AZ13: 0 | BA13: No MACRS | BB13: 0 | BC13: 0 | BD13: https://drive.google.com/file/d/1jrpu40DzxTFYY6LiD8LJLWmYTYBMVds2/view?usp=drive_link | BE13: 1 | BF13: 10 | BG13: No MACRS | BH13: 0 | BI13: LT Heat Pumps, net billing, 4 hour battery, free capital | REopt Web Tool | REopt Energy Integration & Optimization | NLR | BM13: 84030
A15: Peak demand: 51.0 kW

Sheet LT Heat Pumps Schedule 24
A1: Scenario | B1: Neither | C1: Net metering | D1: Net billing | E1: No PV | F1: CEC & EC PV | G1: Full cost (25 year) | H1: NPV savings (10 year) | I1: REopt Results: | J1: Select Technologies to Evaluate | K1: Air-Source Heat Pump configuration | L1: Evaluation name | M1: Site location (latitude, longitude) | N1: PV & wind space available | O1: Roofspace available (sq ft) | P1: Electricity rate | Q1: Compensation type | R1: Net metering system size limit (kW) | S1: Net billing compensation for all exports ($/kWh) | T1: Existing heating system fuel type | U1: Annual existing heating system fuel cost ($/gallon) | V1: Upload typical electric load profile | W1: Year of load profile | X1: Upload typical heating load profile | Y1: Space heating load percent of total heating load (%) | Z1: Year of load profile | AA1: Existing heating system efficiency (% HHV-basis) | AB1: Analysis period (years) | AC1: Host discount rate, nominal (%) | AD1: Electricity cost escalation rate, nominal (%/year) | AE1: Existing heating system fuel cost escalation rate, nominal (%/year) | AF1: Host effective tax rate (%) | AG1: Emissions | AH1: Size class | AI1: System capital cost ($/kW-DC) | AJ1: Array type | AK1: Array azimuth (deg) | AL1: Array tilt (deg) | AM1: Federal Incentive based on percentage of cost (%) | AN1: MACRS schedule | AO1: MACRS bonus depreciation | AP1: Energy capacity cost ($/kWh) | AQ1: Power capacity cost ($/kW) | AR1: Constant cost ($) | AS1: Minimum energy capacity (kWh) | AT1: Maximum energy capacity (kWh) | AU1: Energy capacity replacement cost ($/kWh) | AV1: Power capacity replacement cost ($/kWh) | AW1: Constant replacement cost ($) | AX1: Minimum power capacity (kW) | AY1: Maximum power capacity (kW) | AZ1: Federal Incentive based on percentage of cost (%) | BA1: MACRS schedule | BB1: MACRS bonus depreciation | BC1: Total installed cost ($/ton) | BD1: Upload COP Table | BE1: Heat pump capacity sizing factor | BF1: Resistive heating back-up temperature threshold (°F) | BG1: MACRS schedule | BH1: MACRS bonus depreciation | BI1: REopt Results: | BJ1: Optimized PV size (kW) | BK1: Optimized ASHP size (tonnes) | BL1: Optimized Battery Power and Capacity (kW/kWh) | BM1: Potential Life Cycle Savings | BN1: Avg. Annual Grid Serving Load (kWh) | BO1: Avg. Annual Grid Charging Battery (kWh) | BP1: Avg. Annual Grid Total Electricity Consumed (kWh) | BQ1: Avg. Annual PV Serving Load (kWh) | BR1: Avg. Annual PV Charging Battery (kWh) | BS1: Avg. Annual PV Exported to Grid (kWh) | BT1: Avg. Annual PV Curtailment (kWh) | BU1: Avg. Annual PV Total Electricity Produced (kWh) | BV1: Avg. Annual Battery Serving Load (kWh) | BW1: Non-PV Average Annual Energy Supplied from Grid (kWh) | BX1: PV System Average Annual Energy Supplied from Grid (kWh) | BY1: Difference in Avg. Annual Energy Supplied from Grid | BZ1: w/PV Annual Renewable Electricity (% of electricity consumed) | CA1: PV Avoided CO2e Emissions throughout Analysis Period | CB1: Non-PV Total Year 1 Elec Cost - Pre-Tax | CC1: PV Total Year 1 Elec Cost - Pre-Tax | CD1: Difference Total Year 1 Elec Cost | CE1: PV Total Full Period Elec Cost | CF1: Difference in Full Period Utility Cost | CG1: Non-PV Total Life Cycle Costs | CH1: PV/Battery Total Life Cycle Costs | CI1: Difference in Total life cycle costs | CJ1: w/PV/ Battery Net Present Value | CK1: Payback Period for PV /Battery (yrs)
A2: SCHEDULE 24: LT Heat Pumps, no PV, full cost | I2: Schedule 24: LT Heat Pumps, no PV, full cost | REopt Web Tool | REopt Energy Integration & Optimization | NLR | J2: ASHP | K2: 2: Full replacement heating | L2: LT Heat Pumps, no PV, full cost | M2: 47.85212, -122.56923 | N2: Roofspace only | O2: 8000 | P2: PSE: 24 (General Service - Three Phase) | Q2: N/A | R2: - | S2: - | T2: propane | U2: 2.01 | V2: https://drive.google.com/file/d/1Xl5WOtWsJzfbC-Y8nCxkp4Y4Mozirc_L/view?usp=drive_link | W2: 2024 | X2: https://drive.google.com/file/d/12MjGV739OVxdOUym7sn516wQM4dv51MR/view?usp=drive_link | Y2: 100 | Z2: 2024 | AA2: 83.07 | AB2: 25 | AC2: 2.5 | AD2: 6 | AE2: 7.8 | AF2: 0 | AG2: - | AH2: - | AI2: - | AJ2: - | AK2: - | AL2: - | AM2: - | AN2: - | AO2: - | AP2: - | AQ2: - | AR2: - | AS2: - | AT2: - | AU2: - | AV2: - | AW2: - | AX2: - | AY2: - | AZ2: - | BA2: - | BB2: - | BC2: 0 | BD2: https://drive.google.com/file/d/1jrpu40DzxTFYY6LiD8LJLWmYTYBMVds2/view?usp=drive_link | BE2: 1 | BF2: 10 | BG2: No MACRS | BH2: 0 | BI2: Schedule 24: LT Heat Pumps, no PV, full cost | REopt Web Tool | REopt Energy Integration & Optimization | NLR | BJ2: - | BK2: 35 | BL2: - | BM2: -158378 | CE2: 1040295
A3: SCHEDULE 24: LT Heat Pumps, no PV, free capital | I3: Schedule 24: LT Heat Pumps, no PV, free capital | REopt Web Tool | REopt Energy Integration & Optimization | NLR | J3: ASHP | K3: 2: Full replacement heating | L3: LT Heat Pumps, no PV, free capital | M3: 47.85212, -122.56923 | N3: Roofspace only | O3: 8000 | P3: PSE: 24 (General Service - Three Phase) | Q3: N/A | R3: - | S3: - | T3: propane | U3: 2.01 | V3: https://drive.google.com/file/d/1Xl5WOtWsJzfbC-Y8nCxkp4Y4Mozirc_L/view?usp=drive_link | W3: 2024 | X3: https://drive.google.com/file/d/12MjGV739OVxdOUym7sn516wQM4dv51MR/view?usp=drive_link | Y3: 100 | Z3: 2024 | AA3: 83.07 | AB3: 10 | AC3: 2.5 | AD3: 6 | AE3: 7.8 | AF3: 0 | AG3: - | AH3: - | AI3: - | AJ3: - | AK3: - | AL3: - | AM3: - | AN3: - | AO3: - | AP3: - | AQ3: - | AR3: - | AS3: - | AT3: - | AU3: - | AV3: - | AW3: - | AX3: - | AY3: - | AZ3: - | BA3: - | BB3: - | BC3: 0 | BD3: https://drive.google.com/file/d/1jrpu40DzxTFYY6LiD8LJLWmYTYBMVds2/view?usp=drive_link | BE3: 1 | BF3: 10 | BG3: No MACRS | BH3: 0 | BI3: LT Heat Pumps, net billing, no battery, no PV, 10 yr NPV | REopt Web Tool | REopt Energy Integration & Optimization | NLR | BJ3: - | BK3: 35 | BL3: - | BM3: -12107 | CE3: 315656
A4: SCHEDULE 24: LT Heat Pumps, net metering, full cost | I4: LT Heat Pumps, net metering, full cost | REopt Web Tool | REopt Energy Integration & Optimization | NLR | J4: ASHP, PV | K4: 2: Full replacement heating | L4: LT Heat Pumps, net metering, full cost | M4: 47.85212, -122.56923 | N4: Roofspace only | O4: 8000 | P4: PSE: 24 (General Service - Three Phase) | Q4: Net metering | R4: 100 | S4: - | T4: propane | U4: 2.01 | V4: https://drive.google.com/file/d/1Xl5WOtWsJzfbC-Y8nCxkp4Y4Mozirc_L/view?usp=drive_link | W4: 2024 | X4: https://drive.google.com/file/d/12MjGV739OVxdOUym7sn516wQM4dv51MR/view?usp=drive_link | Y4: 100 | Z4: 2024 | AA4: 83.07 | AB4: 25 | AC4: 2.5 | AD4: 6 | AE4: 7.8 | AF4: 0 | AG4: - | AH4: Small Commercial | AI4: 2220 | AJ4: Rooftop, Fixed | AK4: 335.4 | AL4: 10.7 | AM4: 0 | AN4: No MACRS | AO4: 0 | AP4: - | AQ4: - | AR4: - | AS4: - | AT4: - | AU4: - | AV4: - | AW4: - | AX4: - | AY4: - | AZ4: - | BA4: - | BB4: - | BC4: 0 | BD4: https://drive.google.com/file/d/1jrpu40DzxTFYY6LiD8LJLWmYTYBMVds2/view?usp=drive_link | BE4: 1 | BF4: 10 | BG4: No MACRS | BH4: 0 | BI4: LT Heat Pumps, net metering, full cost | REopt Web Tool | REopt Energy Integration & Optimization | NLR | BJ4: 80 | BK4: 35 | BL4: - | BM4: 94076 | CE4: 558241
A5: SCHEDULE 24: LT Heat Pumps, net metering, free capital | I5: SCHEDULE 24: LT Heat Pumps, net metering, free capital | REopt Web Tool | REopt Energy Integration & Optimization | NLR | J5: ASHP, PV | K5: 2: Full replacement heating | L5: LT Heat Pumps, net metering, free capital | M5: 47.85212, -122.56923 | N5: Roofspace only | O5: 8000 | P5: PSE: 24 (General Service - Three Phase) | Q5: Net metering | R5: 100 | S5: - | T5: propane | U5: 2.01 | V5: https://drive.google.com/file/d/1Xl5WOtWsJzfbC-Y8nCxkp4Y4Mozirc_L/view?usp=drive_link | W5: 2024 | X5: https://drive.google.com/file/d/12MjGV739OVxdOUym7sn516wQM4dv51MR/view?usp=drive_link | Y5: 100 | Z5: 2024 | AA5: 83.07 | AB5: 10 | AC5: 2.5 | AD5: 6 | AE5: 7.8 | AF5: 0 | AG5: - | AH5: Small Commercial | AI5: 0 | AJ5: Rooftop, Fixed | AK5: 335.4 | AL5: 10.7 | AM5: 0 | AN5: No MACRS | AO5: 0 | AP5: - | AQ5: - | AR5: - | AS5: - | AT5: - | AU5: - | AV5: - | AW5: - | AX5: - | AY5: - | AZ5: - | BA5: - | BB5: - | BC5: 0 | BD5: https://drive.google.com/file/d/1jrpu40DzxTFYY6LiD8LJLWmYTYBMVds2/view?usp=drive_link | BE5: 1 | BF5: 10 | BG5: No MACRS | BH5: 0 | BI5: LT Heat Pumps, net billing, no battery, PV CEC & ED, 10 yr NPV | REopt Web Tool | REopt Energy Integration & Optimization | NLR | BJ5: 80 | BK5: 35 | BL5: - | BM5: 119990 | CE5: 162759
A6: SCHEDULE 24: LT Heat Pumps, net billing, full cost | I6: LT Heat Pumps, net billing, full cost | REopt Web Tool | REopt Energy Integration & Optimization | NLR | J6: ASHP, PV | K6: 2: Full replacement heating | L6: LT Heat Pumps, net billing, full cost | M6: 47.85212, -122.56923 | N6: Roofspace only | O6: 8000 | P6: PSE: 24 (General Service - Three Phase) | Q6: Net billing | R6: - | S6: 0.06713 | T6: propane | U6: 2.01 | V6: https://drive.google.com/file/d/1Xl5WOtWsJzfbC-Y8nCxkp4Y4Mozirc_L/view?usp=drive_link | W6: 2024 | X6: https://drive.google.com/file/d/12MjGV739OVxdOUym7sn516wQM4dv51MR/view?usp=drive_link | Y6: 100 | Z6: 2024 | AA6: 83.07 | AB6: 25 | AC6: 2.5 | AD6: 6 | AE6: 7.8 | AF6: 0 | AG6: - | AH6: Small Commercial | AI6: 2220 | AJ6: Rooftop, Fixed | AK6: 335.4 | AL6: 10.7 | AM6: 0 | AN6: No MACRS | AO6: 0 | AP6: - | AQ6: - | AR6: - | AS6: - | AT6: - | AU6: - | AV6: - | AW6: - | AX6: - | AY6: - | AZ6: - | BA6: - | BB6: - | BC6: 0 | BD6: https://drive.google.com/file/d/1jrpu40DzxTFYY6LiD8LJLWmYTYBMVds2/view?usp=drive_link | BE6: 1 | BF6: 10 | BG6: No MACRS | BH6: 0 | BI6: LT Heat Pumps, net billing, full cost | REopt Web Tool | REopt Energy Integration & Optimization | NLR | BJ6: 71 | BK6: 35 | BL6: - | BM6: -80230 | CE6: 759711
A7: SCHEDULE 24: LT Heat Pumps, net billing, free capital | I7: SCHEDULE 24: LT Heat Pumps, net billing, free capital | REopt Web Tool | REopt Energy Integration & Optimization | NLR | J7: ASHP, PV | K7: 2: Full replacement heating | L7: LT Heat Pumps, net billing, free capital | M7: 47.85212, -122.56923 | N7: Roofspace only | O7: 8000 | P7: PSE: 24 (General Service - Three Phase) | Q7: Net billing | R7: - | S7: 0.06713 | T7: propane | U7: 2.01 | V7: https://drive.google.com/file/d/1Xl5WOtWsJzfbC-Y8nCxkp4Y4Mozirc_L/view?usp=drive_link | W7: 2024 | X7: https://drive.google.com/file/d/12MjGV739OVxdOUym7sn516wQM4dv51MR/view?usp=drive_link | Y7: 100 | Z7: 2024 | AA7: 83.07 | AB7: 10 | AC7: 2.5 | AD7: 6 | AE7: 7.8 | AF7: 0 | AG7: - | AH7: Small Commercial | AI7: 0 | AJ7: Rooftop, Fixed | AK7: 335.4 | AL7: 10.7 | AM7: 0 | AN7: No MACRS | AO7: 0 | AP7: - | AQ7: - | AR7: - | AS7: - | AT7: - | AU7: - | AV7: - | AW7: - | AX7: - | AY7: - | AZ7: - | BA7: - | BB7: - | BC7: 0 | BD7: https://drive.google.com/file/d/1jrpu40DzxTFYY6LiD8LJLWmYTYBMVds2/view?usp=drive_link | BE7: 1 | BF7: 10 | BG7: No MACRS | BH7: 0 | BI7: LT Heat Pumps, net billing, no battery, PV CEC & ED, 10 yr NPV | REopt Web Tool | REopt Energy Integration & Optimization | NLR | BJ7: 80 | BK7: 35 | BL7: - | BM7: 63373 | CE7: 219375
A9: Peak demand: 51.0 kW

Sheet LTHP PV cost sensitivity analys
A1: Scenario | B1: Net metering | C1: Net billing | D1: PV cost: | E1: REopt Results: | F1: Select Technologies to Evaluate | G1: Air-Source Heat Pump configuration | H1: Evaluation name | I1: Site location (latitude, longitude) | J1: PV & wind space available | K1: Roofspace available (sq ft) | L1: Electricity rate | M1: Compensation type | N1: Net metering system size limit (kW) | O1: Net billing compensation for all exports ($/kWh) | P1: Existing heating system fuel type | Q1: Annual existing heating system fuel cost ($/gallon) | R1: Upload typical electric load profile | S1: Year of load profile | T1: Upload typical heating load profile | U1: Space heating load percent of total heating load (%) | V1: Year of load profile | W1: Existing heating system efficiency (% HHV-basis) | X1: Analysis period (years) | Y1: Host discount rate, nominal (%) | Z1: Electricity cost escalation rate, nominal (%/year) | AA1: Existing heating system fuel cost escalation rate, nominal (%/year) | AB1: Host effective tax rate (%) | AC1: Emissions | AD1: Size class | AE1: System capital cost ($/kW-DC) | AF1: Array type | AG1: Array azimuth (deg) | AH1: Array tilt (deg) | AI1: Federal Incentive based on percentage of cost (%) | AJ1: MACRS schedule | AK1: MACRS bonus depreciation | AL1: Energy capacity cost ($/kWh) | AM1: Power capacity cost ($/kW) | AN1: Constant cost ($) | AO1: Minimum energy capacity (kWh) | AP1: Maximum energy capacity (kWh) | AQ1: Energy capacity replacement cost ($/kWh) | AR1: Power capacity replacement cost ($/kWh) | AS1: Constant replacement cost ($) | AT1: Minimum power capacity (kW) | AU1: Maximum power capacity (kW) | AV1: Federal Incentive based on percentage of cost (%) | AW1: MACRS schedule | AX1: MACRS bonus depreciation | AY1: Total installed cost ($/ton) | AZ1: Upload COP Table | BA1: Heat pump capacity sizing factor | BB1: Resistive heating back-up temperature threshold (°F) | BC1: MACRS schedule | BD1: MACRS bonus depreciation | BE1: REopt Results: | BF1: Optimized PV size (kW) | BG1: Optimized ASHP size (tonnes) | BH1: Optimized Battery Power and Capacity (kW/kWh) | BI1: Potential Life Cycle Savings | BJ1: Avg. Annual Grid Serving Load (kWh) | BK1: Avg. Annual Grid Charging Battery (kWh) | BL1: Avg. Annual Grid Total Electricity Consumed (kWh) | BM1: Avg. Annual PV Serving Load (kWh) | BN1: Avg. Annual PV Charging Battery (kWh) | BO1: Avg. Annual PV Exported to Grid (kWh) | BP1: Avg. Annual PV Curtailment (kWh) | BQ1: Avg. Annual PV Total Electricity Produced (kWh) | BR1: Avg. Annual Battery Serving Load (kWh) | BS1: Non-PV Average Annual Energy Supplied from Grid (kWh) | BT1: PV System Average Annual Energy Supplied from Grid (kWh) | BU1: Difference in Avg. Annual Energy Supplied from Grid | BV1: w/PV Annual Renewable Electricity (% of electricity consumed) | BW1: PV Avoided CO2e Emissions throughout Analysis Period | BX1: Non-PV Total Year 1 Elec Cost - Pre-Tax | BY1: PV Total Year 1 Elec Cost - Pre-Tax | BZ1: Difference Total Year 1 Elec Cost | CA1: Non-PV Total Full Period Elec Cost | CB1: PV Total Full Period Elec Cost | CC1: Difference in Full Period Utility Cost | CD1: Non-PV Total Life Cycle Costs | CE1: PV/Battery Total Life Cycle Costs | CF1: Difference in Total life cycle costs | CG1: w/PV/ Battery Net Present Value | CH1: Payback Period for PV /Battery (yrs)
A2: LT Heat Pumps, net metering, full cost | D2: 3900 | E2: $3,900 | REopt Web Tool | REopt Energy Integration & Optimization | NLR | F2: ASHP, PV | G2: 2: Full replacement heating | H2: LT Heat Pumps, net metering, full cost | I2: 47.85212, -122.56923 | J2: Roofspace only | K2: 8000 | L2: PSE: 25 | M2: Net metering | N2: 100 | O2: - | P2: propane | Q2: 2.01 | R2: https://drive.google.com/file/d/1Xl5WOtWsJzfbC-Y8nCxkp4Y4Mozirc_L/view?usp=drive_link | S2: 2024 | T2: https://drive.google.com/file/d/12MjGV739OVxdOUym7sn516wQM4dv51MR/view?usp=drive_link | U2: 100 | V2: 2024 | W2: 83.07 | X2: 25 | Y2: 2.5 | Z2: 6 | AA2: 7.8 | AB2: 0 | AC2: - | AD2: Small Commercial | AE2: 2220 | AF2: Rooftop, Fixed | AG2: 335.4 | AH2: 10.7 | AI2: 0 | AJ2: No MACRS | AK2: 0 | AL2: - | AM2: - | AN2: - | AO2: - | AP2: - | AQ2: - | AR2: - | AS2: - | AT2: - | AU2: - | AV2: - | AW2: - | AX2: - | AY2: 0 | AZ2: https://drive.google.com/file/d/1jrpu40DzxTFYY6LiD8LJLWmYTYBMVds2/view?usp=drive_link | BA2: 1 | BB2: 10 | BC2: No MACRS | BD2: 0 | BE2: $3,900 | REopt Web Tool | REopt Energy Integration & Optimization | NLR | BF2: 80
A3: LT Heat Pumps, net metering, full cost | D3: 4100 | E3: $4,100 | REopt Web Tool | REopt Energy Integration & Optimization | NLR | F3: ASHP, PV | G3: 2: Full replacement heating | H3: LT Heat Pumps, net metering, full cost | I3: 47.85212, -122.56923 | J3: Roofspace only | K3: 8000 | L3: PSE: 25 | M3: Net metering | N3: 100 | O3: - | P3: propane | Q3: 2.01 | R3: https://drive.google.com/file/d/1Xl5WOtWsJzfbC-Y8nCxkp4Y4Mozirc_L/view?usp=drive_link | S3: 2024 | T3: https://drive.google.com/file/d/12MjGV739OVxdOUym7sn516wQM4dv51MR/view?usp=drive_link | U3: 100 | V3: 2024 | W3: 83.07 | X3: 25 | Y3: 2.5 | Z3: 6 | AA3: 7.8 | AB3: 0 | AC3: - | AD3: Small Commercial | AE3: 2220 | AF3: Rooftop, Fixed | AG3: 335.4 | AH3: 10.7 | AI3: 0 | AJ3: No MACRS | AK3: 0 | AL3: - | AM3: - | AN3: - | AO3: - | AP3: - | AQ3: - | AR3: - | AS3: - | AT3: - | AU3: - | AV3: - | AW3: - | AX3: - | AY3: 0 | AZ3: https://drive.google.com/file/d/1jrpu40DzxTFYY6LiD8LJLWmYTYBMVds2/view?usp=drive_link | BA3: 1 | BB3: 10 | BC3: No MACRS | BD3: 0 | BE3: $4,100 | REopt Web Tool | REopt Energy Integration & Optimization | NLR | BF3: 60
A4: LT Heat Pumps, net metering, full cost | D4: 4300 | E4: $4,300 | REopt Web Tool | REopt Energy Integration & Optimization | NLR | F4: ASHP, PV | G4: 2: Full replacement heating | H4: LT Heat Pumps, net metering, full cost | I4: 47.85212, -122.56923 | J4: Roofspace only | K4: 8000 | L4: PSE: 25 | M4: Net metering | N4: 100 | O4: - | P4: propane | Q4: 2.01 | R4: https://drive.google.com/file/d/1Xl5WOtWsJzfbC-Y8nCxkp4Y4Mozirc_L/view?usp=drive_link | S4: 2024 | T4: https://drive.google.com/file/d/12MjGV739OVxdOUym7sn516wQM4dv51MR/view?usp=drive_link | U4: 100 | V4: 2024 | W4: 83.07 | X4: 25 | Y4: 2.5 | Z4: 6 | AA4: 7.8 | AB4: 0 | AC4: - | AD4: Small Commercial | AE4: 2220 | AF4: Rooftop, Fixed | AG4: 335.4 | AH4: 10.7 | AI4: 0 | AJ4: No MACRS | AK4: 0 | AL4: - | AM4: - | AN4: - | AO4: - | AP4: - | AQ4: - | AR4: - | AS4: - | AT4: - | AU4: - | AV4: - | AW4: - | AX4: - | AY4: 0 | AZ4: https://drive.google.com/file/d/1jrpu40DzxTFYY6LiD8LJLWmYTYBMVds2/view?usp=drive_link | BA4: 1 | BB4: 10 | BC4: No MACRS | BD4: 0 | BE4: $4,300 | REopt Web Tool | REopt Energy Integration & Optimization | NLR | BF4: 20
A5: LT Heat Pumps, net metering, full cost | D5: 4500 | E5: $4,500 | REopt Web Tool | REopt Energy Integration & Optimization | NLR | F5: ASHP, PV | G5: 2: Full replacement heating | H5: LT Heat Pumps, net metering, full cost | I5: 47.85212, -122.56923 | J5: Roofspace only | K5: 8000 | L5: PSE: 25 | M5: Net metering | N5: 100 | O5: - | P5: propane | Q5: 2.01 | R5: https://drive.google.com/file/d/1Xl5WOtWsJzfbC-Y8nCxkp4Y4Mozirc_L/view?usp=drive_link | S5: 2024 | T5: https://drive.google.com/file/d/12MjGV739OVxdOUym7sn516wQM4dv51MR/view?usp=drive_link | U5: 100 | V5: 2024 | W5: 83.07 | X5: 25 | Y5: 2.5 | Z5: 6 | AA5: 7.8 | AB5: 0 | AC5: - | AD5: Small Commercial | AE5: 2220 | AF5: Rooftop, Fixed | AG5: 335.4 | AH5: 10.7 | AI5: 0 | AJ5: No MACRS | AK5: 0 | AL5: - | AM5: - | AN5: - | AO5: - | AP5: - | AQ5: - | AR5: - | AS5: - | AT5: - | AU5: - | AV5: - | AW5: - | AX5: - | AY5: 0 | AZ5: https://drive.google.com/file/d/1jrpu40DzxTFYY6LiD8LJLWmYTYBMVds2/view?usp=drive_link | BA5: 1 | BB5: 10 | BC5: No MACRS | BD5: 0 | BE5: $4,500 | REopt Web Tool | REopt Energy Integration & Optimization | NLR | BF5: 10
A6: LT Heat Pumps, net metering, full cost | D6: 4700 | E6: $4,700 | REopt Web Tool | REopt Energy Integration & Optimization | NLR | F6: ASHP, PV | G6: 2: Full replacement heating | H6: LT Heat Pumps, net metering, full cost | I6: 47.85212, -122.56923 | J6: Roofspace only | K6: 8000 | L6: PSE: 25 | M6: Net metering | N6: 100 | O6: - | P6: propane | Q6: 2.01 | R6: https://drive.google.com/file/d/1Xl5WOtWsJzfbC-Y8nCxkp4Y4Mozirc_L/view?usp=drive_link | S6: 2024 | T6: https://drive.google.com/file/d/12MjGV739OVxdOUym7sn516wQM4dv51MR/view?usp=drive_link | U6: 100 | V6: 2024 | W6: 83.07 | X6: 25 | Y6: 2.5 | Z6: 6 | AA6: 7.8 | AB6: 0 | AC6: - | AD6: Small Commercial | AE6: 2220 | AF6: Rooftop, Fixed | AG6: 335.4 | AH6: 10.7 | AI6: 0 | AJ6: No MACRS | AK6: 0 | AL6: - | AM6: - | AN6: - | AO6: - | AP6: - | AQ6: - | AR6: - | AS6: - | AT6: - | AU6: - | AV6: - | AW6: - | AX6: - | AY6: 0 | AZ6: https://drive.google.com/file/d/1jrpu40DzxTFYY6LiD8LJLWmYTYBMVds2/view?usp=drive_link | BA6: 1 | BB6: 10 | BC6: No MACRS | BD6: 0 | BE6: $4,700 | REopt Web Tool | REopt Energy Integration & Optimization | NLR | BF6: 0
A9: LT Heat Pumps, net billing, full cost | D9: 2000 | E9: $2,000 | REopt Web Tool | REopt Energy Integration & Optimization | NLR | F9: ASHP, PV | G9: 2: Full replacement heating | H9: LT Heat Pumps, net billing, full cost | I9: 47.85212, -122.56923 | J9: Roofspace only | K9: 8000 | L9: PSE: 25 | M9: Net billing | N9: - | O9: 0.06713 | P9: propane | Q9: 2.01 | R9: https://drive.google.com/file/d/1Xl5WOtWsJzfbC-Y8nCxkp4Y4Mozirc_L/view?usp=drive_link | S9: 2024 | T9: https://drive.google.com/file/d/12MjGV739OVxdOUym7sn516wQM4dv51MR/view?usp=drive_link | U9: 100 | V9: 2024 | W9: 83.07 | X9: 25 | Y9: 2.5 | Z9: 6 | AA9: 7.8 | AB9: 0 | AC9: - | AD9: Small Commercial | AE9: 2220 | AF9: Rooftop, Fixed | AG9: 335.4 | AH9: 10.7 | AI9: 0 | AJ9: No MACRS | AK9: 0 | AL9: - | AM9: - | AN9: - | AO9: - | AP9: - | AQ9: - | AR9: - | AS9: - | AT9: - | AU9: - | AV9: - | AW9: - | AX9: - | AY9: 0 | AZ9: https://drive.google.com/file/d/1jrpu40DzxTFYY6LiD8LJLWmYTYBMVds2/view?usp=drive_link | BA9: 1 | BB9: 10 | BC9: No MACRS | BD9: 0 | BE9: $2,000 | REopt Web Tool | REopt Energy Integration & Optimization | NLR | BF9: 80
A10: LT Heat Pumps, net billing, full cost | D10: 2100 | E10: $2,100 | REopt Web Tool | REopt Energy Integration & Optimization | NLR | F10: ASHP, PV | G10: 2: Full replacement heating | H10: LT Heat Pumps, net billing, full cost | I10: 47.85212, -122.56923 | J10: Roofspace only | K10: 8000 | L10: PSE: 25 | M10: Net billing | N10: - | O10: 0.06713 | P10: propane | Q10: 2.01 | R10: https://drive.google.com/file/d/1Xl5WOtWsJzfbC-Y8nCxkp4Y4Mozirc_L/view?usp=drive_link | S10: 2024 | T10: https://drive.google.com/file/d/12MjGV739OVxdOUym7sn516wQM4dv51MR/view?usp=drive_link | U10: 100 | V10: 2024 | W10: 83.07 | X10: 25 | Y10: 2.5 | Z10: 6 | AA10: 7.8 | AB10: 0 | AC10: - | AD10: Small Commercial | AE10: 2220 | AF10: Rooftop, Fixed | AG10: 335.4 | AH10: 10.7 | AI10: 0 | AJ10: No MACRS | AK10: 0 | AL10: - | AM10: - | AN10: - | AO10: - | AP10: - | AQ10: - | AR10: - | AS10: - | AT10: - | AU10: - | AV10: - | AW10: - | AX10: - | AY10: 0 | AZ10: https://drive.google.com/file/d/1jrpu40DzxTFYY6LiD8LJLWmYTYBMVds2/view?usp=drive_link | BA10: 1 | BB10: 10 | BC10: No MACRS | BD10: 0 | BE10: $2,100 | REopt Web Tool | REopt Energy Integration & Optimization | NLR | BF10: 68
A11: LT Heat Pumps, net billing, full cost | D11: 2200 | E11: $2,200 | REopt Web Tool | REopt Energy Integration & Optimization | NLR | F11: ASHP, PV | G11: 2: Full replacement heating | H11: LT Heat Pumps, net billing, full cost | I11: 47.85212, -122.56923 | J11: Roofspace only | K11: 8000 | L11: PSE: 25 | M11: Net billing | N11: - | O11: 0.06713 | P11: propane | Q11: 2.01 | R11: https://drive.google.com/file/d/1Xl5WOtWsJzfbC-Y8nCxkp4Y4Mozirc_L/view?usp=drive_link | S11: 2024 | T11: https://drive.google.com/file/d/12MjGV739OVxdOUym7sn516wQM4dv51MR/view?usp=drive_link | U11: 100 | V11: 2024 | W11: 83.07 | X11: 25 | Y11: 2.5 | Z11: 6 | AA11: 7.8 | AB11: 0 | AC11: - | AD11: Small Commercial | AE11: 2220 | AF11: Rooftop, Fixed | AG11: 335.4 | AH11: 10.7 | AI11: 0 | AJ11: No MACRS | AK11: 0 | AL11: - | AM11: - | AN11: - | AO11: - | AP11: - | AQ11: - | AR11: - | AS11: - | AT11: - | AU11: - | AV11: - | AW11: - | AX11: - | AY11: 0 | AZ11: https://drive.google.com/file/d/1jrpu40DzxTFYY6LiD8LJLWmYTYBMVds2/view?usp=drive_link | BA11: 1 | BB11: 10 | BC11: No MACRS | BD11: 0 | BE11: $2,200 | REopt Web Tool | REopt Energy Integration & Optimization | NLR | BF11: 57
A12: LT Heat Pumps, net billing, full cost | D12: 2300 | E12: $2,300 | REopt Web Tool | REopt Energy Integration & Optimization | NLR | F12: ASHP, PV | G12: 2: Full replacement heating | H12: LT Heat Pumps, net billing, full cost | I12: 47.85212, -122.56923 | J12: Roofspace only | K12: 8000 | L12: PSE: 25 | M12: Net billing | N12: - | O12: 0.06713 | P12: propane | Q12: 2.01 | R12: https://drive.google.com/file/d/1Xl5WOtWsJzfbC-Y8nCxkp4Y4Mozirc_L/view?usp=drive_link | S12: 2024 | T12: https://drive.google.com/file/d/12MjGV739OVxdOUym7sn516wQM4dv51MR/view?usp=drive_link | U12: 100 | V12: 2024 | W12: 83.07 | X12: 25 | Y12: 2.5 | Z12: 6 | AA12: 7.8 | AB12: 0 | AC12: - | AD12: Small Commercial | AE12: 2220 | AF12: Rooftop, Fixed | AG12: 335.4 | AH12: 10.7 | AI12: 0 | AJ12: No MACRS | AK12: 0 | AL12: - | AM12: - | AN12: - | AO12: - | AP12: - | AQ12: - | AR12: - | AS12: - | AT12: - | AU12: - | AV12: - | AW12: - | AX12: - | AY12: 0 | AZ12: https://drive.google.com/file/d/1jrpu40DzxTFYY6LiD8LJLWmYTYBMVds2/view?usp=drive_link | BA12: 1 | BB12: 10 | BC12: No MACRS | BD12: 0 | BE12: $2,300 | REopt Web Tool | REopt Energy Integration & Optimization | NLR | BF12: 49
A13: LT Heat Pumps, net billing, full cost | D13: 2500 | E13: $2,500 | REopt Web Tool | REopt Energy Integration & Optimization | NLR | F13: ASHP, PV | G13: 2: Full replacement heating | H13: LT Heat Pumps, net billing, full cost | I13: 47.85212, -122.56923 | J13: Roofspace only | K13: 8000 | L13: PSE: 25 | M13: Net billing | N13: - | O13: 0.06713 | P13: propane | Q13: 2.01 | R13: https://drive.google.com/file/d/1Xl5WOtWsJzfbC-Y8nCxkp4Y4Mozirc_L/view?usp=drive_link | S13: 2024 | T13: https://drive.google.com/file/d/12MjGV739OVxdOUym7sn516wQM4dv51MR/view?usp=drive_link | U13: 100 | V13: 2024 | W13: 83.07 | X13: 25 | Y13: 2.5 | Z13: 6 | AA13: 7.8 | AB13: 0 | AC13: - | AD13: Small Commercial | AE13: 2220 | AF13: Rooftop, Fixed | AG13: 335.4 | AH13: 10.7 | AI13: 0 | AJ13: No MACRS | AK13: 0 | AL13: - | AM13: - | AN13: - | AO13: - | AP13: - | AQ13: - | AR13: - | AS13: - | AT13: - | AU13: - | AV13: - | AW13: - | AX13: - | AY13: 0 | AZ13: https://drive.google.com/file/d/1jrpu40DzxTFYY6LiD8LJLWmYTYBMVds2/view?usp=drive_link | BA13: 1 | BB13: 10 | BC13: No MACRS | BD13: 0 | BE13: $2,500 | REopt Web Tool | REopt Energy Integration & Optimization | NLR | BF13: 39
A14: LT Heat Pumps, net billing, full cost | D14: 2700 | E14: $2,700 | REopt Web Tool | REopt Energy Integration & Optimization | NLR | F14: ASHP, PV | G14: 2: Full replacement heating | H14: LT Heat Pumps, net billing, full cost | I14: 47.85212, -122.56923 | J14: Roofspace only | K14: 8000 | L14: PSE: 25 | M14: Net billing | N14: - | O14: 0.06713 | P14: propane | Q14: 2.01 | R14: https://drive.google.com/file/d/1Xl5WOtWsJzfbC-Y8nCxkp4Y4Mozirc_L/view?usp=drive_link | S14: 2024 | T14: https://drive.google.com/file/d/12MjGV739OVxdOUym7sn516wQM4dv51MR/view?usp=drive_link | U14: 100 | V14: 2024 | W14: 83.07 | X14: 25 | Y14: 2.5 | Z14: 6 | AA14: 7.8 | AB14: 0 | AC14: - | AD14: Small Commercial | AE14: 2220 | AF14: Rooftop, Fixed | AG14: 335.4 | AH14: 10.7 | AI14: 0 | AJ14: No MACRS | AK14: 0 | AL14: - | AM14: - | AN14: - | AO14: - | AP14: - | AQ14: - | AR14: - | AS14: - | AT14: - | AU14: - | AV14: - | AW14: - | AX14: - | AY14: 0 | AZ14: https://drive.google.com/file/d/1jrpu40DzxTFYY6LiD8LJLWmYTYBMVds2/view?usp=drive_link | BA14: 1 | BB14: 10 | BC14: No MACRS | BD14: 0 | BE14: $2,700 | REopt Web Tool | REopt Energy Integration & Optimization | NLR | BF14: 32
A15: LT Heat Pumps, net billing, full cost | D15: 2900 | E15: $2,900 | REopt Web Tool | REopt Energy Integration & Optimization | NLR | F15: ASHP, PV | G15: 2: Full replacement heating | H15: LT Heat Pumps, net billing, full cost | I15: 47.85212, -122.56923 | J15: Roofspace only | K15: 8000 | L15: PSE: 25 | M15: Net billing | N15: - | O15: 0.06713 | P15: propane | Q15: 2.01 | R15: https://drive.google.com/file/d/1Xl5WOtWsJzfbC-Y8nCxkp4Y4Mozirc_L/view?usp=drive_link | S15: 2024 | T15: https://drive.google.com/file/d/12MjGV739OVxdOUym7sn516wQM4dv51MR/view?usp=drive_link | U15: 100 | V15: 2024 | W15: 83.07 | X15: 25 | Y15: 2.5 | Z15: 6 | AA15: 7.8 | AB15: 0 | AC15: - | AD15: Small Commercial | AE15: 2220 | AF15: Rooftop, Fixed | AG15: 335.4 | AH15: 10.7 | AI15: 0 | AJ15: No MACRS | AK15: 0 | AL15: - | AM15: - | AN15: - | AO15: - | AP15: - | AQ15: - | AR15: - | AS15: - | AT15: - | AU15: - | AV15: - | AW15: - | AX15: - | AY15: 0 | AZ15: https://drive.google.com/file/d/1jrpu40DzxTFYY6LiD8LJLWmYTYBMVds2/view?usp=drive_link | BA15: 1 | BB15: 10 | BC15: No MACRS | BD15: 0 | BE15: $2,900 | REopt Web Tool | REopt Energy Integration & Optimization | NLR | BF15: 27
A16: LT Heat Pumps, net billing, full cost | D16: 3200 | E16: $3,200 | REopt Web Tool | REopt Energy Integration & Optimization | NLR | F16: ASHP, PV | G16: 2: Full replacement heating | H16: LT Heat Pumps, net billing, full cost | I16: 47.85212, -122.56923 | J16: Roofspace only | K16: 8000 | L16: PSE: 25 | M16: Net billing | N16: - | O16: 0.06713 | P16: propane | Q16: 2.01 | R16: https://drive.google.com/file/d/1Xl5WOtWsJzfbC-Y8nCxkp4Y4Mozirc_L/view?usp=drive_link | S16: 2024 | T16: https://drive.google.com/file/d/12MjGV739OVxdOUym7sn516wQM4dv51MR/view?usp=drive_link | U16: 100 | V16: 2024 | W16: 83.07 | X16: 25 | Y16: 2.5 | Z16: 6 | AA16: 7.8 | AB16: 0 | AC16: - | AD16: Small Commercial | AE16: 2220 | AF16: Rooftop, Fixed | AG16: 335.4 | AH16: 10.7 | AI16: 0 | AJ16: No MACRS | AK16: 0 | AL16: - | AM16: - | AN16: - | AO16: - | AP16: - | AQ16: - | AR16: - | AS16: - | AT16: - | AU16: - | AV16: - | AW16: - | AX16: - | AY16: 0 | AZ16: https://drive.google.com/file/d/1jrpu40DzxTFYY6LiD8LJLWmYTYBMVds2/view?usp=drive_link | BA16: 1 | BB16: 10 | BC16: No MACRS | BD16: 0 | BE16: $3,200 | REopt Web Tool | REopt Energy Integration & Optimization | NLR | BF16: 21
A17: LT Heat Pumps, net billing, full cost | D17: 3600 | E17: $3,600 | REopt Web Tool | REopt Energy Integration & Optimization | NLR | F17: ASHP, PV | G17: 2: Full replacement heating | H17: LT Heat Pumps, net billing, full cost | I17: 47.85212, -122.56923 | J17: Roofspace only | K17: 8000 | L17: PSE: 25 | M17: Net billing | N17: - | O17: 0.06713 | P17: propane | Q17: 2.01 | R17: https://drive.google.com/file/d/1Xl5WOtWsJzfbC-Y8nCxkp4Y4Mozirc_L/view?usp=drive_link | S17: 2024 | T17: https://drive.google.com/file/d/12MjGV739OVxdOUym7sn516wQM4dv51MR/view?usp=drive_link | U17: 100 | V17: 2024 | W17: 83.07 | X17: 25 | Y17: 2.5 | Z17: 6 | AA17: 7.8 | AB17: 0 | AC17: - | AD17: Small Commercial | AE17: 2220 | AF17: Rooftop, Fixed | AG17: 335.4 | AH17: 10.7 | AI17: 0 | AJ17: No MACRS | AK17: 0 | AL17: - | AM17: - | AN17: - | AO17: - | AP17: - | AQ17: - | AR17: - | AS17: - | AT17: - | AU17: - | AV17: - | AW17: - | AX17: - | AY17: 0 | AZ17: https://drive.google.com/file/d/1jrpu40DzxTFYY6LiD8LJLWmYTYBMVds2/view?usp=drive_link | BA17: 1 | BB17: 10 | BC17: No MACRS | BD17: 0 | BE17: $3,600 | REopt Web Tool | REopt Energy Integration & Optimization | NLR | BF17: 17
A18: LT Heat Pumps, net billing, full cost | D18: 4200 | E18: $4,200 | REopt Web Tool | REopt Energy Integration & Optimization | NLR | F18: ASHP, PV | G18: 2: Full replacement heating | H18: LT Heat Pumps, net billing, full cost | I18: 47.85212, -122.56923 | J18: Roofspace only | K18: 8000 | L18: PSE: 25 | M18: Net billing | N18: - | O18: 0.06713 | P18: propane | Q18: 2.01 | R18: https://drive.google.com/file/d/1Xl5WOtWsJzfbC-Y8nCxkp4Y4Mozirc_L/view?usp=drive_link | S18: 2024 | T18: https://drive.google.com/file/d/12MjGV739OVxdOUym7sn516wQM4dv51MR/view?usp=drive_link | U18: 100 | V18: 2024 | W18: 83.07 | X18: 25 | Y18: 2.5 | Z18: 6 | AA18: 7.8 | AB18: 0 | AC18: - | AD18: Small Commercial | AE18: 2220 | AF18: Rooftop, Fixed | AG18: 335.4 | AH18: 10.7 | AI18: 0 | AJ18: No MACRS | AK18: 0 | AL18: - | AM18: - | AN18: - | AO18: - | AP18: - | AQ18: - | AR18: - | AS18: - | AT18: - | AU18: - | AV18: - | AW18: - | AX18: - | AY18: 0 | AZ18: https://drive.google.com/file/d/1jrpu40DzxTFYY6LiD8LJLWmYTYBMVds2/view?usp=drive_link | BA18: 1 | BB18: 10 | BC18: No MACRS | BD18: 0 | BE18: $4,200 | REopt Web Tool | REopt Energy Integration & Optimization | NLR | BF18: 11
A19: LT Heat Pumps, net billing, full cost | D19: 4800 | E19: $4,800 | REopt Web Tool | REopt Energy Integration & Optimization | NLR | F19: ASHP, PV | G19: 2: Full replacement heating | H19: LT Heat Pumps, net billing, full cost | I19: 47.85212, -122.56923 | J19: Roofspace only | K19: 8000 | L19: PSE: 25 | M19: Net billing | N19: - | O19: 0.06713 | P19: propane | Q19: 2.01 | R19: https://drive.google.com/file/d/1Xl5WOtWsJzfbC-Y8nCxkp4Y4Mozirc_L/view?usp=drive_link | S19: 2024 | T19: https://drive.google.com/file/d/12MjGV739OVxdOUym7sn516wQM4dv51MR/view?usp=drive_link | U19: 100 | V19: 2024 | W19: 83.07 | X19: 25 | Y19: 2.5 | Z19: 6 | AA19: 7.8 | AB19: 0 | AC19: - | AD19: Small Commercial | AE19: 2220 | AF19: Rooftop, Fixed | AG19: 335.4 | AH19: 10.7 | AI19: 0 | AJ19: No MACRS | AK19: 0 | AL19: - | AM19: - | AN19: - | AO19: - | AP19: - | AQ19: - | AR19: - | AS19: - | AT19: - | AU19: - | AV19: - | AW19: - | AX19: - | AY19: 0 | AZ19: https://drive.google.com/file/d/1jrpu40DzxTFYY6LiD8LJLWmYTYBMVds2/view?usp=drive_link | BA19: 1 | BB19: 10 | BC19: No MACRS | BD19: 0 | BE19: $4,800 | REopt Web Tool | REopt Energy Integration & Optimization | NLR | BF19: 0

Sheet LTHP Escalation Rate sensitivit
A1: Scenario | B1: Net metering | C1: Net billing | D1: Electricity cost escalation rate, nominal (%/year) | E1: REopt Results: | F1: Select Technologies to Evaluate | G1: Air-Source Heat Pump configuration | H1: Evaluation name | I1: Site location (latitude, longitude) | J1: PV & wind space available | K1: Roofspace available (sq ft) | L1: Electricity rate | M1: Compensation type | N1: Net metering system size limit (kW) | O1: Net billing compensation for all exports ($/kWh) | P1: Existing heating system fuel type | Q1: Annual existing heating system fuel cost ($/gallon) | R1: Upload typical electric load profile | S1: Year of load profile | T1: Upload typical heating load profile | U1: Space heating load percent of total heating load (%) | V1: Year of load profile | W1: Existing heating system efficiency (% HHV-basis) | X1: Analysis period (years) | Y1: Host discount rate, nominal (%) | Z1: Electricity cost escalation rate, nominal (%/year) | AA1: Existing heating system fuel cost escalation rate, nominal (%/year) | AB1: Host effective tax rate (%) | AC1: Emissions | AD1: Size class | AE1: System capital cost ($/kW-DC) | AF1: Array type | AG1: Array azimuth (deg) | AH1: Array tilt (deg) | AI1: Federal Incentive based on percentage of cost (%) | AJ1: MACRS schedule | AK1: MACRS bonus depreciation | AL1: Energy capacity cost ($/kWh) | AM1: Power capacity cost ($/kW) | AN1: Constant cost ($) | AO1: Minimum energy capacity (kWh) | AP1: Maximum energy capacity (kWh) | AQ1: Energy capacity replacement cost ($/kWh) | AR1: Power capacity replacement cost ($/kWh) | AS1: Constant replacement cost ($) | AT1: Minimum power capacity (kW) | AU1: Maximum power capacity (kW) | AV1: Federal Incentive based on percentage of cost (%) | AW1: MACRS schedule | AX1: MACRS bonus depreciation | AY1: Total installed cost ($/ton) | AZ1: Upload COP Table | BA1: Heat pump capacity sizing factor | BB1: Resistive heating back-up temperature threshold (°F) | BC1: MACRS schedule | BD1: MACRS bonus depreciation | BE1: REopt Results: | BF1: Optimized PV size (kW) | BG1: Optimized ASHP size (tonnes) | BH1: Optimized Battery Power and Capacity (kW/kWh) | BI1: Potential Life Cycle Savings | BJ1: Avg. Annual Grid Serving Load (kWh) | BK1: Avg. Annual Grid Charging Battery (kWh) | BL1: Avg. Annual Grid Total Electricity Consumed (kWh) | BM1: Avg. Annual PV Serving Load (kWh) | BN1: Avg. Annual PV Charging Battery (kWh) | BO1: Avg. Annual PV Exported to Grid (kWh) | BP1: Avg. Annual PV Curtailment (kWh) | BQ1: Avg. Annual PV Total Electricity Produced (kWh) | BR1: Avg. Annual Battery Serving Load (kWh) | BS1: Non-PV Average Annual Energy Supplied from Grid (kWh) | BT1: PV System Average Annual Energy Supplied from Grid (kWh) | BU1: Difference in Avg. Annual Energy Supplied from Grid | BV1: w/PV Annual Renewable Electricity (% of electricity consumed) | BW1: PV Avoided CO2e Emissions throughout Analysis Period | BX1: Non-PV Total Year 1 Elec Cost - Pre-Tax | BY1: PV Total Year 1 Elec Cost - Pre-Tax | BZ1: Difference Total Year 1 Elec Cost | CA1: Non-PV Total Full Period Elec Cost | CB1: PV Total Full Period Elec Cost | CC1: Difference in Full Period Utility Cost | CD1: Non-PV Total Life Cycle Costs | CE1: PV/Battery Total Life Cycle Costs | CF1: Difference in Total life cycle costs | CG1: w/PV/ Battery Net Present Value | CH1: Payback Period for PV /Battery (yrs)
A2: LT Heat Pumps, no PV, full cost | D2: 0 | E2: LT Heat Pumps, no PV, full cost, 0% escalation | F2: ASHP | G2: 2: Full replacement heating | H2: LT Heat Pumps, no PV, net metering, full cost, 0% escalation | I2: 47.85212, -122.56923 | J2: Roofspace only | K2: 8000 | L2: PSE: 25 | M2: - | N2: 100 | O2: - | P2: propane | Q2: 2.01 | R2: https://drive.google.com/file/d/1Xl5WOtWsJzfbC-Y8nCxkp4Y4Mozirc_L/view?usp=drive_link | S2: 2024 | T2: https://drive.google.com/file/d/12MjGV739OVxdOUym7sn516wQM4dv51MR/view?usp=drive_link | U2: 100 | V2: 2024 | W2: 83.07 | X2: 25 | Y2: 2.5 | Z2: 0 | AA2: 7.8 | AB2: 0 | AC2: - | AD2: Small Commercial | AE2: - | AF2: Rooftop, Fixed | AG2: 335.4 | AH2: 10.7 | AI2: 0 | AJ2: No MACRS | AK2: 0 | AL2: - | AM2: - | AN2: - | AO2: - | AP2: - | AQ2: - | AR2: - | AS2: - | AT2: - | AU2: - | AV2: - | AW2: - | AX2: - | AY2: 0 | AZ2: https://drive.google.com/file/d/1jrpu40DzxTFYY6LiD8LJLWmYTYBMVds2/view?usp=drive_link | BA2: 1 | BB2: 10 | BC2: No MACRS | BD2: 0 | BE2: LT Heat Pumps, no PV, full cost, 0% escalation | BF2: - | BG2: 35 | BH2: - | BI2: 243117 | BJ2: - | BK2: - | BL2: - | BM2: - | BN2: - | BO2: - | BP2: - | BQ2: - | BR2: - | CE2: 438012
A3: LT Heat Pumps, no PV, full cost | D3: 2 | E3: LT Heat Pumps, no PV, full cost, 2% escalation | F3: ASHP | G3: 2: Full replacement heating | H3: LT Heat Pumps, no PV, full cost, 2% escalation | I3: 47.85212, -122.56923 | J3: Roofspace only | K3: 8000 | L3: PSE: 25 | M3: - | N3: 100 | O3: - | P3: propane | Q3: 2.01 | R3: https://drive.google.com/file/d/1Xl5WOtWsJzfbC-Y8nCxkp4Y4Mozirc_L/view?usp=drive_link | S3: 2024 | T3: https://drive.google.com/file/d/12MjGV739OVxdOUym7sn516wQM4dv51MR/view?usp=drive_link | U3: 100 | V3: 2024 | W3: 83.07 | X3: 25 | Y3: 2.5 | Z3: 2 | AA3: 7.8 | AB3: 0 | AC3: - | AD3: Small Commercial | AE3: - | AF3: Rooftop, Fixed | AG3: 335.4 | AH3: 10.7 | AI3: 0 | AJ3: No MACRS | AK3: 0 | AL3: - | AM3: - | AN3: - | AO3: - | AP3: - | AQ3: - | AR3: - | AS3: - | AT3: - | AU3: - | AV3: - | AW3: - | AX3: - | AY3: 0 | AZ3: https://drive.google.com/file/d/1jrpu40DzxTFYY6LiD8LJLWmYTYBMVds2/view?usp=drive_link | BA3: 1 | BB3: 10 | BC3: No MACRS | BD3: 0 | BE3: LT Heat Pumps, no PV, full cost, 2% escalation | BF3: - | BG3: 35 | BH3: - | BI3: 165443 | BJ3: - | BK3: - | BL3: - | BM3: - | BN3: - | BO3: - | BP3: - | BQ3: - | BR3: - | CE3: 558078
A4: LT Heat Pumps, no PV, full cost | D4: 4 | E4: LT Heat Pumps, no PV, full cost, 4% escalation | F4: ASHP | G4: 2: Full replacement heating | H4: LT Heat Pumps, no PV, full cost, 4% escalation | I4: 47.85212, -122.56923 | J4: Roofspace only | K4: 8000 | L4: PSE: 25 | M4: - | N4: 100 | O4: - | P4: propane | Q4: 2.01 | R4: https://drive.google.com/file/d/1Xl5WOtWsJzfbC-Y8nCxkp4Y4Mozirc_L/view?usp=drive_link | S4: 2024 | T4: https://drive.google.com/file/d/12MjGV739OVxdOUym7sn516wQM4dv51MR/view?usp=drive_link | U4: 100 | V4: 2024 | W4: 83.07 | X4: 25 | Y4: 2.5 | Z4: 4 | AA4: 7.8 | AB4: 0 | AC4: - | AD4: Small Commercial | AE4: - | AF4: Rooftop, Fixed | AG4: 335.4 | AH4: 10.7 | AI4: 0 | AJ4: No MACRS | AK4: 0 | AL4: - | AM4: - | AN4: - | AO4: - | AP4: - | AQ4: - | AR4: - | AS4: - | AT4: - | AU4: - | AV4: - | AW4: - | AX4: - | AY4: 0 | AZ4: https://drive.google.com/file/d/1jrpu40DzxTFYY6LiD8LJLWmYTYBMVds2/view?usp=drive_link | BA4: 1 | BB4: 10 | BC4: No MACRS | BD4: 0 | BE4: LT Heat Pumps, no PV, full cost, 4% escalation | BF4: - | BG4: 35 | BH4: - | BI4: 59505 | BJ4: - | BK4: - | BL4: - | BM4: - | BN4: - | BO4: - | BP4: - | BQ4: - | BR4: - | CE4: 721833
A5: LT Heat Pumps, no PV, full cost | D5: 6 | E5: LT Heat Pumps, no PV, full cost, 6% escalation | F5: ASHP | G5: 2: Full replacement heating | H5: LT Heat Pumps, no PV, full cost, 6% escalation | I5: 47.85212, -122.56923 | J5: Roofspace only | K5: 8000 | L5: PSE: 25 | M5: - | N5: 100 | O5: - | P5: propane | Q5: 2.01 | R5: https://drive.google.com/file/d/1Xl5WOtWsJzfbC-Y8nCxkp4Y4Mozirc_L/view?usp=drive_link | S5: 2024 | T5: https://drive.google.com/file/d/12MjGV739OVxdOUym7sn516wQM4dv51MR/view?usp=drive_link | U5: 100 | V5: 2024 | W5: 83.07 | X5: 25 | Y5: 2.5 | Z5: 6 | AA5: 7.8 | AB5: 0 | AC5: - | AD5: Small Commercial | AE5: - | AF5: Rooftop, Fixed | AG5: 335.4 | AH5: 10.7 | AI5: 0 | AJ5: No MACRS | AK5: 0 | AL5: - | AM5: - | AN5: - | AO5: - | AP5: - | AQ5: - | AR5: - | AS5: - | AT5: - | AU5: - | AV5: - | AW5: - | AX5: - | AY5: 0 | AZ5: https://drive.google.com/file/d/1jrpu40DzxTFYY6LiD8LJLWmYTYBMVds2/view?usp=drive_link | BA5: 1 | BB5: 10 | BC5: No MACRS | BD5: 0 | BE5: LT Heat Pumps, no PV, full cost, 6% escalation | BF5: - | BG5: 35 | BH5: - | BI5: -86028 | BJ5: - | BK5: - | BL5: - | BM5: - | BN5: - | BO5: - | BP5: - | BQ5: - | BR5: - | CE5: 946792
A6: LT Heat Pumps, no PV, full cost | D6: 8 | E6: LT Heat Pumps, no PV, full cost, 8% escalation | F6: ASHP | G6: 2: Full replacement heating | H6: LT Heat Pumps, no PV, full cost, 8% escalation | I6: 47.85212, -122.56923 | J6: Roofspace only | K6: 8000 | L6: PSE: 25 | M6: - | N6: 100 | O6: - | P6: propane | Q6: 2.01 | R6: https://drive.google.com/file/d/1Xl5WOtWsJzfbC-Y8nCxkp4Y4Mozirc_L/view?usp=drive_link | S6: 2024 | T6: https://drive.google.com/file/d/12MjGV739OVxdOUym7sn516wQM4dv51MR/view?usp=drive_link | U6: 100 | V6: 2024 | W6: 83.07 | X6: 25 | Y6: 2.5 | Z6: 8 | AA6: 7.8 | AB6: 0 | AC6: - | AD6: Small Commercial | AE6: - | AF6: Rooftop, Fixed | AG6: 335.4 | AH6: 10.7 | AI6: 0 | AJ6: No MACRS | AK6: 0 | AL6: - | AM6: - | AN6: - | AO6: - | AP6: - | AQ6: - | AR6: - | AS6: - | AT6: - | AU6: - | AV6: - | AW6: - | AX6: - | AY6: 0 | AZ6: https://drive.google.com/file/d/1jrpu40DzxTFYY6LiD8LJLWmYTYBMVds2/view?usp=drive_link | BA6: 1 | BB6: 10 | BC6: No MACRS | BD6: 0 | BE6: LT Heat Pumps, no PV, full cost, 8% escalation | BF6: - | BG6: 35 | BH6: - | BI6: -287117 | BJ6: - | BK6: - | BL6: - | BM6: - | BN6: - | BO6: - | BP6: - | BQ6: - | BR6: - | CE6: 1257627
A7: LT Heat Pumps, no PV, full cost | D7: 10 | E7: LT Heat Pumps, no PV, full cost, 10% escalation | F7: ASHP | G7: 2: Full replacement heating | H7: LT Heat Pumps, no PV, full cost, 10% escalation | I7: 47.85212, -122.56923 | J7: Roofspace only | K7: 8000 | L7: PSE: 25 | M7: - | N7: 100 | O7: - | P7: propane | Q7: 2.01 | R7: https://drive.google.com/file/d/1Xl5WOtWsJzfbC-Y8nCxkp4Y4Mozirc_L/view?usp=drive_link | S7: 2024 | T7: https://drive.google.com/file/d/12MjGV739OVxdOUym7sn516wQM4dv51MR/view?usp=drive_link | U7: 100 | V7: 2024 | W7: 83.07 | X7: 25 | Y7: 2.5 | Z7: 10 | AA7: 7.8 | AB7: 0 | AC7: - | AD7: Small Commercial | AE7: - | AF7: Rooftop, Fixed | AG7: 335.4 | AH7: 10.7 | AI7: 0 | AJ7: No MACRS | AK7: 0 | AL7: - | AM7: - | AN7: - | AO7: - | AP7: - | AQ7: - | AR7: - | AS7: - | AT7: - | AU7: - | AV7: - | AW7: - | AX7: - | AY7: 0 | AZ7: https://drive.google.com/file/d/1jrpu40DzxTFYY6LiD8LJLWmYTYBMVds2/view?usp=drive_link | BA7: 1 | BB7: 10 | BC7: No MACRS | BD7: 0 | BE7: LT Heat Pumps, no PV, full cost, 10% escalation | BF7: - | BG7: 35 | BH7: - | BI7: -566212 | BJ7: - | BK7: - | BL7: - | BM7: - | BN7: - | BO7: - | BP7: - | BQ7: - | BR7: - | CE7: 1689043
A9: LT Heat Pumps, net metering, full cost | D9: 0 | E9: LT Heat Pumps, net metering, full cost, 0% escalation | F9: ASHP, PV | G9: 2: Full replacement heating | H9: LT Heat Pumps, net metering, full cost, 0% escalation | I9: 47.85212, -122.56923 | J9: Roofspace only | K9: 8000 | L9: PSE: 25 | M9: Net metering | N9: 100 | O9: - | P9: propane | Q9: 2.01 | R9: https://drive.google.com/file/d/1Xl5WOtWsJzfbC-Y8nCxkp4Y4Mozirc_L/view?usp=drive_link | S9: 2024 | T9: https://drive.google.com/file/d/12MjGV739OVxdOUym7sn516wQM4dv51MR/view?usp=drive_link | U9: 100 | V9: 2024 | W9: 83.07 | X9: 25 | Y9: 2.5 | Z9: 0 | AA9: 7.8 | AB9: 0 | AC9: - | AD9: Small Commercial | AE9: 2220 | AF9: Rooftop, Fixed | AG9: 335.4 | AH9: 10.7 | AI9: 0 | AJ9: No MACRS | AK9: 0 | AL9: - | AM9: - | AN9: - | AO9: - | AP9: - | AQ9: - | AR9: - | AS9: - | AT9: - | AU9: - | AV9: - | AW9: - | AX9: - | AY9: 0 | AZ9: https://drive.google.com/file/d/1jrpu40DzxTFYY6LiD8LJLWmYTYBMVds2/view?usp=drive_link | BA9: 1 | BB9: 10 | BC9: No MACRS | BD9: 0 | BE9: LT Heat Pumps, net metering, full cost, 0% escalation | BF9: 0 | BG9: 35 | BH9: - | BI9: 243117 | BK9: - | CE9: 438012
A10: LT Heat Pumps, net metering, full cost | D10: 2 | E10: LT Heat Pumps, net metering, full cost, 2% escalation | F10: ASHP, PV | G10: 2: Full replacement heating | H10: LT Heat Pumps, net metering, full cost, 2% escalation | I10: 47.85212, -122.56923 | J10: Roofspace only | K10: 8000 | L10: PSE: 25 | M10: Net metering | N10: 100 | O10: - | P10: propane | Q10: 2.01 | R10: https://drive.google.com/file/d/1Xl5WOtWsJzfbC-Y8nCxkp4Y4Mozirc_L/view?usp=drive_link | S10: 2024 | T10: https://drive.google.com/file/d/12MjGV739OVxdOUym7sn516wQM4dv51MR/view?usp=drive_link | U10: 100 | V10: 2024 | W10: 83.07 | X10: 25 | Y10: 2.5 | Z10: 2 | AA10: 7.8 | AB10: 0 | AC10: - | AD10: Small Commercial | AE10: 2220 | AF10: Rooftop, Fixed | AG10: 335.4 | AH10: 10.7 | AI10: 0 | AJ10: No MACRS | AK10: 0 | AL10: - | AM10: - | AN10: - | AO10: - | AP10: - | AQ10: - | AR10: - | AS10: - | AT10: - | AU10: - | AV10: - | AW10: - | AX10: - | AY10: 0 | AZ10: https://drive.google.com/file/d/1jrpu40DzxTFYY6LiD8LJLWmYTYBMVds2/view?usp=drive_link | BA10: 1 | BB10: 10 | BC10: No MACRS | BD10: 0 | BE10: LT Heat Pumps, net metering, full cost, 2% escalation | BF10: 37 | BG10: 35 | BH10: - | BI10: 169396 | BK10: - | CE10: 554124
A11: LT Heat Pumps, net metering, full cost | D11: 4 | E11: LT Heat Pumps, net metering, full cost, 4% escalation | F11: ASHP, PV | G11: 2: Full replacement heating | H11: LT Heat Pumps, net metering, full cost, 4% escalation | I11: 47.85212, -122.56923 | J11: Roofspace only | K11: 8000 | L11: PSE: 25 | M11: Net metering | N11: 100 | O11: - | P11: propane | Q11: 2.01 | R11: https://drive.google.com/file/d/1Xl5WOtWsJzfbC-Y8nCxkp4Y4Mozirc_L/view?usp=drive_link | S11: 2024 | T11: https://drive.google.com/file/d/12MjGV739OVxdOUym7sn516wQM4dv51MR/view?usp=drive_link | U11: 100 | V11: 2024 | W11: 83.07 | X11: 25 | Y11: 2.5 | Z11: 4 | AA11: 7.8 | AB11: 0 | AC11: - | AD11: Small Commercial | AE11: 2220 | AF11: Rooftop, Fixed | AG11: 335.4 | AH11: 10.7 | AI11: 0 | AJ11: No MACRS | AK11: 0 | AL11: - | AM11: - | AN11: - | AO11: - | AP11: - | AQ11: - | AR11: - | AS11: - | AT11: - | AU11: - | AV11: - | AW11: - | AX11: - | AY11: 0 | AZ11: https://drive.google.com/file/d/1jrpu40DzxTFYY6LiD8LJLWmYTYBMVds2/view?usp=drive_link | BA11: 1 | BB11: 10 | BC11: No MACRS | BD11: 0 | BE11: LT Heat Pumps, net metering, full cost, 4% escalation | BF11: 80 | BG11: 35 | BH11: - | BI11: 128419 | BK11: - | CE11: 652918
A12: LT Heat Pumps, net metering, full cost | D12: 6 | E12: LT Heat Pumps, net metering, full cost, 6% escalation | F12: ASHP, PV | G12: 2: Full replacement heating | H12: LT Heat Pumps, net metering, full cost, 6% escalation | I12: 47.85212, -122.56923 | J12: Roofspace only | K12: 8000 | L12: PSE: 25 | M12: Net metering | N12: 100 | O12: - | P12: propane | Q12: 2.01 | R12: https://drive.google.com/file/d/1Xl5WOtWsJzfbC-Y8nCxkp4Y4Mozirc_L/view?usp=drive_link | S12: 2024 | T12: https://drive.google.com/file/d/12MjGV739OVxdOUym7sn516wQM4dv51MR/view?usp=drive_link | U12: 100 | V12: 2024 | W12: 83.07 | X12: 25 | Y12: 2.5 | Z12: 6 | AA12: 7.8 | AB12: 0 | AC12: - | AD12: Small Commercial | AE12: 2220 | AF12: Rooftop, Fixed | AG12: 335.4 | AH12: 10.7 | AI12: 0 | AJ12: No MACRS | AK12: 0 | AL12: - | AM12: - | AN12: - | AO12: - | AP12: - | AQ12: - | AR12: - | AS12: - | AT12: - | AU12: - | AV12: - | AW12: - | AX12: - | AY12: 0 | AZ12: https://drive.google.com/file/d/1jrpu40DzxTFYY6LiD8LJLWmYTYBMVds2/view?usp=drive_link | BA12: 1 | BB12: 10 | BC12: No MACRS | BD12: 0 | BE12: LT Heat Pumps, net metering, full cost, 6% escalation | BF12: 80 | BG12: 35 | BH12: - | BI12: 74069 | BK12: - | CE12: 786695
A13: LT Heat Pumps, net metering, full cost | D13: 8 | E13: LT Heat Pumps, net metering, full cost, 8% escalation | F13: ASHP, PV | G13: 2: Full replacement heating | H13: LT Heat Pumps, net metering, full cost, 8% escalation | I13: 47.85212, -122.56923 | J13: Roofspace only | K13: 8000 | L13: PSE: 25 | M13: Net metering | N13: 100 | O13: - | P13: propane | Q13: 2.01 | R13: https://drive.google.com/file/d/1Xl5WOtWsJzfbC-Y8nCxkp4Y4Mozirc_L/view?usp=drive_link | S13: 2024 | T13: https://drive.google.com/file/d/12MjGV739OVxdOUym7sn516wQM4dv51MR/view?usp=drive_link | U13: 100 | V13: 2024 | W13: 83.07 | X13: 25 | Y13: 2.5 | Z13: 8 | AA13: 7.8 | AB13: 0 | AC13: - | AD13: Small Commercial | AE13: 2220 | AF13: Rooftop, Fixed | AG13: 335.4 | AH13: 10.7 | AI13: 0 | AJ13: No MACRS | AK13: 0 | AL13: - | AM13: - | AN13: - | AO13: - | AP13: - | AQ13: - | AR13: - | AS13: - | AT13: - | AU13: - | AV13: - | AW13: - | AX13: - | AY13: 0 | AZ13: https://drive.google.com/file/d/1jrpu40DzxTFYY6LiD8LJLWmYTYBMVds2/view?usp=drive_link | BA13: 1 | BB13: 10 | BC13: No MACRS | BD13: 0 | BE13: LT Heat Pumps, net metering, full cost, 8% escalation | BF13: 80 | BG13: 35 | BH13: - | BI13: -1395 | BK13: - | CE13: 971906
A14: LT Heat Pumps, net metering, full cost | D14: 10 | E14: LT Heat Pumps, net metering, full cost, 10% escalation | F14: ASHP, PV | G14: 2: Full replacement heating | H14: LT Heat Pumps, net metering, full cost, 10% escalation | I14: 47.85212, -122.56923 | J14: Roofspace only | K14: 8000 | L14: PSE: 25 | M14: Net metering | N14: 100 | O14: - | P14: propane | Q14: 2.01 | R14: https://drive.google.com/file/d/1Xl5WOtWsJzfbC-Y8nCxkp4Y4Mozirc_L/view?usp=drive_link | S14: 2024 | T14: https://drive.google.com/file/d/12MjGV739OVxdOUym7sn516wQM4dv51MR/view?usp=drive_link | U14: 100 | V14: 2024 | W14: 83.07 | X14: 25 | Y14: 2.5 | Z14: 10 | AA14: 7.8 | AB14: 0 | AC14: - | AD14: Small Commercial | AE14: 2220 | AF14: Rooftop, Fixed | AG14: 335.4 | AH14: 10.7 | AI14: 0 | AJ14: No MACRS | AK14: 0 | AL14: - | AM14: - | AN14: - | AO14: - | AP14: - | AQ14: - | AR14: - | AS14: - | AT14: - | AU14: - | AV14: - | AW14: - | AX14: - | AY14: 0 | AZ14: https://drive.google.com/file/d/1jrpu40DzxTFYY6LiD8LJLWmYTYBMVds2/view?usp=drive_link | BA14: 1 | BB14: 10 | BC14: No MACRS | BD14: 0 | BE14: LT Heat Pumps, net metering, full cost, 10% escalation | BF14: 80 | BG14: 35 | BH14: - | BI14: -106592 | BK14: - | CE14: 1229423
A16: LT Heat Pumps, net billing, full cost | D16: 0 | E16: LT Heat Pumps, net billing, full cost, 0% escalation | F16: ASHP, PV | G16: 2: Full replacement heating | H16: LT Heat Pumps, net billing, full cost, 0% escalation | I16: 47.85212, -122.56923 | J16: Roofspace only | K16: 8000 | L16: PSE: 25 | M16: Net billing | N16: - | O16: 0.06713 | P16: propane | Q16: 2.01 | R16: https://drive.google.com/file/d/1Xl5WOtWsJzfbC-Y8nCxkp4Y4Mozirc_L/view?usp=drive_link | S16: 2024 | T16: https://drive.google.com/file/d/12MjGV739OVxdOUym7sn516wQM4dv51MR/view?usp=drive_link | U16: 100 | V16: 2024 | W16: 83.07 | X16: 25 | Y16: 2.5 | Z16: 0 | AA16: 7.8 | AB16: 0 | AC16: - | AD16: Small Commercial | AE16: 2220 | AF16: Rooftop, Fixed | AG16: 335.4 | AH16: 10.7 | AI16: 0 | AJ16: No MACRS | AK16: 0 | AL16: - | AM16: - | AN16: - | AO16: - | AP16: - | AQ16: - | AR16: - | AS16: - | AT16: - | AU16: - | AV16: - | AW16: - | AX16: - | AY16: 0 | AZ16: https://drive.google.com/file/d/1jrpu40DzxTFYY6LiD8LJLWmYTYBMVds2/view?usp=drive_link | BA16: 1 | BB16: 10 | BC16: No MACRS | BD16: 0 | BE16: LT Heat Pumps, net billing, full cost, 0% escalation | BF16: 0 | BG16: 35 | BH16: - | BI16: 243117 | BK16: - | CE16: 438012
A17: LT Heat Pumps, net billing, full cost | D17: 2 | E17: LT Heat Pumps, net billing, full cost, 2% escalation | F17: ASHP, PV | G17: 2: Full replacement heating | H17: LT Heat Pumps, net billing, full cost, 2% escalation | I17: 47.85212, -122.56923 | J17: Roofspace only | K17: 8000 | L17: PSE: 25 | M17: Net billing | N17: - | O17: 0.06713 | P17: propane | Q17: 2.01 | R17: https://drive.google.com/file/d/1Xl5WOtWsJzfbC-Y8nCxkp4Y4Mozirc_L/view?usp=drive_link | S17: 2024 | T17: https://drive.google.com/file/d/12MjGV739OVxdOUym7sn516wQM4dv51MR/view?usp=drive_link | U17: 100 | V17: 2024 | W17: 83.07 | X17: 25 | Y17: 2.5 | Z17: 2 | AA17: 7.8 | AB17: 0 | AC17: - | AD17: Small Commercial | AE17: 2220 | AF17: Rooftop, Fixed | AG17: 335.4 | AH17: 10.7 | AI17: 0 | AJ17: No MACRS | AK17: 0 | AL17: - | AM17: - | AN17: - | AO17: - | AP17: - | AQ17: - | AR17: - | AS17: - | AT17: - | AU17: - | AV17: - | AW17: - | AX17: - | AY17: 0 | AZ17: https://drive.google.com/file/d/1jrpu40DzxTFYY6LiD8LJLWmYTYBMVds2/view?usp=drive_link | BA17: 1 | BB17: 10 | BC17: No MACRS | BD17: 0 | BE17: LT Heat Pumps, net billing, full cost, 2% escalation | BF17: 12 | BG17: 35 | BH17: - | BI17: 167461 | BK17: - | CE17: 556059
A18: LT Heat Pumps, net billing, full cost | D18: 4 | E18: LT Heat Pumps, net billing, full cost, 4% escalation | F18: ASHP, PV | G18: 2: Full replacement heating | H18: LT Heat Pumps, net billing, full cost, 4% escalation | I18: 47.85212, -122.56923 | J18: Roofspace only | K18: 8000 | L18: PSE: 25 | M18: Net billing | N18: - | O18: 0.06713 | P18: propane | Q18: 2.01 | R18: https://drive.google.com/file/d/1Xl5WOtWsJzfbC-Y8nCxkp4Y4Mozirc_L/view?usp=drive_link | S18: 2024 | T18: https://drive.google.com/file/d/12MjGV739OVxdOUym7sn516wQM4dv51MR/view?usp=drive_link | U18: 100 | V18: 2024 | W18: 83.07 | X18: 25 | Y18: 2.5 | Z18: 4 | AA18: 7.8 | AB18: 0 | AC18: - | AD18: Small Commercial | AE18: 2220 | AF18: Rooftop, Fixed | AG18: 335.4 | AH18: 10.7 | AI18: 0 | AJ18: No MACRS | AK18: 0 | AL18: - | AM18: - | AN18: - | AO18: - | AP18: - | AQ18: - | AR18: - | AS18: - | AT18: - | AU18: - | AV18: - | AW18: - | AX18: - | AY18: 0 | AZ18: https://drive.google.com/file/d/1jrpu40DzxTFYY6LiD8LJLWmYTYBMVds2/view?usp=drive_link | BA18: 1 | BB18: 10 | BC18: No MACRS | BD18: 0 | BE18: LT Heat Pumps, net billing, full cost, 4% escalation | BF18: 23 | BG18: 35 | BH18: - | BI18: 75793 | BK18: - | CE18: 705545
A19: LT Heat Pumps, net billing, full cost | D19: 6 | E19: LT Heat Pumps, net billing, full cost, 6% escalation | F19: ASHP, PV | G19: 2: Full replacement heating | H19: LT Heat Pumps, net billing, full cost, 6% escalation | I19: 47.85212, -122.56923 | J19: Roofspace only | K19: 8000 | L19: PSE: 25 | M19: Net billing | N19: - | O19: 0.06713 | P19: propane | Q19: 2.01 | R19: https://drive.google.com/file/d/1Xl5WOtWsJzfbC-Y8nCxkp4Y4Mozirc_L/view?usp=drive_link | S19: 2024 | T19: https://drive.google.com/file/d/12MjGV739OVxdOUym7sn516wQM4dv51MR/view?usp=drive_link | U19: 100 | V19: 2024 | W19: 83.07 | X19: 25 | Y19: 2.5 | Z19: 6 | AA19: 7.8 | AB19: 0 | AC19: - | AD19: Small Commercial | AE19: 2220 | AF19: Rooftop, Fixed | AG19: 335.4 | AH19: 10.7 | AI19: 0 | AJ19: No MACRS | AK19: 0 | AL19: - | AM19: - | AN19: - | AO19: - | AP19: - | AQ19: - | AR19: - | AS19: - | AT19: - | AU19: - | AV19: - | AW19: - | AX19: - | AY19: 0 | AZ19: https://drive.google.com/file/d/1jrpu40DzxTFYY6LiD8LJLWmYTYBMVds2/view?usp=drive_link | BA19: 1 | BB19: 10 | BC19: No MACRS | BD19: 0 | BE19: LT Heat Pumps, net billing, full cost, 6% escalation | BF19: 55 | BG19: 35 | BH19: - | BI19: -33927 | BK19: - | CE19: 894691
A20: LT Heat Pumps, net billing, full cost | D20: 8 | E20: LT Heat Pumps, net billing, full cost, 8% escalation | F20: ASHP, PV | G20: 2: Full replacement heating | H20: LT Heat Pumps, net billing, full cost, 8% escalation | I20: 47.85212, -122.56923 | J20: Roofspace only | K20: 8000 | L20: PSE: 25 | M20: Net billing | N20: - | O20: 0.06713 | P20: propane | Q20: 2.01 | R20: https://drive.google.com/file/d/1Xl5WOtWsJzfbC-Y8nCxkp4Y4Mozirc_L/view?usp=drive_link | S20: 2024 | T20: https://drive.google.com/file/d/12MjGV739OVxdOUym7sn516wQM4dv51MR/view?usp=drive_link | U20: 100 | V20: 2024 | W20: 83.07 | X20: 25 | Y20: 2.5 | Z20: 8 | AA20: 7.8 | AB20: 0 | AC20: - | AD20: Small Commercial | AE20: 2220 | AF20: Rooftop, Fixed | AG20: 335.4 | AH20: 10.7 | AI20: 0 | AJ20: No MACRS | AK20: 0 | AL20: - | AM20: - | AN20: - | AO20: - | AP20: - | AQ20: - | AR20: - | AS20: - | AT20: - | AU20: - | AV20: - | AW20: - | AX20: - | AY20: 0 | AZ20: https://drive.google.com/file/d/1jrpu40DzxTFYY6LiD8LJLWmYTYBMVds2/view?usp=drive_link | BA20: 1 | BB20: 10 | BC20: No MACRS | BD20: 0 | BE20: LT Heat Pumps, net billing, full cost, 8% escalation | BF20: 80 | BG20: 35 | BH20: - | BI20: -147606 | BK20: - | CE20: 1118116
A21: LT Heat Pumps, net billing, full cost | D21: 10 | E21: LT Heat Pumps, net billing, full cost, 10% escalation | F21: ASHP, PV | G21: 2: Full replacement heating | H21: LT Heat Pumps, net billing, full cost, 10% escalation | I21: 47.85212, -122.56923 | J21: Roofspace only | K21: 8000 | L21: PSE: 25 | M21: Net billing | N21: - | O21: 0.06713 | P21: propane | Q21: 2.01 | R21: https://drive.google.com/file/d/1Xl5WOtWsJzfbC-Y8nCxkp4Y4Mozirc_L/view?usp=drive_link | S21: 2024 | T21: https://drive.google.com/file/d/12MjGV739OVxdOUym7sn516wQM4dv51MR/view?usp=drive_link | U21: 100 | V21: 2024 | W21: 83.07 | X21: 25 | Y21: 2.5 | Z21: 10 | AA21: 7.8 | AB21: 0 | AC21: - | AD21: Small Commercial | AE21: 2220 | AF21: Rooftop, Fixed | AG21: 335.4 | AH21: 10.7 | AI21: 0 | AJ21: No MACRS | AK21: 0 | AL21: - | AM21: - | AN21: - | AO21: - | AP21: - | AQ21: - | AR21: - | AS21: - | AT21: - | AU21: - | AV21: - | AW21: - | AX21: - | AY21: 0 | AZ21: https://drive.google.com/file/d/1jrpu40DzxTFYY6LiD8LJLWmYTYBMVds2/view?usp=drive_link | BA21: 1 | BB21: 10 | BC21: No MACRS | BD21: 0 | BE21: LT Heat Pumps, net billing, full cost, 10% escalation | BF21: 80 | BG21: 35 | BH21: - | BI21: -301704 | BK21: - | CE21: 1424534
A25: If direct equation they clearly follow, you don't need to bother with running all - would also be useful to plot as a curve
A26: Life Cycle Savings
A27: Electricity cost escalation rate, nominal (%/year) | B27: No PV | C27: Net metering | D27: Net billing
A28: 0 | B28: 243117 | C28: 243117 | D28: 243117
A29: 2 | B29: 165443 | C29: 169396 | D29: 167461
A30: 4 | B30: 59505 | C30: 128419 | D30: 75793
A31: 6 | B31: -86028 | C31: 74069 | D31: -33927
A32: 8 | B32: -287117 | C32: -1395 | D32: -147606
A33: 10 | B33: -566212 | C33: -106592 | D33: -301704
A34: Life Cycle Costs
A35: Electricity cost escalation rate, nominal (%/year) | B35: No PV | C35: Net metering | D35: Net billing
A36: 0 | B36: =CE2+110000 -> 548012 | C36: =CE9+110000 -> 548012 | D36: =CE16+110000 -> 548012
A37: 2 | B37: =CE3+110000 -> 668078 | C37: =CE10+110000 -> 664124 | D37: =CE17+110000 -> 666059
A38: 4 | B38: =CE4+110000 -> 831833 | C38: =CE11+110000 -> 762918 | D38: =CE18+110000 -> 815545
A39: 6 | B39: =CE5+110000 -> 1056792 | C39: =CE12+110000 -> 896695 | D39: =CE19+110000 -> 1004691
A40: 8 | B40: =CE6+110000 -> 1367627 | C40: =CE13+110000 -> 1081906 | D40: =CE20+110000 -> 1228116
A41: 10 | B41: =CE7+110000 -> 1799043 | C41: =CE14+110000 -> 1339423 | D41: =CE21+110000 -> 1534534
A43: Electricity cost escalation rate, nominal (%/year) | B43: Net metering | C43: Net billing
A44: 0 | B44: 0 | C44: 0
A45: 2 | B45: 37 | C45: 12
A46: 4 | B46: 80 | C46: 23
A47: 6 | B47: 80 | C47: 55
A48: 8 | B48: 80 | C48: 80
A49: 10 | B49: 80 | C49: 80
A52: Scenario | B52: Net metering | C52: Net billing | D52: Annual existing heating system fuel cost ($/gallon) | E52: REopt Results: | F52: Select Technologies to Evaluate | G52: Air-Source Heat Pump configuration | H52: Evaluation name | I52: Site location (latitude, longitude) | J52: PV & wind space available | K52: Roofspace available (sq ft) | L52: Electricity rate | M52: Compensation type | N52: Net metering system size limit (kW) | O52: Net billing compensation for all exports ($/kWh) | P52: Existing heating system fuel type | Q52: Annual existing heating system fuel cost ($/gallon) | R52: Upload typical electric load profile | S52: Year of load profile | T52: Upload typical heating load profile | U52: Space heating load percent of total heating load (%) | V52: Year of load profile | W52: Existing heating system efficiency (% HHV-basis) | X52: Analysis period (years) | Y52: Host discount rate, nominal (%) | Z52: Electricity cost escalation rate, nominal (%/year) | AA52: Existing heating system fuel cost escalation rate, nominal (%/year) | AB52: Host effective tax rate (%) | AC52: Emissions | AD52: Size class | AE52: System capital cost ($/kW-DC) | AF52: Array type | AG52: Array azimuth (deg) | AH52: Array tilt (deg) | AI52: Federal Incentive based on percentage of cost (%) | AJ52: MACRS schedule | AK52: MACRS bonus depreciation | AL52: Energy capacity cost ($/kWh) | AM52: Power capacity cost ($/kW) | AN52: Constant cost ($) | AO52: Minimum energy capacity (kWh) | AP52: Maximum energy capacity (kWh) | AQ52: Energy capacity replacement cost ($/kWh) | AR52: Power capacity replacement cost ($/kWh) | AS52: Constant replacement cost ($) | AT52: Minimum power capacity (kW) | AU52: Maximum power capacity (kW) | AV52: Federal Incentive based on percentage of cost (%) | AW52: MACRS schedule | AX52: MACRS bonus depreciation | AY52: Total installed cost ($/ton) | AZ52: Upload COP Table | BA52: Heat pump capacity sizing factor | BB52: Resistive heating back-up temperature threshold (°F) | BC52: MACRS schedule | BD52: MACRS bonus depreciation | BE52: REopt Results: | BF52: Optimized PV size (kW) | BG52: Optimized ASHP size (tonnes) | BH52: Optimized Battery Power and Capacity (kW/kWh) | BI52: Potential Life Cycle Savings | BJ52: Avg. Annual Grid Serving Load (kWh) | BK52: Avg. Annual Grid Charging Battery (kWh) | BL52: Avg. Annual Grid Total Electricity Consumed (kWh) | BM52: Avg. Annual PV Serving Load (kWh) | BN52: Avg. Annual PV Charging Battery (kWh) | BO52: Avg. Annual PV Exported to Grid (kWh) | BP52: Avg. Annual PV Curtailment (kWh) | BQ52: Avg. Annual PV Total Electricity Produced (kWh) | BR52: Avg. Annual Battery Serving Load (kWh) | BS52: Non-PV Average Annual Energy Supplied from Grid (kWh) | BT52: PV System Average Annual Energy Supplied from Grid (kWh) | BU52: Difference in Avg. Annual Energy Supplied from Grid | BV52: w/PV Annual Renewable Electricity (% of electricity consumed) | BW52: PV Avoided CO2e Emissions throughout Analysis Period | BX52: Non-PV Total Year 1 Elec Cost - Pre-Tax | BY52: PV Total Year 1 Elec Cost - Pre-Tax | BZ52: Difference Total Year 1 Elec Cost | CA52: Non-PV Total Full Period Elec Cost | CB52: PV Total Full Period Elec Cost | CC52: Difference in Full Period Utility Cost | CD52: BAU Total Life Cycle Costs | CE52: New Total Life Cycle Costs | CF52: Difference in Total life cycle costs | CG52: w/PV/ Battery Net Present Value | CH52: Payback Period for PV /Battery (yrs)
A53: LT Heat Pumps, no PV, full cost | D53: 1.5 | E53: LT Heat Pumps, no PV, full cost, $1.50 propane rate | REopt Web Tool | REopt Energy Integration & Optimization | NLR | F53: ASHP | G53: 2: Full replacement heating | H53: LT Heat Pumps, no PV, full cost, $1.50 propane rate | I53: 47.85212, -122.56923 | J53: Roofspace only | K53: 8000 | L53: PSE: 24 | M53: - | N53: 100 | O53: - | P53: propane | Q53: 1.5 | R53: https://drive.google.com/file/d/1Xl5WOtWsJzfbC-Y8nCxkp4Y4Mozirc_L/view?usp=drive_link | S53: 2024 | T53: https://drive.google.com/file/d/12MjGV739OVxdOUym7sn516wQM4dv51MR/view?usp=drive_link | U53: 100 | V53: 2024 | W53: 83.07 | X53: 25 | Y53: 2.5 | Z53: 6 | AA53: 7.8 | AB53: 0 | AC53: - | AD53: Small Commercial | AE53: - | AF53: Rooftop, Fixed | AG53: 335.4 | AH53: 10.7 | AI53: 0 | AJ53: No MACRS | AK53: 0 | AL53: - | AM53: - | AN53: - | AO53: - | AP53: - | AQ53: - | AR53: - | AS53: - | AT53: - | AU53: - | AV53: - | AW53: - | AX53: - | AY53: 0 | AZ53: https://drive.google.com/file/d/1jrpu40DzxTFYY6LiD8LJLWmYTYBMVds2/view?usp=drive_link | BA53: 1 | BB53: 10 | BC53: No MACRS | BD53: 0 | BE53: LT Heat Pumps, net metering, full cost, 0% escalation | BF53: - | BG53: 35 | BH53: - | BI53: -219612 | BJ53: - | BK53: - | BL53: - | BM53: - | BN53: - | BO53: - | BP53: - | BQ53: - | BR53: - | CD53: 748333 | CE53: 946792
A54: LT Heat Pumps, no PV, full cost | D54: 1.75 | E54: LT Heat Pumps, no PV, full cost, $1.75 propane rate | REopt Web Tool | REopt Energy Integration & Optimization | NLR | F54: ASHP | G54: 2: Full replacement heating | H54: LT Heat Pumps, no PV, full cost, $1.75 propane rate | I54: 47.85212, -122.56923 | J54: Roofspace only | K54: 8000 | L54: PSE: 24 | M54: - | N54: 100 | O54: - | P54: propane | Q54: 1.75 | R54: https://drive.google.com/file/d/1Xl5WOtWsJzfbC-Y8nCxkp4Y4Mozirc_L/view?usp=drive_link | S54: 2024 | T54: https://drive.google.com/file/d/12MjGV739OVxdOUym7sn516wQM4dv51MR/view?usp=drive_link | U54: 100 | V54: 2024 | W54: 83.07 | X54: 25 | Y54: 2.5 | Z54: 6 | AA54: 7.8 | AB54: 0 | AC54: - | AD54: Small Commercial | AE54: - | AF54: Rooftop, Fixed | AG54: 335.4 | AH54: 10.7 | AI54: 0 | AJ54: No MACRS | AK54: 0 | AL54: - | AM54: - | AN54: - | AO54: - | AP54: - | AQ54: - | AR54: - | AS54: - | AT54: - | AU54: - | AV54: - | AW54: - | AX54: - | AY54: 0 | AZ54: https://drive.google.com/file/d/1jrpu40DzxTFYY6LiD8LJLWmYTYBMVds2/view?usp=drive_link | BA54: 1 | BB54: 10 | BC54: No MACRS | BD54: 0 | BE54: LT Heat Pumps, net metering, full cost, 2% escalation | BF54: - | BG54: 35 | BH54: - | BI54: -154130 | BJ54: - | BK54: - | BL54: - | BM54: - | BN54: - | BO54: - | BP54: - | BQ54: - | BR54: - | CD54: 813816 | CE54: 946792
A55: LT Heat Pumps, no PV, full cost | D55: 2.01 | E55: LT Heat Pumps, no PV, full cost, $2.00 propane rate | REopt Web Tool | REopt Energy Integration & Optimization | NLR | F55: ASHP | G55: 2: Full replacement heating | H55: LT Heat Pumps, no PV, full cost, $2.00 propane rate | I55: 47.85212, -122.56923 | J55: Roofspace only | K55: 8000 | L55: PSE: 24 | M55: - | N55: 100 | O55: - | P55: propane | Q55: 2 | R55: https://drive.google.com/file/d/1Xl5WOtWsJzfbC-Y8nCxkp4Y4Mozirc_L/view?usp=drive_link | S55: 2024 | T55: https://drive.google.com/file/d/12MjGV739OVxdOUym7sn516wQM4dv51MR/view?usp=drive_link | U55: 100 | V55: 2024 | W55: 83.07 | X55: 25 | Y55: 2.5 | Z55: 6 | AA55: 7.8 | AB55: 0 | AC55: - | AD55: Small Commercial | AE55: - | AF55: Rooftop, Fixed | AG55: 335.4 | AH55: 10.7 | AI55: 0 | AJ55: No MACRS | AK55: 0 | AL55: - | AM55: - | AN55: - | AO55: - | AP55: - | AQ55: - | AR55: - | AS55: - | AT55: - | AU55: - | AV55: - | AW55: - | AX55: - | AY55: 0 | AZ55: https://drive.google.com/file/d/1jrpu40DzxTFYY6LiD8LJLWmYTYBMVds2/view?usp=drive_link | BA55: 1 | BB55: 10 | BC55: No MACRS | BD55: 0 | BE55: LT Heat Pumps, net metering, full cost, 4% escalation | BF55: - | BG55: 35 | BH55: - | BI55: -88647 | BJ55: - | BK55: - | BL55: - | BM55: - | BN55: - | BO55: - | BP55: - | BQ55: - | BR55: - | CD55: 881918 | CE55: 946792
A56: LT Heat Pumps, no PV, full cost | D56: 2.25 | E56: LT Heat Pumps, no PV, full cost, $2.25 propane rate | REopt Web Tool | REopt Energy Integration & Optimization | NLR | F56: ASHP | G56: 2: Full replacement heating | H56: LT Heat Pumps, no PV, full cost, $2.25 propane rate | I56: 47.85212, -122.56923 | J56: Roofspace only | K56: 8000 | L56: PSE: 24 | M56: - | N56: 100 | O56: - | P56: propane | Q56: 2.25 | R56: https://drive.google.com/file/d/1Xl5WOtWsJzfbC-Y8nCxkp4Y4Mozirc_L/view?usp=drive_link | S56: 2024 | T56: https://drive.google.com/file/d/12MjGV739OVxdOUym7sn516wQM4dv51MR/view?usp=drive_link | U56: 100 | V56: 2024 | W56: 83.07 | X56: 25 | Y56: 2.5 | Z56: 6 | AA56: 7.8 | AB56: 0 | AC56: - | AD56: Small Commercial | AE56: - | AF56: Rooftop, Fixed | AG56: 335.4 | AH56: 10.7 | AI56: 0 | AJ56: No MACRS | AK56: 0 | AL56: - | AM56: - | AN56: - | AO56: - | AP56: - | AQ56: - | AR56: - | AS56: - | AT56: - | AU56: - | AV56: - | AW56: - | AX56: - | AY56: 0 | AZ56: https://drive.google.com/file/d/1jrpu40DzxTFYY6LiD8LJLWmYTYBMVds2/view?usp=drive_link | BA56: 1 | BB56: 10 | BC56: No MACRS | BD56: 0 | BE56: LT Heat Pumps, net metering, full cost, 6% escalation | BF56: - | BG56: 35 | BH56: - | BI56: -23165 | BJ56: - | BK56: - | BL56: - | BM56: - | BN56: - | BO56: - | BP56: - | BQ56: - | BR56: - | CD56: 944781 | CE56: 946792
A57: LT Heat Pumps, no PV, full cost | D57: 2.5 | E57: LT Heat Pumps, no PV, full cost, $2.50 propane rate | REopt Web Tool | REopt Energy Integration & Optimization | NLR | F57: ASHP | G57: 2: Full replacement heating | H57: LT Heat Pumps, no PV, full cost, $2.50 propane rate | I57: 47.85212, -122.56923 | J57: Roofspace only | K57: 8000 | L57: PSE: 24 | M57: - | N57: 100 | O57: - | P57: propane | Q57: 2.5 | R57: https://drive.google.com/file/d/1Xl5WOtWsJzfbC-Y8nCxkp4Y4Mozirc_L/view?usp=drive_link | S57: 2024 | T57: https://drive.google.com/file/d/12MjGV739OVxdOUym7sn516wQM4dv51MR/view?usp=drive_link | U57: 100 | V57: 2024 | W57: 83.07 | X57: 25 | Y57: 2.5 | Z57: 6 | AA57: 7.8 | AB57: 0 | AC57: - | AD57: Small Commercial | AE57: - | AF57: Rooftop, Fixed | AG57: 335.4 | AH57: 10.7 | AI57: 0 | AJ57: No MACRS | AK57: 0 | AL57: - | AM57: - | AN57: - | AO57: - | AP57: - | AQ57: - | AR57: - | AS57: - | AT57: - | AU57: - | AV57: - | AW57: - | AX57: - | AY57: 0 | AZ57: https://drive.google.com/file/d/1jrpu40DzxTFYY6LiD8LJLWmYTYBMVds2/view?usp=drive_link | BA57: 1 | BB57: 10 | BC57: No MACRS | BD57: 0 | BE57: LT Heat Pumps, net metering, full cost, 8% escalation | BF57: - | BG57: 35 | BH57: - | BI57: 42318 | BJ57: - | BK57: - | BL57: - | BM57: - | BN57: - | BO57: - | BP57: - | BQ57: - | BR57: - | CD57: 1010264 | CE57: 946792
A58: LT Heat Pumps, no PV, full cost | D58: 2.75 | E58: LT Heat Pumps, no PV, full cost, $2.75 propane rate | F58: ASHP | G58: 2: Full replacement heating | H58: LT Heat Pumps, no PV, full cost, $2.75 propane rate | I58: 47.85212, -122.56923 | J58: Roofspace only | K58: 8000 | L58: PSE: 24 | M58: - | N58: 100 | O58: - | P58: propane | Q58: 2.75 | R58: https://drive.google.com/file/d/1Xl5WOtWsJzfbC-Y8nCxkp4Y4Mozirc_L/view?usp=drive_link | S58: 2024 | T58: https://drive.google.com/file/d/12MjGV739OVxdOUym7sn516wQM4dv51MR/view?usp=drive_link | U58: 100 | V58: 2024 | W58: 83.07 | X58: 25 | Y58: 2.5 | Z58: 6 | AA58: 7.8 | AB58: 0 | AC58: - | AD58: Small Commercial | AE58: - | AF58: Rooftop, Fixed | AG58: 335.4 | AH58: 10.7 | AI58: 0 | AJ58: No MACRS | AK58: 0 | AL58: - | AM58: - | AN58: - | AO58: - | AP58: - | AQ58: - | AR58: - | AS58: - | AT58: - | AU58: - | AV58: - | AW58: - | AX58: - | AY58: 0 | AZ58: https://drive.google.com/file/d/1jrpu40DzxTFYY6LiD8LJLWmYTYBMVds2/view?usp=drive_link | BA58: 1 | BB58: 10 | BC58: No MACRS | BD58: 0 | BE58: LT Heat Pumps, net metering, full cost, 10% escalation | BF58: - | BG58: 35 | BH58: - | BI58: 107800 | BJ58: - | BK58: - | BL58: - | BM58: - | BN58: - | BO58: - | BP58: - | BQ58: - | BR58: - | CD58: 1075746 | CE58: 946792
A60: LT Heat Pumps, net metering, full cost | D60: 1.5 | E60: LT Heat Pumps, net metering, full cost, $1.50 propane rate | F60: ASHP, PV | G60: 2: Full replacement heating | H60: LT Heat Pumps, net metering, full cost, $1.50 propane rate | I60: 47.85212, -122.56923 | J60: Roofspace only | K60: 8000 | L60: PSE: 25 | M60: Net metering | N60: 100 | O60: - | P60: propane | Q60: 1.5 | R60: https://drive.google.com/file/d/1Xl5WOtWsJzfbC-Y8nCxkp4Y4Mozirc_L/view?usp=drive_link | S60: 2024 | T60: https://drive.google.com/file/d/12MjGV739OVxdOUym7sn516wQM4dv51MR/view?usp=drive_link | U60: 100 | V60: 2024 | W60: 83.07 | X60: 25 | Y60: 2.5 | Z60: 6 | AA60: 7.8 | AB60: 0 | AC60: - | AD60: Small Commercial | AE60: 2220 | AF60: Rooftop, Fixed | AG60: 335.4 | AH60: 10.7 | AI60: 0 | AJ60: No MACRS | AK60: 0 | AL60: - | AM60: - | AN60: - | AO60: - | AP60: - | AQ60: - | AR60: - | AS60: - | AT60: - | AU60: - | AV60: - | AW60: - | AX60: - | AY60: 0 | AZ60: https://drive.google.com/file/d/1jrpu40DzxTFYY6LiD8LJLWmYTYBMVds2/view?usp=drive_link | BA60: 1 | BB60: 10 | BC60: No MACRS | BD60: 0 | BE60: $3,900 | REopt Web Tool | REopt Energy Integration & Optimization | NLR | BF60: 80 | BG60: 35 | BH60: - | BI60: -59515 | BK60: - | CD60: 727179 | CE60: 786695
A61: LT Heat Pumps, net metering, full cost | D61: 1.75 | E61: LT Heat Pumps, net metering, full cost, $1.75 propane rate | F61: ASHP, PV | G61: 2: Full replacement heating | H61: LT Heat Pumps, net metering, full cost, $1.75 propane rate | I61: 47.85212, -122.56923 | J61: Roofspace only | K61: 8000 | L61: PSE: 25 | M61: Net metering | N61: 100 | O61: - | P61: propane | Q61: 1.75 | R61: https://drive.google.com/file/d/1Xl5WOtWsJzfbC-Y8nCxkp4Y4Mozirc_L/view?usp=drive_link | S61: 2024 | T61: https://drive.google.com/file/d/12MjGV739OVxdOUym7sn516wQM4dv51MR/view?usp=drive_link | U61: 100 | V61: 2024 | W61: 83.07 | X61: 25 | Y61: 2.5 | Z61: 6 | AA61: 7.8 | AB61: 0 | AC61: - | AD61: Small Commercial | AE61: 2220 | AF61: Rooftop, Fixed | AG61: 335.4 | AH61: 10.7 | AI61: 0 | AJ61: No MACRS | AK61: 0 | AL61: - | AM61: - | AN61: - | AO61: - | AP61: - | AQ61: - | AR61: - | AS61: - | AT61: - | AU61: - | AV61: - | AW61: - | AX61: - | AY61: 0 | AZ61: https://drive.google.com/file/d/1jrpu40DzxTFYY6LiD8LJLWmYTYBMVds2/view?usp=drive_link | BA61: 1 | BB61: 10 | BC61: No MACRS | BD61: 0 | BE61: $4,100 | REopt Web Tool | REopt Energy Integration & Optimization | NLR | BF61: 80 | BG61: 35 | BH61: - | BI61: 5967 | BK61: - | CD61: 792662 | CE61: 786695
A62: LT Heat Pumps, net metering, full cost | D62: 2 | E62: LT Heat Pumps, net metering, full cost, $2.00 propane rate | F62: ASHP, PV | G62: 2: Full replacement heating | H62: LT Heat Pumps, net metering, full cost, $2.00 propane rate | I62: 47.85212, -122.56923 | J62: Roofspace only | K62: 8000 | L62: PSE: 25 | M62: Net metering | N62: 100 | O62: - | P62: propane | Q62: 2 | R62: https://drive.google.com/file/d/1Xl5WOtWsJzfbC-Y8nCxkp4Y4Mozirc_L/view?usp=drive_link | S62: 2024 | T62: https://drive.google.com/file/d/12MjGV739OVxdOUym7sn516wQM4dv51MR/view?usp=drive_link | U62: 100 | V62: 2024 | W62: 83.07 | X62: 25 | Y62: 2.5 | Z62: 6 | AA62: 7.8 | AB62: 0 | AC62: - | AD62: Small Commercial | AE62: 2220 | AF62: Rooftop, Fixed | AG62: 335.4 | AH62: 10.7 | AI62: 0 | AJ62: No MACRS | AK62: 0 | AL62: - | AM62: - | AN62: - | AO62: - | AP62: - | AQ62: - | AR62: - | AS62: - | AT62: - | AU62: - | AV62: - | AW62: - | AX62: - | AY62: 0 | AZ62: https://drive.google.com/file/d/1jrpu40DzxTFYY6LiD8LJLWmYTYBMVds2/view?usp=drive_link | BA62: 1 | BB62: 10 | BC62: No MACRS | BD62: 0 | BE62: $4,300 | REopt Web Tool | REopt Energy Integration & Optimization | NLR | BF62: 80 | BG62: 35 | BH62: - | BI62: 71450 | BK62: - | CD62: 858145 | CE62: 786695
A63: LT Heat Pumps, net metering, full cost | D63: 2.25 | E63: LT Heat Pumps, net metering, full cost, $2.25 propane rate | F63: ASHP, PV | G63: 2: Full replacement heating | H63: LT Heat Pumps, net metering, full cost, $2.25 propane rate | I63: 47.85212, -122.56923 | J63: Roofspace only | K63: 8000 | L63: PSE: 25 | M63: Net metering | N63: 100 | O63: - | P63: propane | Q63: 2.25 | R63: https://drive.google.com/file/d/1Xl5WOtWsJzfbC-Y8nCxkp4Y4Mozirc_L/view?usp=drive_link | S63: 2024 | T63: https://drive.google.com/file/d/12MjGV739OVxdOUym7sn516wQM4dv51MR/view?usp=drive_link | U63: 100 | V63: 2024 | W63: 83.07 | X63: 25 | Y63: 2.5 | Z63: 6 | AA63: 7.8 | AB63: 0 | AC63: - | AD63: Small Commercial | AE63: 2220 | AF63: Rooftop, Fixed | AG63: 335.4 | AH63: 10.7 | AI63: 0 | AJ63: No MACRS | AK63: 0 | AL63: - | AM63: - | AN63: - | AO63: - | AP63: - | AQ63: - | AR63: - | AS63: - | AT63: - | AU63: - | AV63: - | AW63: - | AX63: - | AY63: 0 | AZ63: https://drive.google.com/file/d/1jrpu40DzxTFYY6LiD8LJLWmYTYBMVds2/view?usp=drive_link | BA63: 1 | BB63: 10 | BC63: No MACRS | BD63: 0 | BE63: $4,500 | REopt Web Tool | REopt Energy Integration & Optimization | NLR | BF63: 80 | BG63: 35 | BH63: - | BI63: 136932 | BK63: - | CD63: 923627 | CE63: 786695
A64: LT Heat Pumps, net metering, full cost | D64: 2.5 | E64: LT Heat Pumps, net metering, full cost, $2.50 propane rate | F64: ASHP, PV | G64: 2: Full replacement heating | H64: LT Heat Pumps, net metering, full cost, $2.50 propane rate | I64: 47.85212, -122.56923 | J64: Roofspace only | K64: 8000 | L64: PSE: 25 | M64: Net metering | N64: 100 | O64: - | P64: propane | Q64: 2.5 | R64: https://drive.google.com/file/d/1Xl5WOtWsJzfbC-Y8nCxkp4Y4Mozirc_L/view?usp=drive_link | S64: 2024 | T64: https://drive.google.com/file/d/12MjGV739OVxdOUym7sn516wQM4dv51MR/view?usp=drive_link | U64: 100 | V64: 2024 | W64: 83.07 | X64: 25 | Y64: 2.5 | Z64: 6 | AA64: 7.8 | AB64: 0 | AC64: - | AD64: Small Commercial | AE64: 2220 | AF64: Rooftop, Fixed | AG64: 335.4 | AH64: 10.7 | AI64: 0 | AJ64: No MACRS | AK64: 0 | AL64: - | AM64: - | AN64: - | AO64: - | AP64: - | AQ64: - | AR64: - | AS64: - | AT64: - | AU64: - | AV64: - | AW64: - | AX64: - | AY64: 0 | AZ64: https://drive.google.com/file/d/1jrpu40DzxTFYY6LiD8LJLWmYTYBMVds2/view?usp=drive_link | BA64: 1 | BB64: 10 | BC64: No MACRS | BD64: 0 | BE64: $4,700 | REopt Web Tool | REopt Energy Integration & Optimization | NLR | BF64: 80 | BG64: 35 | BH64: - | BI64: 202415 | BK64: - | CD64: 989110 | CE64: 786695
A65: LT Heat Pumps, net metering, full cost | D65: 2.75 | E65: LT Heat Pumps, net metering, full cost, $2.75 propane rate | F65: ASHP, PV | G65: 2: Full replacement heating | H65: LT Heat Pumps, net metering, full cost, $2.75 propane rate | I65: 47.85212, -122.56923 | J65: Roofspace only | K65: 8000 | L65: PSE: 25 | M65: Net metering | N65: 100 | O65: - | P65: propane | Q65: 2.75 | R65: https://drive.google.com/file/d/1Xl5WOtWsJzfbC-Y8nCxkp4Y4Mozirc_L/view?usp=drive_link | S65: 2024 | T65: https://drive.google.com/file/d/12MjGV739OVxdOUym7sn516wQM4dv51MR/view?usp=drive_link | U65: 100 | V65: 2024 | W65: 83.07 | X65: 25 | Y65: 2.5 | Z65: 6 | AA65: 7.8 | AB65: 0 | AC65: - | AD65: Small Commercial | AE65: 2220 | AF65: Rooftop, Fixed | AG65: 335.4 | AH65: 10.7 | AI65: 0 | AJ65: No MACRS | AK65: 0 | AL65: - | AM65: - | AN65: - | AO65: - | AP65: - | AQ65: - | AR65: - | AS65: - | AT65: - | AU65: - | AV65: - | AW65: - | AX65: - | AY65: 0 | AZ65: https://drive.google.com/file/d/1jrpu40DzxTFYY6LiD8LJLWmYTYBMVds2/view?usp=drive_link | BA65: 1 | BB65: 10 | BC65: No MACRS | BD65: 0 | BE65: $4,700 | REopt Web Tool | REopt Energy Integration & Optimization | NLR | BF65: 80 | BG65: 35 | BH65: - | BI65: 267897 | BK65: - | CD65: 1054592 | CE65: 786695
A67: LT Heat Pumps, net billing, full cost | D67: 1.5 | E67: LT Heat Pumps, net billing, full cost, 0% escalation | F67: ASHP, PV | G67: 2: Full replacement heating | H67: LT Heat Pumps, net billing, full cost, $1.50 propane rate | I67: 47.85212, -122.56923 | J67: Roofspace only | K67: 8000 | L67: PSE: 25 | M67: Net billing | N67: - | O67: 0.06713 | P67: propane | Q67: 1.5 | R67: https://drive.google.com/file/d/1Xl5WOtWsJzfbC-Y8nCxkp4Y4Mozirc_L/view?usp=drive_link | S67: 2024 | T67: https://drive.google.com/file/d/12MjGV739OVxdOUym7sn516wQM4dv51MR/view?usp=drive_link | U67: 100 | V67: 2024 | W67: 83.07 | X67: 25 | Y67: 2.5 | Z67: 6 | AA67: 7.8 | AB67: 0 | AC67: - | AD67: Small Commercial | AE67: 2220 | AF67: Rooftop, Fixed | AG67: 335.4 | AH67: 10.7 | AI67: 0 | AJ67: No MACRS | AK67: 0 | AL67: - | AM67: - | AN67: - | AO67: - | AP67: - | AQ67: - | AR67: - | AS67: - | AT67: - | AU67: - | AV67: - | AW67: - | AX67: - | AY67: 0 | AZ67: https://drive.google.com/file/d/1jrpu40DzxTFYY6LiD8LJLWmYTYBMVds2/view?usp=drive_link | BA67: 1 | BB67: 10 | BC67: No MACRS | BD67: 0 | BE67: LT Heat Pumps, net billing, full cost, 0% escalation | BG67: 35 | BH67: - | BI67: -167512 | BK67: - | CD67: 727179 | CE67: 894691
A68: LT Heat Pumps, net billing, full cost | D68: 1.75 | E68: LT Heat Pumps, net billing, full cost, $1.75 propane rate | F68: ASHP, PV | G68: 2: Full replacement heating | H68: LT Heat Pumps, net billing, full cost, $1.75 propane rate | I68: 47.85212, -122.56923 | J68: Roofspace only | K68: 8000 | L68: PSE: 25 | M68: Net billing | N68: - | O68: 0.06713 | P68: propane | Q68: 1.75 | R68: https://drive.google.com/file/d/1Xl5WOtWsJzfbC-Y8nCxkp4Y4Mozirc_L/view?usp=drive_link | S68: 2024 | T68: https://drive.google.com/file/d/12MjGV739OVxdOUym7sn516wQM4dv51MR/view?usp=drive_link | U68: 100 | V68: 2024 | W68: 83.07 | X68: 25 | Y68: 2.5 | Z68: 6 | AA68: 7.8 | AB68: 0 | AC68: - | AD68: Small Commercial | AE68: 2220 | AF68: Rooftop, Fixed | AG68: 335.4 | AH68: 10.7 | AI68: 0 | AJ68: No MACRS | AK68: 0 | AL68: - | AM68: - | AN68: - | AO68: - | AP68: - | AQ68: - | AR68: - | AS68: - | AT68: - | AU68: - | AV68: - | AW68: - | AX68: - | AY68: 0 | AZ68: https://drive.google.com/file/d/1jrpu40DzxTFYY6LiD8LJLWmYTYBMVds2/view?usp=drive_link | BA68: 1 | BB68: 10 | BC68: No MACRS | BD68: 0 | BE68: LT Heat Pumps, net billing, full cost, 2% escalation | BG68: 35 | BH68: - | BI68: -102029 | BK68: - | CD68: 792662 | CE68: 894691
A69: LT Heat Pumps, net billing, full cost | D69: 2 | E69: LT Heat Pumps, net billing, full cost, $2.00 propane rate | F69: ASHP, PV | G69: 2: Full replacement heating | H69: LT Heat Pumps, net billing, full cost, $2.00 propane rate | I69: 47.85212, -122.56923 | J69: Roofspace only | K69: 8000 | L69: PSE: 25 | M69: Net billing | N69: - | O69: 0.06713 | P69: propane | Q69: 2 | R69: https://drive.google.com/file/d/1Xl5WOtWsJzfbC-Y8nCxkp4Y4Mozirc_L/view?usp=drive_link | S69: 2024 | T69: https://drive.google.com/file/d/12MjGV739OVxdOUym7sn516wQM4dv51MR/view?usp=drive_link | U69: 100 | V69: 2024 | W69: 83.07 | X69: 25 | Y69: 2.5 | Z69: 6 | AA69: 7.8 | AB69: 0 | AC69: - | AD69: Small Commercial | AE69: 2220 | AF69: Rooftop, Fixed | AG69: 335.4 | AH69: 10.7 | AI69: 0 | AJ69: No MACRS | AK69: 0 | AL69: - | AM69: - | AN69: - | AO69: - | AP69: - | AQ69: - | AR69: - | AS69: - | AT69: - | AU69: - | AV69: - | AW69: - | AX69: - | AY69: 0 | AZ69: https://drive.google.com/file/d/1jrpu40DzxTFYY6LiD8LJLWmYTYBMVds2/view?usp=drive_link | BA69: 1 | BB69: 10 | BC69: No MACRS | BD69: 0 | BE69: LT Heat Pumps, net billing, full cost, 4% escalation | BG69: 35 | BH69: - | BI69: -36546 | BK69: - | CD69: 858145 | CE69: 894691
A70: LT Heat Pumps, net billing, full cost | D70: 2.25 | E70: LT Heat Pumps, net billing, full cost, $2.25 propane rate | F70: ASHP, PV | G70: 2: Full replacement heating | H70: LT Heat Pumps, net billing, full cost, $2.25 propane rate | I70: 47.85212, -122.56923 | J70: Roofspace only | K70: 8000 | L70: PSE: 25 | M70: Net billing | N70: - | O70: 0.06713 | P70: propane | Q70: 2.25 | R70: https://drive.google.com/file/d/1Xl5WOtWsJzfbC-Y8nCxkp4Y4Mozirc_L/view?usp=drive_link | S70: 2024 | T70: https://drive.google.com/file/d/12MjGV739OVxdOUym7sn516wQM4dv51MR/view?usp=drive_link | U70: 100 | V70: 2024 | W70: 83.07 | X70: 25 | Y70: 2.5 | Z70: 6 | AA70: 7.8 | AB70: 0 | AC70: - | AD70: Small Commercial | AE70: 2220 | AF70: Rooftop, Fixed | AG70: 335.4 | AH70: 10.7 | AI70: 0 | AJ70: No MACRS | AK70: 0 | AL70: - | AM70: - | AN70: - | AO70: - | AP70: - | AQ70: - | AR70: - | AS70: - | AT70: - | AU70: - | AV70: - | AW70: - | AX70: - | AY70: 0 | AZ70: https://drive.google.com/file/d/1jrpu40DzxTFYY6LiD8LJLWmYTYBMVds2/view?usp=drive_link | BA70: 1 | BB70: 10 | BC70: No MACRS | BD70: 0 | BE70: LT Heat Pumps, net billing, full cost, 6% escalation | BG70: 35 | BH70: - | BI70: 28936 | BK70: - | CD70: 923627 | CE70: 894691
A71: LT Heat Pumps, net billing, full cost | D71: 2.5 | E71: LT Heat Pumps, net billing, full cost, $2.50 propane rate | F71: ASHP, PV | G71: 2: Full replacement heating | H71: LT Heat Pumps, net billing, full cost, $2.50 propane rate | I71: 47.85212, -122.56923 | J71: Roofspace only | K71: 8000 | L71: PSE: 25 | M71: Net billing | N71: - | O71: 0.06713 | P71: propane | Q71: 2.5 | R71: https://drive.google.com/file/d/1Xl5WOtWsJzfbC-Y8nCxkp4Y4Mozirc_L/view?usp=drive_link | S71: 2024 | T71: https://drive.google.com/file/d/12MjGV739OVxdOUym7sn516wQM4dv51MR/view?usp=drive_link | U71: 100 | V71: 2024 | W71: 83.07 | X71: 25 | Y71: 2.5 | Z71: 6 | AA71: 7.8 | AB71: 0 | AC71: - | AD71: Small Commercial | AE71: 2220 | AF71: Rooftop, Fixed | AG71: 335.4 | AH71: 10.7 | AI71: 0 | AJ71: No MACRS | AK71: 0 | AL71: - | AM71: - | AN71: - | AO71: - | AP71: - | AQ71: - | AR71: - | AS71: - | AT71: - | AU71: - | AV71: - | AW71: - | AX71: - | AY71: 0 | AZ71: https://drive.google.com/file/d/1jrpu40DzxTFYY6LiD8LJLWmYTYBMVds2/view?usp=drive_link | BA71: 1 | BB71: 10 | BC71: No MACRS | BD71: 0 | BE71: LT Heat Pumps, net billing, full cost, 8% escalation | BG71: 35 | BH71: - | BI71: 94419 | BK71: - | CD71: 989110 | CE71: 894691
A72: LT Heat Pumps, net billing, full cost | D72: 2.75 | E72: LT Heat Pumps, net billing, full cost, $2.75 propane rate | F72: ASHP, PV | G72: 2: Full replacement heating | H72: LT Heat Pumps, net billing, full cost, $2.75 propane rate | I72: 47.85212, -122.56923 | J72: Roofspace only | K72: 8000 | L72: PSE: 25 | M72: Net billing | N72: - | O72: 0.06713 | P72: propane | Q72: 2.75 | R72: https://drive.google.com/file/d/1Xl5WOtWsJzfbC-Y8nCxkp4Y4Mozirc_L/view?usp=drive_link | S72: 2024 | T72: https://drive.google.com/file/d/12MjGV739OVxdOUym7sn516wQM4dv51MR/view?usp=drive_link | U72: 100 | V72: 2024 | W72: 83.07 | X72: 25 | Y72: 2.5 | Z72: 6 | AA72: 7.8 | AB72: 0 | AC72: - | AD72: Small Commercial | AE72: 2220 | AF72: Rooftop, Fixed | AG72: 335.4 | AH72: 10.7 | AI72: 0 | AJ72: No MACRS | AK72: 0 | AL72: - | AM72: - | AN72: - | AO72: - | AP72: - | AQ72: - | AR72: - | AS72: - | AT72: - | AU72: - | AV72: - | AW72: - | AX72: - | AY72: 0 | AZ72: https://drive.google.com/file/d/1jrpu40DzxTFYY6LiD8LJLWmYTYBMVds2/view?usp=drive_link | BA72: 1 | BB72: 10 | BC72: No MACRS | BD72: 0 | BE72: LT Heat Pumps, net billing, full cost, 10% escalation | BG72: 35 | BH72: - | BI72: 159901 | BK72: - | CD72: 1054592 | CE72: 894691
A76: If direct equation they clearly follow, you don't need to bother with running all - would also be useful to plot as a curve
A77: Life Cycle Savings
A78: Annual existing heating system fuel cost ($/gallon) | B78: No PV | C78: Net metering | D78: Net billing
A79: 1.5 | B79: -219612 | C79: -59515 | D79: -167512
A80: 1.75 | B80: -154130 | C80: 5967 | D80: -102029
A81: 2 | B81: -88647 | C81: 71450 | D81: -36546
A82: 2.25 | B82: -23165 | C82: 136932 | D82: 28936
A83: 2.5 | B83: 42318 | C83: 202415 | D83: 94419
A84: 2.75 | B84: 107800 | C84: 267897 | D84: 159901
A85: BAU Life Cycle Costs
A86: Annual existing heating system fuel cost ($/gallon) | B86: All Scenarios
A87: 1.5 | B87: =CD53+28000 -> 776333
A88: 1.75 | B88: =CD54+28000 -> 841816
A89: 2.01 | B89: =CD55+28000 -> 909918
A90: 2.25 | B90: =CD56+28000 -> 972781
A91: 2.5 | B91: =CD57+28000 -> 1038264
A92: 2.75 | B92: =CD58+28000 -> 1103746

Sheet HT Heat Pumps with Battery
A1: Scenario | B1: 1-hour Battery | C1: 2-hour Battery | D1: 4-hour Battery | E1: Net metering | F1: Net billing | G1: Full cost (25 year) | H1: NPV savings (10 year) | I1: REopt Results: | J1: Select Technologies to Evaluate | K1: Air-Source Heat Pump configuration | L1: Evaluation name | M1: Site location (latitude, longitude) | N1: PV & wind space available | O1: Roofspace available (sq ft) | P1: Electricity rate | Q1: Compensation type | R1: Net metering system size limit (kW) | S1: Net billing compensation for all exports ($/kWh) | T1: Existing heating system fuel type | U1: Annual existing heating system fuel cost ($/gallon) | V1: Upload typical electric load profile | W1: Year of load profile | X1: Upload typical heating load profile | Y1: Space heating load percent of total heating load (%) | Z1: Year of load profile | AA1: Existing heating system efficiency (% HHV-basis) | AB1: Analysis period (years) | AC1: Host discount rate, nominal (%) | AD1: Electricity cost escalation rate, nominal (%/year) | AE1: Existing heating system fuel cost escalation rate, nominal (%/year) | AF1: Host effective tax rate (%) | AG1: Emissions | AH1: Size class | AI1: System capital cost ($/kW-DC) | AJ1: Array type | AK1: Array azimuth (deg) | AL1: Array tilt (deg) | AM1: Federal Incentive based on percentage of cost (%) | AN1: MACRS schedule | AO1: MACRS bonus depreciation | AP1: Energy capacity cost ($/kWh) | AQ1: Power capacity cost ($/kW) | AR1: Constant cost ($) | AS1: Minimum energy capacity (kWh) | AT1: Maximum energy capacity (kWh) | AU1: Energy capacity replacement cost ($/kWh) | AV1: Power capacity replacement cost ($/kWh) | AW1: Constant replacement cost ($) | AX1: Minimum power capacity (kW) | AY1: Maximum power capacity (kW) | AZ1: Federal Incentive based on percentage of cost (%) | BA1: MACRS schedule | BB1: MACRS bonus depreciation | BC1: Total installed cost ($/ton) | BD1: Upload COP Table | BE1: Heat pump capacity sizing factor | BF1: Resistive heating back-up temperature threshold (°F) | BG1: MACRS schedule | BH1: MACRS bonus depreciation | BI1: REopt Results: | BJ1: Optimized PV size (kW) | BK1: Optimized ASHP size (tonnes) | BL1: Optimized Battery Power and Capacity (kW/kWh) | BM1: Potential Life Cycle Savings | BN1: Avg. Annual Grid Serving Load (kWh) | BO1: Avg. Annual Grid Charging Battery (kWh) | BP1: Avg. Annual Grid Total Electricity Consumed (kWh) | BQ1: Avg. Annual PV Serving Load (kWh) | BR1: Avg. Annual PV Charging Battery (kWh) | BS1: Avg. Annual PV Exported to Grid (kWh) | BT1: Avg. Annual PV Curtailment (kWh) | BU1: Avg. Annual PV Total Electricity Produced (kWh) | BV1: Avg. Annual Battery Serving Load (kWh) | BW1: BAU Average Annual Energy Supplied from Grid (kWh) | BX1: New System Average Annual Energy Supplied from Grid (kWh) | BY1: Difference in Avg. Annual Energy Supplied from Grid | BZ1: BAU Annual Renewable Electricity (% of electricity consumed) | CA1: Avoided CO2e Emissions throughout Analysis Period | CB1: BAU Total Year 1 Elec Cost - Pre-Tax | CC1: New Total Year 1 Elec Cost - Pre-Tax | CD1: Difference Total Year 1 Elec Cost | CE1: BAU Total Full Period Elec Cost | CF1: New Total Full Period Elec Cost | CG1: Difference in Full Period Utility Cost | CH1: BAU Total Life Cycle Costs | CI1: New Total Life Cycle Costs | CJ1: Difference in Total life cycle costs | CK1: New System Net Present Value | CL1: Payback Period for PV/ASHP (yrs)
A2: HT Heat Pumps, net metering, 1 hour battery, full cost | I2: HT Heat Pumps, net metering, 1 hour battery, full cost | REopt Web Tool | REopt Energy Integration & Optimization | NLR | J2: ASHP, Battery, PV | K2: 2: Full replacement heating | L2: HT Heat Pumps, net metering, 1 hour battery, full cost | M2: 47.85212, -122.56923 | N2: Roofspace only | O2: 8000 | P2: PSE: 25 | Q2: Net metering | R2: 100 | S2: - | T2: propane | U2: 2.01 | V2: https://drive.google.com/file/d/1Xl5WOtWsJzfbC-Y8nCxkp4Y4Mozirc_L/view?usp=drive_link | W2: 2024 | X2: https://drive.google.com/file/d/12MjGV739OVxdOUym7sn516wQM4dv51MR/view?usp=drive_link | Y2: 100 | Z2: 2024 | AA2: 83.07 | AB2: 25 | AC2: 2.5 | AD2: 6 | AE2: 7.8 | AF2: 0 | AG2: - | AH2: Small Commercial | AI2: 2220 | AJ2: Rooftop, Fixed | AK2: 335.4 | AL2: 10.7 | AM2: 0 | AN2: No MACRS | AO2: 0 | AP2: 495 | AQ2: 665 | AR2: 8066 | AS2: 25 | AT2: 25 | AU2: =0.7*AP2 -> 346.5 | AV2: =0.7*AQ2 -> 465.5 | AW2: =0.7*AR2 -> 5646.2 | AX2: 25 | AY2: 25 | AZ2: 0 | BA2: No MACRS | BB2: 0 | BC2: 0 | BD2: https://drive.google.com/file/d/16UAUdtQOC8qioWbnM096MsZ4fLvZ1Viy/view?usp=drive_link | BE2: 1 | BF2: 30 | BG2: No MACRS | BH2: 0 | BI2: HT Heat Pumps, net metering, 1 hour battery, full cost | REopt Web Tool | REopt Energy Integration & Optimization | NLR | BM2: -241084
A3: HT Heat Pumps, net metering, 1 hour battery, free capital | I3: HT Heat Pumps, net metering, 1 hour battery, free capital | REopt Web Tool | REopt Energy Integration & Optimization | NLR | J3: ASHP, Battery, PV | K3: 2: Full replacement heating | L3: HT Heat Pumps, net metering, 1 hour battery, free capital | M3: 47.85212, -122.56923 | N3: Roofspace only | O3: 8000 | P3: PSE: 25 | Q3: Net metering | R3: 100 | S3: - | T3: propane | U3: 2.01 | V3: https://drive.google.com/file/d/1Xl5WOtWsJzfbC-Y8nCxkp4Y4Mozirc_L/view?usp=drive_link | W3: 2024 | X3: https://drive.google.com/file/d/12MjGV739OVxdOUym7sn516wQM4dv51MR/view?usp=drive_link | Y3: 100 | Z3: 2024 | AA3: 83.07 | AB3: 10 | AC3: 2.5 | AD3: 6 | AE3: 7.8 | AF3: 0 | AG3: - | AH3: Small Commercial | AI3: 0 | AJ3: Rooftop, Fixed | AK3: 335.4 | AL3: 10.7 | AM3: 0 | AN3: No MACRS | AO3: 0 | AP3: 0 | AQ3: 0 | AR3: 0 | AS3: 25 | AT3: 25 | AU3: =0.7*AP3 -> 0 | AV3: =0.7*AQ3 -> 0 | AW3: =0.7*AR3 -> 0 | AX3: 25 | AY3: 25 | AZ3: 0 | BA3: No MACRS | BB3: 0 | BC3: 0 | BD3: https://drive.google.com/file/d/16UAUdtQOC8qioWbnM096MsZ4fLvZ1Viy/view?usp=drive_link | BE3: 1 | BF3: 30 | BG3: No MACRS | BH3: 0 | BI3: HT Heat Pumps, net metering, 1 hour battery, free capital | REopt Web Tool | REopt Energy Integration & Optimization | NLR | BM3: 41287
A4: HT Heat Pumps, net billing, 1 hour battery, full cost | I4: HT Heat Pumps, net billing, 1 hour battery, full cost | REopt Web Tool | REopt Energy Integration & Optimization | NLR | J4: ASHP, Battery, PV | K4: 2: Full replacement heating | L4: HT Heat Pumps, net billing, 1 hour battery, full cost | M4: 47.85212, -122.56923 | N4: Roofspace only | O4: 8000 | P4: PSE: 25 | Q4: Net billing | R4: - | S4: 0.06713 | T4: propane | U4: 2.01 | V4: https://drive.google.com/file/d/1Xl5WOtWsJzfbC-Y8nCxkp4Y4Mozirc_L/view?usp=drive_link | W4: 2024 | X4: https://drive.google.com/file/d/12MjGV739OVxdOUym7sn516wQM4dv51MR/view?usp=drive_link | Y4: 100 | Z4: 2024 | AA4: 83.07 | AB4: 25 | AC4: 2.5 | AD4: 6 | AE4: 7.8 | AF4: 0 | AG4: - | AH4: Small Commercial | AI4: 2220 | AJ4: Rooftop, Fixed | AK4: 335.4 | AL4: 10.7 | AM4: 0 | AN4: No MACRS | AO4: 0 | AP4: 495 | AQ4: 665 | AR4: 8066 | AS4: 25 | AT4: 25 | AU4: =0.7*AP4 -> 346.5 | AV4: =0.7*AQ4 -> 465.5 | AW4: =0.7*AR4 -> 5646.2 | AX4: 25 | AY4: 25 | AZ4: 0 | BA4: No MACRS | BB4: 0 | BC4: 0 | BD4: https://drive.google.com/file/d/16UAUdtQOC8qioWbnM096MsZ4fLvZ1Viy/view?usp=drive_link | BE4: 1 | BF4: 30 | BG4: No MACRS | BH4: 0 | BI4: HT Heat Pumps, net billing, 1 hour battery, full cost | REopt Web Tool | REopt Energy Integration & Optimization | NLR | BM4: -330906
A5: HT Heat Pumps, net billing, 1 hour battery, free capital | I5: HT Heat Pumps, net billing, 1 hour battery, free capital | REopt Web Tool | REopt Energy Integration & Optimization | NLR | J5: ASHP, Battery, PV | K5: 2: Full replacement heating | L5: HT Heat Pumps, net billing, 1 hour battery, free capital | M5: 47.85212, -122.56923 | N5: Roofspace only | O5: 8000 | P5: PSE: 25 | Q5: Net billing | R5: - | S5: 0.06713 | T5: propane | U5: 2.01 | V5: https://drive.google.com/file/d/1Xl5WOtWsJzfbC-Y8nCxkp4Y4Mozirc_L/view?usp=drive_link | W5: 2024 | X5: https://drive.google.com/file/d/12MjGV739OVxdOUym7sn516wQM4dv51MR/view?usp=drive_link | Y5: 100 | Z5: 2024 | AA5: 83.07 | AB5: 10 | AC5: 2.5 | AD5: 6 | AE5: 7.8 | AF5: 0 | AG5: - | AH5: Small Commercial | AI5: 0 | AJ5: Rooftop, Fixed | AK5: 335.4 | AL5: 10.7 | AM5: 0 | AN5: No MACRS | AO5: 0 | AP5: 0 | AQ5: 0 | AR5: 0 | AS5: 25 | AT5: 25 | AU5: =0.7*AP5 -> 0 | AV5: =0.7*AQ5 -> 0 | AW5: =0.7*AR5 -> 0 | AX5: 25 | AY5: 25 | AZ5: 0 | BA5: No MACRS | BB5: 0 | BC5: 0 | BD5: https://drive.google.com/file/d/16UAUdtQOC8qioWbnM096MsZ4fLvZ1Viy/view?usp=drive_link | BE5: 1 | BF5: 30 | BG5: No MACRS | BH5: 0 | BI5: HT Heat Pumps, net billing, 1 hour battery, free capital | REopt Web Tool | REopt Energy Integration & Optimization | NLR | BM5: 11828
A6: HT Heat Pumps, net metering, 2 hour battery, full cost | I6: HT Heat Pumps, net metering, 2 hour battery, full cost | REopt Web Tool | REopt Energy Integration & Optimization | NLR | J6: ASHP, Battery, PV | K6: 2: Full replacement heating | L6: HT Heat Pumps, net metering, 2 hour battery, full cost | M6: 47.85212, -122.56923 | N6: Roofspace only | O6: 8000 | P6: PSE: 25 | Q6: Net metering | R6: 100 | S6: - | T6: propane | U6: 2.01 | V6: https://drive.google.com/file/d/1Xl5WOtWsJzfbC-Y8nCxkp4Y4Mozirc_L/view?usp=drive_link | W6: 2024 | X6: https://drive.google.com/file/d/12MjGV739OVxdOUym7sn516wQM4dv51MR/view?usp=drive_link | Y6: 100 | Z6: 2024 | AA6: 83.07 | AB6: 25 | AC6: 2.5 | AD6: 6 | AE6: 7.8 | AF6: 0 | AG6: - | AH6: Small Commercial | AI6: 2220 | AJ6: Rooftop, Fixed | AK6: 335.4 | AL6: 10.7 | AM6: 0 | AN6: No MACRS | AO6: 0 | AP6: 495 | AQ6: 665 | AR6: 8066 | AS6: 50 | AT6: 50 | AU6: =0.7*AP6 -> 346.5 | AV6: =0.7*AQ6 -> 465.5 | AW6: =0.7*AR6 -> 5646.2 | AX6: 25 | AY6: 25 | AZ6: 0 | BA6: No MACRS | BB6: 0 | BC6: 0 | BD6: https://drive.google.com/file/d/16UAUdtQOC8qioWbnM096MsZ4fLvZ1Viy/view?usp=drive_link | BE6: 1 | BF6: 30 | BG6: No MACRS | BH6: 0 | BI6: HT Heat Pumps, net metering, 2 hour battery, full cost | REopt Web Tool | REopt Energy Integration & Optimization | NLR | BM6: -266401
A7: HT Heat Pumps, net metering, 2 hour battery, free capital | I7: HT Heat Pumps, net metering, 2 hour battery, free capital | REopt Web Tool | REopt Energy Integration & Optimization | NLR | J7: ASHP, Battery, PV | K7: 2: Full replacement heating | L7: HT Heat Pumps, net metering, 2 hour battery, free capital | M7: 47.85212, -122.56923 | N7: Roofspace only | O7: 8000 | P7: PSE: 25 | Q7: Net metering | R7: 100 | S7: - | T7: propane | U7: 2.01 | V7: https://drive.google.com/file/d/1Xl5WOtWsJzfbC-Y8nCxkp4Y4Mozirc_L/view?usp=drive_link | W7: 2024 | X7: https://drive.google.com/file/d/12MjGV739OVxdOUym7sn516wQM4dv51MR/view?usp=drive_link | Y7: 100 | Z7: 2024 | AA7: 83.07 | AB7: 10 | AC7: 2.5 | AD7: 6 | AE7: 7.8 | AF7: 0 | AG7: - | AH7: Small Commercial | AI7: 0 | AJ7: Rooftop, Fixed | AK7: 335.4 | AL7: 10.7 | AM7: 0 | AN7: No MACRS | AO7: 0 | AP7: 0 | AQ7: 0 | AR7: 0 | AS7: 50 | AT7: 50 | AU7: =0.7*AP7 -> 0 | AV7: =0.7*AQ7 -> 0 | AW7: =0.7*AR7 -> 0 | AX7: 25 | AY7: 25 | AZ7: 0 | BA7: No MACRS | BB7: 0 | BC7: 0 | BD7: https://drive.google.com/file/d/16UAUdtQOC8qioWbnM096MsZ4fLvZ1Viy/view?usp=drive_link | BE7: 1 | BF7: 30 | BG7: No MACRS | BH7: 0 | BI7: HT Heat Pumps, net metering, 2 hour battery, free capital | REopt Web Tool | REopt Energy Integration & Optimization | NLR | BM7: 41768
A8: HT Heat Pumps, net billing, 2 hour battery, full cost | I8: HT Heat Pumps, net billing, 2 hour battery, full cost | REopt Web Tool | REopt Energy Integration & Optimization | NLR | J8: ASHP, Battery, PV | K8: 2: Full replacement heating | L8: HT Heat Pumps, net billing, 2 hour battery, full cost | M8: 47.85212, -122.56923 | N8: Roofspace only | O8: 8000 | P8: PSE: 25 | Q8: Net billing | R8: - | S8: 0.06713 | T8: propane | U8: 2.01 | V8: https://drive.google.com/file/d/1Xl5WOtWsJzfbC-Y8nCxkp4Y4Mozirc_L/view?usp=drive_link | W8: 2024 | X8: https://drive.google.com/file/d/12MjGV739OVxdOUym7sn516wQM4dv51MR/view?usp=drive_link | Y8: 100 | Z8: 2024 | AA8: 83.07 | AB8: 25 | AC8: 2.5 | AD8: 6 | AE8: 7.8 | AF8: 0 | AG8: - | AH8: Small Commercial | AI8: 2220 | AJ8: Rooftop, Fixed | AK8: 335.4 | AL8: 10.7 | AM8: 0 | AN8: No MACRS | AO8: 0 | AP8: 495 | AQ8: 665 | AR8: 8066 | AS8: 50 | AT8: 50 | AU8: =0.7*AP8 -> 346.5 | AV8: =0.7*AQ8 -> 465.5 | AW8: =0.7*AR8 -> 5646.2 | AX8: 25 | AY8: 25 | AZ8: 0 | BA8: No MACRS | BB8: 0 | BC8: 0 | BD8: https://drive.google.com/file/d/16UAUdtQOC8qioWbnM096MsZ4fLvZ1Viy/view?usp=drive_link | BE8: 1 | BF8: 30 | BG8: No MACRS | BH8: 0 | BI8: HT Heat Pumps, net billing, 2 hour battery, full cost | REopt Web Tool | REopt Energy Integration & Optimization | NLR | BM8: -343896
A9: HT Heat Pumps, net billing, 2 hour battery, free capital | I9: HT Heat Pumps, net billing, 2 hour battery, free capital | REopt Web Tool | REopt Energy Integration & Optimization | NLR | J9: ASHP, Battery, PV | K9: 2: Full replacement heating | L9: HT Heat Pumps, net billing, 2 hour battery, free capital | M9: 47.85212, -122.56923 | N9: Roofspace only | O9: 8000 | P9: PSE: 25 | Q9: Net billing | R9: - | S9: 0.06713 | T9: propane | U9: 2.01 | V9: https://drive.google.com/file/d/1Xl5WOtWsJzfbC-Y8nCxkp4Y4Mozirc_L/view?usp=drive_link | W9: 2024 | X9: https://drive.google.com/file/d/12MjGV739OVxdOUym7sn516wQM4dv51MR/view?usp=drive_link | Y9: 100 | Z9: 2024 | AA9: 83.07 | AB9: 10 | AC9: 2.5 | AD9: 6 | AE9: 7.8 | AF9: 0 | AG9: - | AH9: Small Commercial | AI9: 0 | AJ9: Rooftop, Fixed | AK9: 335.4 | AL9: 10.7 | AM9: 0 | AN9: No MACRS | AO9: 0 | AP9: 0 | AQ9: 0 | AR9: 0 | AS9: 50 | AT9: 50 | AU9: =0.7*AP9 -> 0 | AV9: =0.7*AQ9 -> 0 | AW9: =0.7*AR9 -> 0 | AX9: 25 | AY9: 25 | AZ9: 0 | BA9: No MACRS | BB9: 0 | BC9: 0 | BD9: https://drive.google.com/file/d/16UAUdtQOC8qioWbnM096MsZ4fLvZ1Viy/view?usp=drive_link | BE9: 1 | BF9: 30 | BG9: No MACRS | BH9: 0 | BI9: HT Heat Pumps, net billing, 2 hour battery, free capital | REopt Web Tool | REopt Energy Integration & Optimization | NLR | BM9: 16210
A10: HT Heat Pumps, net metering, 4 hour battery, full cost | I10: HT Heat Pumps, net metering, 4 hour battery, full cost | REopt Web Tool | REopt Energy Integration & Optimization | NLR | J10: ASHP, Battery, PV | K10: 2: Full replacement heating | L10: HT Heat Pumps, net metering, 4 hour battery, full cost | M10: 47.85212, -122.56923 | N10: Roofspace only | O10: 8000 | P10: PSE: 25 | Q10: Net metering | R10: 100 | S10: - | T10: propane | U10: 2.01 | V10: https://drive.google.com/file/d/1Xl5WOtWsJzfbC-Y8nCxkp4Y4Mozirc_L/view?usp=drive_link | W10: 2024 | X10: https://drive.google.com/file/d/12MjGV739OVxdOUym7sn516wQM4dv51MR/view?usp=drive_link | Y10: 100 | Z10: 2024 | AA10: 83.07 | AB10: 25 | AC10: 2.5 | AD10: 6 | AE10: 7.8 | AF10: 0 | AG10: - | AH10: Small Commercial | AI10: 2220 | AJ10: Rooftop, Fixed | AK10: 335.4 | AL10: 10.7 | AM10: 0 | AN10: No MACRS | AO10: 0 | AP10: 495 | AQ10: 665 | AR10: 8066 | AS10: 100 | AT10: 100 | AU10: =0.7*AP10 -> 346.5 | AV10: =0.7*AQ10 -> 465.5 | AW10: =0.7*AR10 -> 5646.2 | AX10: 25 | AY10: 25 | AZ10: 0 | BA10: No MACRS | BB10: 0 | BC10: 0 | BD10: https://drive.google.com/file/d/16UAUdtQOC8qioWbnM096MsZ4fLvZ1Viy/view?usp=drive_link | BE10: 1 | BF10: 30 | BG10: No MACRS | BH10: 0 | BI10: HT Heat Pumps, net metering, 4 hour battery, full cost | REopt Web Tool | REopt Energy Integration & Optimization | NLR | BM10: -318776
A11: HT Heat Pumps, net metering, 4 hour battery, free capital | I11: HT Heat Pumps, net metering, 4 hour battery, free capital | REopt Web Tool | REopt Energy Integration & Optimization | NLR | J11: ASHP, Battery, PV | K11: 2: Full replacement heating | L11: HT Heat Pumps, net metering, 4 hour battery, free capital | M11: 47.85212, -122.56923 | N11: Roofspace only | O11: 8000 | P11: PSE: 25 | Q11: Net metering | R11: 100 | S11: - | T11: propane | U11: 2.01 | V11: https://drive.google.com/file/d/1Xl5WOtWsJzfbC-Y8nCxkp4Y4Mozirc_L/view?usp=drive_link | W11: 2024 | X11: https://drive.google.com/file/d/12MjGV739OVxdOUym7sn516wQM4dv51MR/view?usp=drive_link | Y11: 100 | Z11: 2024 | AA11: 83.07 | AB11: 10 | AC11: 2.5 | AD11: 6 | AE11: 7.8 | AF11: 0 | AG11: - | AH11: Small Commercial | AI11: 0 | AJ11: Rooftop, Fixed | AK11: 335.4 | AL11: 10.7 | AM11: 0 | AN11: No MACRS | AO11: 0 | AP11: 0 | AQ11: 0 | AR11: 0 | AS11: 100 | AT11: 100 | AU11: =0.7*AP11 -> 0 | AV11: =0.7*AQ11 -> 0 | AW11: =0.7*AR11 -> 0 | AX11: 25 | AY11: 25 | AZ11: 0 | BA11: No MACRS | BB11: 0 | BC11: 0 | BD11: https://drive.google.com/file/d/16UAUdtQOC8qioWbnM096MsZ4fLvZ1Viy/view?usp=drive_link | BE11: 1 | BF11: 30 | BG11: No MACRS | BH11: 0 | BI11: HT Heat Pumps, net metering, 4 hour battery, free capital | REopt Web Tool | REopt Energy Integration & Optimization | NLR | BM11: 42207
A12: HT Heat Pumps, net billing, 4 hour battery, full cost | I12: HT Heat Pumps, net billing, 4 hour battery, full cost | REopt Web Tool | REopt Energy Integration & Optimization | NLR | J12: ASHP, Battery, PV | K12: 2: Full replacement heating | L12: HT Heat Pumps, net billing, 4 hour battery, full cost | M12: 47.85212, -122.56923 | N12: Roofspace only | O12: 8000 | P12: PSE: 25 | Q12: Net billing | R12: - | S12: 0.06713 | T12: propane | U12: 2.01 | V12: https://drive.google.com/file/d/1Xl5WOtWsJzfbC-Y8nCxkp4Y4Mozirc_L/view?usp=drive_link | W12: 2024 | X12: https://drive.google.com/file/d/12MjGV739OVxdOUym7sn516wQM4dv51MR/view?usp=drive_link | Y12: 100 | Z12: 2024 | AA12: 83.07 | AB12: 25 | AC12: 2.5 | AD12: 6 | AE12: 7.8 | AF12: 0 | AG12: - | AH12: Small Commercial | AI12: 2220 | AJ12: Rooftop, Fixed | AK12: 335.4 | AL12: 10.7 | AM12: 0 | AN12: No MACRS | AO12: 0 | AP12: 495 | AQ12: 665 | AR12: 8066 | AS12: 100 | AT12: 100 | AU12: =0.7*AP12 -> 346.5 | AV12: =0.7*AQ12 -> 465.5 | AW12: =0.7*AR12 -> 5646.2 | AX12: 25 | AY12: 25 | AZ12: 0 | BA12: No MACRS | BB12: 0 | BC12: 0 | BD12: https://drive.google.com/file/d/16UAUdtQOC8qioWbnM096MsZ4fLvZ1Viy/view?usp=drive_link | BE12: 1 | BF12: 30 | BG12: No MACRS | BH12: 0 | BI12: HT Heat Pumps, net billing, 4 hour battery, full cost | REopt Web Tool | REopt Energy Integration & Optimization | NLR | BM12: -379926
A13: HT Heat Pumps, net billing, 4 hour battery, free capital | I13: HT Heat Pumps, net billing, 4 hour battery, free capital | REopt Web Tool | REopt Energy Integration & Optimization | NLR | J13: ASHP, Battery, PV | K13: 2: Full replacement heating | L13: HT Heat Pumps, net billing, 4 hour battery, free capital | M13: 47.85212, -122.56923 | N13: Roofspace only | O13: 8000 | P13: PSE: 25 | Q13: Net billing | R13: - | S13: 0.06713 | T13: propane | U13: 2.01 | V13: https://drive.google.com/file/d/1Xl5WOtWsJzfbC-Y8nCxkp4Y4Mozirc_L/view?usp=drive_link | W13: 2024 | X13: https://drive.google.com/file/d/12MjGV739OVxdOUym7sn516wQM4dv51MR/view?usp=drive_link | Y13: 100 | Z13: 2024 | AA13: 83.07 | AB13: 10 | AC13: 2.5 | AD13: 6 | AE13: 7.8 | AF13: 0 | AG13: - | AH13: Small Commercial | AI13: 0 | AJ13: Rooftop, Fixed | AK13: 335.4 | AL13: 10.7 | AM13: 0 | AN13: No MACRS | AO13: 0 | AP13: 0 | AQ13: 0 | AR13: 0 | AS13: 100 | AT13: 100 | AU13: =0.7*AP13 -> 0 | AV13: =0.7*AQ13 -> 0 | AW13: =0.7*AR13 -> 0 | AX13: 25 | AY13: 25 | AZ13: 0 | BA13: No MACRS | BB13: 0 | BC13: 0 | BD13: https://drive.google.com/file/d/16UAUdtQOC8qioWbnM096MsZ4fLvZ1Viy/view?usp=drive_link | BE13: 1 | BF13: 30 | BG13: No MACRS | BH13: 0 | BI13: HT Heat Pumps, net billing, 4 hour battery, free capital | REopt Web Tool | REopt Energy Integration & Optimization | NLR | BM13: 21739
A15: Peak demand: 66.9 kW

Sheet Electric Boiler with Battery
A1: Scenario | B1: 1-hour Battery | C1: 2-hour Battery | D1: 4-hour Battery | E1: Net metering | F1: Net billing | G1: Full cost (25 year) | H1: NPV savings (10 year) | I1: REopt Results: | J1: Select Technologies to Evaluate | K1: Air-Source Heat Pump configuration | L1: Evaluation name | M1: Site location (latitude, longitude) | N1: PV & wind space available | O1: Roofspace available (sq ft) | P1: Electricity rate | Q1: Compensation type | R1: Net metering system size limit (kW) | S1: Net billing compensation for all exports ($/kWh) | T1: Existing heating system fuel type | U1: Annual existing heating system fuel cost ($/gallon) | V1: Upload typical electric load profile | W1: Year of load profile | X1: Upload typical heating load profile | Y1: Space heating load percent of total heating load (%) | Z1: Year of load profile | AA1: Existing heating system efficiency (% HHV-basis) | AB1: Analysis period (years) | AC1: Host discount rate, nominal (%) | AD1: Electricity cost escalation rate, nominal (%/year) | AE1: Existing heating system fuel cost escalation rate, nominal (%/year) | AF1: Host effective tax rate (%) | AG1: Emissions | AH1: Size class | AI1: System capital cost ($/kW-DC) | AJ1: Array type | AK1: Array azimuth (deg) | AL1: Array tilt (deg) | AM1: Federal Incentive based on percentage of cost (%) | AN1: MACRS schedule | AO1: MACRS bonus depreciation | AP1: Energy capacity cost ($/kWh) | AQ1: Power capacity cost ($/kW) | AR1: Constant cost ($) | AS1: Minimum energy capacity (kWh) | AT1: Maximum energy capacity (kWh) | AU1: Energy capacity replacement cost ($/kWh) | AV1: Power capacity replacement cost ($/kWh) | AW1: Constant replacement cost ($) | AX1: Minimum power capacity (kW) | AY1: Maximum power capacity (kW) | AZ1: Federal Incentive based on percentage of cost (%) | BA1: MACRS schedule | BB1: MACRS bonus depreciation | BC1: Total installed cost ($/ton) | BD1: Upload COP Table | BE1: Heat pump capacity sizing factor | BF1: Resistive heating back-up temperature threshold (°F) | BG1: MACRS schedule | BH1: MACRS bonus depreciation | BI1: REopt Results: | BJ1: Optimized PV size (kW) | BK1: Optimized ASHP size (tonnes) | BL1: Optimized Battery Power and Capacity (kW/kWh) | BM1: Potential Life Cycle Savings | BN1: Avg. Annual Grid Serving Load (kWh) | BO1: Avg. Annual Grid Charging Battery (kWh) | BP1: Avg. Annual Grid Total Electricity Consumed (kWh) | BQ1: Avg. Annual PV Serving Load (kWh) | BR1: Avg. Annual PV Charging Battery (kWh) | BS1: Avg. Annual PV Exported to Grid (kWh) | BT1: Avg. Annual PV Curtailment (kWh) | BU1: Avg. Annual PV Total Electricity Produced (kWh) | BV1: Avg. Annual Battery Serving Load (kWh) | BW1: Non-PV Average Annual Energy Supplied from Grid (kWh) | BX1: PV System Average Annual Energy Supplied from Grid (kWh) | BY1: Difference in Avg. Annual Energy Supplied from Grid | BZ1: w/PV Annual Renewable Electricity (% of electricity consumed) | CA1: PV Avoided CO2e Emissions throughout Analysis Period | CB1: Non-PV Total Year 1 Elec Cost - Pre-Tax | CC1: PV Total Year 1 Elec Cost - Pre-Tax | CD1: Difference Total Year 1 Elec Cost | CE1: Non-PV Total Full Period Elec Cost | CF1: PV Total Full Period Elec Cost | CG1: Difference in Full Period Utility Cost | CH1: Non-PV Total Life Cycle Costs | CI1: PV/Battery Total Life Cycle Costs | CJ1: Difference in Total life cycle costs | CK1: w/PV/ Battery Net Present Value | CL1: Payback Period for PV /Battery (yrs)
A2: Electric Boiler, net metering, 1 hour battery, full cost | I2: Electric boiler, net metering, 1 hour battery, full cost | REopt Web Tool | REopt Energy Integration & Optimization | NLR | J2: ASHP, Battery, PV | K2: 2: Full replacement heating | L2: Electric Boiler, net metering, 1 hour battery, full cost | M2: 47.85212, -122.56923 | N2: Roofspace only | O2: 8000 | P2: PSE: 25 | Q2: Net metering | R2: 100 | S2: - | T2: propane | U2: 2.01 | V2: https://drive.google.com/file/d/1Xl5WOtWsJzfbC-Y8nCxkp4Y4Mozirc_L/view?usp=drive_link | W2: 2024 | X2: https://drive.google.com/file/d/12MjGV739OVxdOUym7sn516wQM4dv51MR/view?usp=drive_link | Y2: 100 | Z2: 2024 | AA2: 83.07 | AB2: 25 | AC2: 2.5 | AD2: 6 | AE2: 7.8 | AF2: 0 | AG2: - | AH2: Small Commercial | AI2: 2220 | AJ2: Rooftop, Fixed | AK2: 335.4 | AL2: 10.7 | AM2: 0 | AN2: No MACRS | AO2: 0 | AP2: 495 | AQ2: 665 | AR2: 8066 | AS2: 50 | AT2: 50 | AU2: =0.7*AP2 -> 346.5 | AV2: =0.7*AQ2 -> 465.5 | AW2: =0.7*AR2 -> 5646.2 | AX2: 50 | AY2: 50 | AZ2: 0 | BA2: No MACRS | BB2: 0 | BC2: 0 | BD2: https://drive.google.com/file/d/1ierMR5pp-9e4Oh1RndrdR-TIpi-DdJ91/view?usp=drive_link | BE2: 1 | BF2: 10 | BG2: No MACRS | BH2: 0 | BI2: Electric boiler, net metering, 1 hour battery, full cost | REopt Web Tool | REopt Energy Integration & Optimization | NLR | BJ2: 80 | BK2: 26 | BL2: 50;50 | BM2: -879489 | BN2: 209753 | BO2: 258 | BP2: 209753 | BQ2: 33445 | BR2: 7131 | BS2: 21262 | BT2: 0 | BU2: 61838 | BV2: 6654 | BW2: 44197 | BX2: 209753 | BY2: =BX2-BW2 -> 165556 | BZ2: 0.24 | CA2: 1183 | CB2: 8394 | CC2: 34328 | CD2: =CC2-CB2 -> 25934 | CE2: 334284 | CF2: 1367129 | CG2: =CF2-CE2 -> 1032845 | CH2: 860764 | CI2: 1740253 | CJ2: =CI2-CH2 -> 879489 | CK2: =-CJ2 -> -879489 | CL2: 0
A3: Electric Boiler, net metering, 1 hour battery, free capital | I3: Electric boiler, net metering, 1 hour battery, free capital | REopt Web Tool | REopt Energy Integration & Optimization | NLR | J3: ASHP, Battery, PV | K3: 2: Full replacement heating | L3: Electric Boiler, net metering, 1 hour battery, free capital | M3: 47.85212, -122.56923 | N3: Roofspace only | O3: 8000 | P3: PSE: 25 | Q3: Net metering | R3: 100 | S3: - | T3: propane | U3: 2.01 | V3: https://drive.google.com/file/d/1Xl5WOtWsJzfbC-Y8nCxkp4Y4Mozirc_L/view?usp=drive_link | W3: 2024 | X3: https://drive.google.com/file/d/12MjGV739OVxdOUym7sn516wQM4dv51MR/view?usp=drive_link | Y3: 100 | Z3: 2024 | AA3: 83.07 | AB3: 10 | AC3: 2.5 | AD3: 6 | AE3: 7.8 | AF3: 0 | AG3: - | AH3: Small Commercial | AI3: 0 | AJ3: Rooftop, Fixed | AK3: 335.4 | AL3: 10.7 | AM3: 0 | AN3: No MACRS | AO3: 0 | AP3: 0 | AQ3: 0 | AR3: 0 | AS3: 50 | AT3: 50 | AU3: =0.7*AP3 -> 0 | AV3: =0.7*AQ3 -> 0 | AW3: =0.7*AR3 -> 0 | AX3: 50 | AY3: 50 | AZ3: 0 | BA3: No MACRS | BB3: 0 | BC3: 0 | BD3: https://drive.google.com/file/d/1ierMR5pp-9e4Oh1RndrdR-TIpi-DdJ91/view?usp=drive_link | BE3: 1 | BF3: 10 | BG3: No MACRS | BH3: 0 | BI3: Electric boiler, net metering, 1 hour battery, free capital | REopt Web Tool | REopt Energy Integration & Optimization | NLR | BJ3: 80 | BK3: 26 | BL3: 50;50 | BM3: -133329 | BN3: 208561 | BO3: 257 | BP3: 208818 | BQ3: 34269 | BR3: 7254 | BS3: 23118 | BT3: 0 | BU3: 64641 | BV3: 6764 | BW3: 44197 | BX3: 208818 | BY3: =BX3-BW3 -> 164621 | BZ3: 0.26 | CA3: 469 | CB3: 8394 | CC3: 33900 | CD3: =CC3-CB3 -> 25506 | CE3: 101431 | CF3: 409659 | CG3: =CF3-CE3 -> 308228 | CH3: 297130 | CI3: 430459 | CJ3: =CI3-CH3 -> 133329 | CK3: =-CJ3 -> -133329 | CL3: 0
A4: Electric Boiler, net billing, 1 hour battery, full cost | I4: Electric boiler, net billing, 1 hour battery, full cost | REopt Web Tool | REopt Energy Integration & Optimization | NLR | J4: ASHP, Battery, PV | K4: 2: Full replacement heating | L4: Electric Boiler, net billing, 1 hour battery, full cost | M4: 47.85212, -122.56923 | N4: Roofspace only | O4: 8000 | P4: PSE: 25 | Q4: Net billing | R4: - | S4: 0.06713 | T4: propane | U4: 2.01 | V4: https://drive.google.com/file/d/1Xl5WOtWsJzfbC-Y8nCxkp4Y4Mozirc_L/view?usp=drive_link | W4: 2024 | X4: https://drive.google.com/file/d/12MjGV739OVxdOUym7sn516wQM4dv51MR/view?usp=drive_link | Y4: 100 | Z4: 2024 | AA4: 83.07 | AB4: 25 | AC4: 2.5 | AD4: 6 | AE4: 7.8 | AF4: 0 | AG4: - | AH4: Small Commercial | AI4: 2220 | AJ4: Rooftop, Fixed | AK4: 335.4 | AL4: 10.7 | AM4: 0 | AN4: No MACRS | AO4: 0 | AP4: 495 | AQ4: 665 | AR4: 8066 | AS4: 50 | AT4: 50 | AU4: =0.7*AP4 -> 346.5 | AV4: =0.7*AQ4 -> 465.5 | AW4: =0.7*AR4 -> 5646.2 | AX4: 50 | AY4: 50 | AZ4: 0 | BA4: No MACRS | BB4: 0 | BC4: 0 | BD4: https://drive.google.com/file/d/1ierMR5pp-9e4Oh1RndrdR-TIpi-DdJ91/view?usp=drive_link | BE4: 1 | BF4: 10 | BG4: No MACRS | BH4: 0 | BI4: Electric boiler, net billing, 1 hour battery, full cost | REopt Web Tool | REopt Energy Integration & Optimization | NLR | BJ4: 80 | BK4: 26 | BL4: 50;50 | BM4: -948014 | BN4: 209286 | BO4: 222 | BP4: 209508 | BQ4: 33450 | BR4: 7393 | BS4: 20994 | BT4: 0 | BU4: 61838 | BV4: 6857 | BW4: 44197 | BX4: 209508 | BY4: =BX4-BW4 -> 165311 | BZ4: 0.24 | CA4: 1183 | CB4: 8394 | CC4: 36049 | CD4: =CC4-CB4 -> 27655 | CE4: 334284 | CF4: 1435654 | CG4: =CF4-CE4 -> 1101370 | CH4: 860764 | CI4: 1808778 | CJ4: =CI4-CH4 -> 948014 | CK4: =-CJ4 -> -948014 | CL4: 0
A5: Electric Boiler, net billing, 1 hour battery, free capital | I5: Electric boiler, net billing, 1 hour battery, free capital | REopt Web Tool | REopt Energy Integration & Optimization | NLR | J5: ASHP, Battery, PV | K5: 2: Full replacement heating | L5: Electric Boiler, net billing, 1 hour battery, free capital | M5: 47.85212, -122.56923 | N5: Roofspace only | O5: 8000 | P5: PSE: 25 | Q5: Net billing | R5: - | S5: 0.06713 | T5: propane | U5: 2.01 | V5: https://drive.google.com/file/d/1Xl5WOtWsJzfbC-Y8nCxkp4Y4Mozirc_L/view?usp=drive_link | W5: 2024 | X5: https://drive.google.com/file/d/12MjGV739OVxdOUym7sn516wQM4dv51MR/view?usp=drive_link | Y5: 100 | Z5: 2024 | AA5: 83.07 | AB5: 10 | AC5: 2.5 | AD5: 6 | AE5: 7.8 | AF5: 0 | AG5: - | AH5: Small Commercial | AI5: 0 | AJ5: Rooftop, Fixed | AK5: 335.4 | AL5: 10.7 | AM5: 0 | AN5: No MACRS | AO5: 0 | AP5: 0 | AQ5: 0 | AR5: 0 | AS5: 50 | AT5: 50 | AU5: =0.7*AP5 -> 0 | AV5: =0.7*AQ5 -> 0 | AW5: =0.7*AR5 -> 0 | AX5: 50 | AY5: 50 | AZ5: 0 | BA5: No MACRS | BB5: 0 | BC5: 0 | BD5: https://drive.google.com/file/d/1ierMR5pp-9e4Oh1RndrdR-TIpi-DdJ91/view?usp=drive_link | BE5: 1 | BF5: 10 | BG5: No MACRS | BH5: 0 | BI5: Electric boiler, net billing, 1 hour battery, free capital | REopt Web Tool | REopt Energy Integration & Optimization | NLR | BJ5: 80 | BK5: 26 | BL5: 50;50 | BM5: -155932 | BN5: 208310 | BO5: 237 | BP5: 208547 | BQ5: 34291 | BR5: 7529 | BS5: 22821 | BT5: 0 | BU5: 64641 | BV5: 6992 | BW5: 44197 | BX5: 208547 | BY5: =BX5-BW5 -> 164350 | BZ5: 0.26 | CA5: 469 | CB5: 8394 | CC5: 35771 | CD5: =CC5-CB5 -> 27377 | CE5: 101431 | CF5: 432262 | CG5: =CF5-CE5 -> 330831 | CH5: 297130 | CI5: 453062 | CJ5: =CI5-CH5 -> 155932 | CK5: =-CJ5 -> -155932 | CL5: 0
A6: Electric Boiler, net metering, 2 hour battery, full cost | I6: Electric boiler, net metering, 2 hour battery, full cost | REopt Web Tool | REopt Energy Integration & Optimization | NLR | J6: ASHP, Battery, PV | K6: 2: Full replacement heating | L6: Electric Boiler, net metering, 2 hour battery, full cost | M6: 47.85212, -122.56923 | N6: Roofspace only | O6: 8000 | P6: PSE: 25 | Q6: Net metering | R6: 100 | S6: - | T6: propane | U6: 2.01 | V6: https://drive.google.com/file/d/1Xl5WOtWsJzfbC-Y8nCxkp4Y4Mozirc_L/view?usp=drive_link | W6: 2024 | X6: https://drive.google.com/file/d/12MjGV739OVxdOUym7sn516wQM4dv51MR/view?usp=drive_link | Y6: 100 | Z6: 2024 | AA6: 83.07 | AB6: 25 | AC6: 2.5 | AD6: 6 | AE6: 7.8 | AF6: 0 | AG6: - | AH6: Small Commercial | AI6: 2220 | AJ6: Rooftop, Fixed | AK6: 335.4 | AL6: 10.7 | AM6: 0 | AN6: No MACRS | AO6: 0 | AP6: 495 | AQ6: 665 | AR6: 8066 | AS6: 100 | AT6: 100 | AU6: =0.7*AP6 -> 346.5 | AV6: =0.7*AQ6 -> 465.5 | AW6: =0.7*AR6 -> 5646.2 | AX6: 50 | AY6: 50 | AZ6: 0 | BA6: No MACRS | BB6: 0 | BC6: 0 | BD6: https://drive.google.com/file/d/1ierMR5pp-9e4Oh1RndrdR-TIpi-DdJ91/view?usp=drive_link | BE6: 1 | BF6: 10 | BG6: No MACRS | BH6: 0 | BI6: Electric boiler, net metering, 2 hour battery, full cost | REopt Web Tool | REopt Energy Integration & Optimization | NLR | BJ6: 80 | BK6: 26 | BL6: 50;100 | BM6: -924987 | BN6: 205123 | BO6: 625 | BP6: 205748 | BQ6: 33416 | BR6: 11645 | BS6: 16777 | BT6: 0 | BU6: 61838 | BV6: 11054 | BW6: 44197 | BX6: 205748 | BY6: =BX6-BW6 -> 161551 | BZ6: 0.24 | CA6: 1184 | CB6: 8394 | CC6: 34121 | CD6: =CC6-CB6 -> 25727 | CE6: 334284 | CF6: 1358855 | CG6: =CF6-CE6 -> 1024571 | CH6: 860764 | CI6: 1785751 | CJ6: =CI6-CH6 -> 924987 | CK6: =-CJ6 -> -924987 | CL6: 0
A7: Electric Boiler, net metering, 2 hour battery, free capital | I7: Electric boiler, net metering, 2 hour battery, free capital | REopt Web Tool | REopt Energy Integration & Optimization | NLR | J7: ASHP, Battery, PV | K7: 2: Full replacement heating | L7: Electric Boiler, net metering, 2 hour battery, free capital | M7: 47.85212, -122.56923 | N7: Roofspace only | O7: 8000 | P7: PSE: 25 | Q7: Net metering | R7: 100 | S7: - | T7: propane | U7: 2.01 | V7: https://drive.google.com/file/d/1Xl5WOtWsJzfbC-Y8nCxkp4Y4Mozirc_L/view?usp=drive_link | W7: 2024 | X7: https://drive.google.com/file/d/12MjGV739OVxdOUym7sn516wQM4dv51MR/view?usp=drive_link | Y7: 100 | Z7: 2024 | AA7: 83.07 | AB7: 10 | AC7: 2.5 | AD7: 6 | AE7: 7.8 | AF7: 0 | AG7: - | AH7: Small Commercial | AI7: 0 | AJ7: Rooftop, Fixed | AK7: 335.4 | AL7: 10.7 | AM7: 0 | AN7: No MACRS | AO7: 0 | AP7: 0 | AQ7: 0 | AR7: 0 | AS7: 100 | AT7: 100 | AU7: =0.7*AP7 -> 0 | AV7: =0.7*AQ7 -> 0 | AW7: =0.7*AR7 -> 0 | AX7: 50 | AY7: 50 | AZ7: 0 | BA7: No MACRS | BB7: 0 | BC7: 0 | BD7: https://drive.google.com/file/d/1ierMR5pp-9e4Oh1RndrdR-TIpi-DdJ91/view?usp=drive_link | BE7: 1 | BF7: 10 | BG7: No MACRS | BH7: 0 | BI7: Electric boiler, net metering, 2 hour battery, free capital | REopt Web Tool | REopt Energy Integration & Optimization | NLR | BJ7: 80 | BK7: 26 | BL7: 50;100 | BM7: -130805 | BN7: 204114 | BO7: 620 | BP7: 204734 | BQ7: 34233 | BR7: 11863 | BS7: 18544 | BT7: 0 | BU7: 64641 | BV7: 11246 | BW7: 44197 | BX7: 204734 | BY7: =BX7-BW7 -> 160537 | BZ7: 0.25 | CA7: 469 | CB7: 8394 | CC7: 33691 | CD7: =CC7-CB7 -> 25297 | CE7: 101431 | CF7: 407135 | CG7: =CF7-CE7 -> 305704 | CH7: 297130 | CI7: 427935 | CJ7: =CI7-CH7 -> 130805 | CK7: =-CJ7 -> -130805 | CL7: 0
A8: Electric Boiler, net billing, 2 hour battery, full cost | I8: Electric boiler, net billing, 2 hour battery, full cost | REopt Web Tool | REopt Energy Integration & Optimization | NLR | J8: ASHP, Battery, PV | K8: 2: Full replacement heating | L8: Electric Boiler, net billing, 2 hour battery, full cost | M8: 47.85212, -122.56923 | N8: Roofspace only | O8: 8000 | P8: PSE: 25 | Q8: Net billing | R8: - | S8: 0.06713 | T8: propane | U8: 2.01 | V8: https://drive.google.com/file/d/1Xl5WOtWsJzfbC-Y8nCxkp4Y4Mozirc_L/view?usp=drive_link | W8: 2024 | X8: https://drive.google.com/file/d/12MjGV739OVxdOUym7sn516wQM4dv51MR/view?usp=drive_link | Y8: 100 | Z8: 2024 | AA8: 83.07 | AB8: 25 | AC8: 2.5 | AD8: 6 | AE8: 7.8 | AF8: 0 | AG8: - | AH8: Small Commercial | AI8: 2220 | AJ8: Rooftop, Fixed | AK8: 335.4 | AL8: 10.7 | AM8: 0 | AN8: No MACRS | AO8: 0 | AP8: 495 | AQ8: 665 | AR8: 8066 | AS8: 100 | AT8: 100 | AU8: =0.7*AP8 -> 346.5 | AV8: =0.7*AQ8 -> 465.5 | AW8: =0.7*AR8 -> 5646.2 | AX8: 50 | AY8: 50 | AZ8: 0 | BA8: No MACRS | BB8: 0 | BC8: 0 | BD8: https://drive.google.com/file/d/1ierMR5pp-9e4Oh1RndrdR-TIpi-DdJ91/view?usp=drive_link | BE8: 1 | BF8: 10 | BG8: No MACRS | BH8: 0 | BI8: Electric boiler, net billing, 2 hour battery, full cost | REopt Web Tool | REopt Energy Integration & Optimization | NLR | BJ8: 80 | BK8: 26 | BL8: 50;100 | BM8: -978750 | BN8: 204903 | BO8: 554 | BP8: 205457 | BQ8: 33429 | BR8: 11947 | BS8: 16461 | BT8: 0 | BU8: 61838 | BV8: 11261 | BW8: 44197 | BX8: 205457 | BY8: =BX8-BW8 -> 161260 | BZ8: 0.24 | CA8: 1184 | CB8: 8394 | CC8: 35470 | CD8: =CC8-CB8 -> 27076 | CE8: 334284 | CF8: 1412617 | CG8: =CF8-CE8 -> 1078333 | CH8: 860764 | CI8: 1839513 | CJ8: =CI8-CH8 -> 978749 | CK8: =-CJ8 -> -978749 | CL8: 0
A9: Electric Boiler, net billing, 2 hour battery, free capital | I9: Electric boiler, net billing, 2 hour battery, free capital | REopt Web Tool | REopt Energy Integration & Optimization | NLR | J9: ASHP, Battery, PV | K9: 2: Full replacement heating | L9: Electric Boiler, net billing, 2 hour battery, free capital | M9: 47.85212, -122.56923 | N9: Roofspace only | O9: 8000 | P9: PSE: 25 | Q9: Net billing | R9: - | S9: 0.06713 | T9: propane | U9: 2.01 | V9: https://drive.google.com/file/d/1Xl5WOtWsJzfbC-Y8nCxkp4Y4Mozirc_L/view?usp=drive_link | W9: 2024 | X9: https://drive.google.com/file/d/12MjGV739OVxdOUym7sn516wQM4dv51MR/view?usp=drive_link | Y9: 100 | Z9: 2024 | AA9: 83.07 | AB9: 10 | AC9: 2.5 | AD9: 6 | AE9: 7.8 | AF9: 0 | AG9: - | AH9: Small Commercial | AI9: 0 | AJ9: Rooftop, Fixed | AK9: 335.4 | AL9: 10.7 | AM9: 0 | AN9: No MACRS | AO9: 0 | AP9: 0 | AQ9: 0 | AR9: 0 | AS9: 100 | AT9: 100 | AU9: =0.7*AP9 -> 0 | AV9: =0.7*AQ9 -> 0 | AW9: =0.7*AR9 -> 0 | AX9: 50 | AY9: 50 | AZ9: 0 | BA9: No MACRS | BB9: 0 | BC9: 0 | BD9: https://drive.google.com/file/d/1ierMR5pp-9e4Oh1RndrdR-TIpi-DdJ91/view?usp=drive_link | BE9: 1 | BF9: 10 | BG9: No MACRS | BH9: 0 | BI9: Electric boiler, net billing, 2 hour battery, free capital | REopt Web Tool | REopt Energy Integration & Optimization | NLR | BJ9: 80 | BK9: 26 | BL9: 50;100 | BM9: -148820 | BN9: 203825 | BO9: 569 | BP9: 204394 | BQ9: 34266 | BR9: 12200 | BS9: 18174 | BT9: 0 | BU9: 64641 | BV9: 11502 | BW9: 44197 | BX9: 204394 | BY9: =BX9-BW9 -> 160197 | BZ9: 0.25 | CA9: 469 | CB9: 8394 | CC9: 35182 | CD9: =CC9-CB9 -> 26788 | CE9: 101431 | CF9: 425150 | CG9: =CF9-CE9 -> 323719 | CH9: 297130 | CI9: 445950 | CJ9: =CI9-CH9 -> 148820 | CK9: =-CJ9 -> -148820 | CL9: 0
A10: Electric Boiler, net metering, 4 hour battery, full cost | I10: Electric boiler, net metering, 4 hour battery, full cost | REopt Web Tool | REopt Energy Integration & Optimization | NLR | J10: ASHP, Battery, PV | K10: 2: Full replacement heating | L10: Electric Boiler, net metering, 4 hour battery, full cost | M10: 47.85212, -122.56923 | N10: Roofspace only | O10: 8000 | P10: PSE: 25 | Q10: Net metering | R10: 100 | S10: - | T10: propane | U10: 2.01 | V10: https://drive.google.com/file/d/1Xl5WOtWsJzfbC-Y8nCxkp4Y4Mozirc_L/view?usp=drive_link | W10: 2024 | X10: https://drive.google.com/file/d/12MjGV739OVxdOUym7sn516wQM4dv51MR/view?usp=drive_link | Y10: 100 | Z10: 2024 | AA10: 83.07 | AB10: 25 | AC10: 2.5 | AD10: 6 | AE10: 7.8 | AF10: 0 | AG10: - | AH10: Small Commercial | AI10: 2220 | AJ10: Rooftop, Fixed | AK10: 335.4 | AL10: 10.7 | AM10: 0 | AN10: No MACRS | AO10: 0 | AP10: 495 | AQ10: 665 | AR10: 8066 | AS10: 200 | AT10: 200 | AU10: =0.7*AP10 -> 346.5 | AV10: =0.7*AQ10 -> 465.5 | AW10: =0.7*AR10 -> 5646.2 | AX10: 50 | AY10: 50 | AZ10: 0 | BA10: No MACRS | BB10: 0 | BC10: 0 | BD10: https://drive.google.com/file/d/1ierMR5pp-9e4Oh1RndrdR-TIpi-DdJ91/view?usp=drive_link | BE10: 1 | BF10: 10 | BG10: No MACRS | BH10: 0 | BI10: Electric boiler, net metering, 4 hour battery, full cost | REopt Web Tool | REopt Energy Integration & Optimization | NLR | BJ10: 80 | BK10: 26 | BL10: 50;200 | BM10: -1023212 | BN10: 201224 | BO10: 1212 | BP10: 202436 | BQ10: 33224 | BR10: 15580 | BS10: 13034 | BT10: 0 | BU10: 61838 | BV10: 15146 | BW10: 44197 | BX10: 202436 | BY10: =BX10-BW10 -> 158239 | BZ10: 0.24 | CA10: 1185 | CB10: 8394 | CC10: 33886 | CD10: =CC10-CB10 -> 25492 | CE10: 334284 | CF10: 1349534 | CG10: =CF10-CE10 -> 1015250 | CH10: 860764 | CI10: 1883976 | CJ10: =CI10-CH10 -> 1023212 | CK10: =-CJ10 -> -1023212 | CL10: 0
A11: Electric Boiler, net metering, 4 hour battery, free capital | I11: Electric boiler, net metering, 4 hour battery, free capital | REopt Web Tool | REopt Energy Integration & Optimization | NLR | J11: ASHP, Battery, PV | K11: 2: Full replacement heating | L11: Electric Boiler, net metering, 4 hour battery, free capital | M11: 47.85212, -122.56923 | N11: Roofspace only | O11: 8000 | P11: PSE: 25 | Q11: Net metering | R11: 100 | S11: - | T11: propane | U11: 2.01 | V11: https://drive.google.com/file/d/1Xl5WOtWsJzfbC-Y8nCxkp4Y4Mozirc_L/view?usp=drive_link | W11: 2024 | X11: https://drive.google.com/file/d/12MjGV739OVxdOUym7sn516wQM4dv51MR/view?usp=drive_link | Y11: 100 | Z11: 2024 | AA11: 83.07 | AB11: 10 | AC11: 2.5 | AD11: 6 | AE11: 7.8 | AF11: 0 | AG11: - | AH11: Small Commercial | AI11: 0 | AJ11: Rooftop, Fixed | AK11: 335.4 | AL11: 10.7 | AM11: 0 | AN11: No MACRS | AO11: 0 | AP11: 0 | AQ11: 0 | AR11: 0 | AS11: 200 | AT11: 200 | AU11: =0.7*AP11 -> 0 | AV11: =0.7*AQ11 -> 0 | AW11: =0.7*AR11 -> 0 | AX11: 50 | AY11: 50 | AZ11: 0 | BA11: No MACRS | BB11: 0 | BC11: 0 | BD11: https://drive.google.com/file/d/1ierMR5pp-9e4Oh1RndrdR-TIpi-DdJ91/view?usp=drive_link | BE11: 1 | BF11: 10 | BG11: No MACRS | BH11: 0 | BI11: Electric boiler, net metering, 4 hour battery, free capital | REopt Web Tool | REopt Energy Integration & Optimization | NLR | BJ11: 80 | BK11: 26 | BL11: 50;200 | BM11: -127969 | BN11: 199976 | BO11: 1315 | BP11: 201291 | BQ11: 34146 | BR11: 15840 | BS11: 14655 | BT11: 0 | BU11: 64641 | BV11: 15472 | BW11: 44197 | BX11: 201291 | BY11: =BX11-BW11 -> 157094 | BZ11: 0.25 | CA11: 469 | CB11: 8394 | CC11: 33456 | CD11: =CC11-CB11 -> 25062 | CE11: 101431 | CF11: 404299 | CG11: =CF11-CE11 -> 302868 | CH11: 297130 | CI11: 425099 | CJ11: =CI11-CH11 -> 127969 | CK11: =-CJ11 -> -127969 | CL11: 0
A12: Electric Boiler, net billing, 4 hour battery, full cost | I12: Electric boiler, net billing, 4 hour battery, full cost | REopt Web Tool | REopt Energy Integration & Optimization | NLR | J12: ASHP, Battery, PV | K12: 2: Full replacement heating | L12: Electric Boiler, net billing, 4 hour battery, full cost | M12: 47.85212, -122.56923 | N12: Roofspace only | O12: 8000 | P12: PSE: 25 | Q12: Net billing | R12: - | S12: 0.06713 | T12: propane | U12: 2.01 | V12: https://drive.google.com/file/d/1Xl5WOtWsJzfbC-Y8nCxkp4Y4Mozirc_L/view?usp=drive_link | W12: 2024 | X12: https://drive.google.com/file/d/12MjGV739OVxdOUym7sn516wQM4dv51MR/view?usp=drive_link | Y12: 100 | Z12: 2024 | AA12: 83.07 | AB12: 25 | AC12: 2.5 | AD12: 6 | AE12: 7.8 | AF12: 0 | AG12: - | AH12: Small Commercial | AI12: 2220 | AJ12: Rooftop, Fixed | AK12: 335.4 | AL12: 10.7 | AM12: 0 | AN12: No MACRS | AO12: 0 | AP12: 495 | AQ12: 665 | AR12: 8066 | AS12: 200 | AT12: 200 | AU12: =0.7*AP12 -> 346.5 | AV12: =0.7*AQ12 -> 465.5 | AW12: =0.7*AR12 -> 5646.2 | AX12: 50 | AY12: 50 | AZ12: 0 | BA12: No MACRS | BB12: 0 | BC12: 0 | BD12: https://drive.google.com/file/d/1ierMR5pp-9e4Oh1RndrdR-TIpi-DdJ91/view?usp=drive_link | BE12: 1 | BF12: 10 | BG12: No MACRS | BH12: 0 | BI12: Electric boiler, net billing, 4 hour battery, full cost | REopt Web Tool | REopt Energy Integration & Optimization | NLR | BJ12: 80 | BK12: 26 | BL12: 50;200 | BM12: -1064731 | BN12: 200983 | BO12: 1153 | BP12: 202136 | BQ12: 33333 | BR12: 15786 | BS12: 12719 | BT12: 0 | BU12: 61838 | BV12: 15277 | BW12: 44197 | BX12: 202136 | BY12: =BX12-BW12 -> 157939 | BZ12: 0.24 | CA12: 1185 | CB12: 8394 | CC12: 34928 | CD12: =CC12-CB12 -> 26534 | CE12: 334284 | CF12: 1391053 | CG12: =CF12-CE12 -> 1056769 | CH12: 860764 | CI12: 1925494 | CJ12: =CI12-CH12 -> 1064730 | CK12: =-CJ12 -> -1064730 | CL12: 0
A13: Electric Boiler, net billing, 4 hour battery, free capital | I13: Electric boiler, net billing, 4 hour battery, free capital | REopt Web Tool | REopt Energy Integration & Optimization | NLR | J13: ASHP, Battery, PV | K13: 2: Full replacement heating | L13: Electric Boiler, net billing, 4 hour battery, free capital | M13: 47.85212, -122.56923 | N13: Roofspace only | O13: 8000 | P13: PSE: 25 | Q13: Net billing | R13: - | S13: 0.06713 | T13: propane | U13: 2.01 | V13: https://drive.google.com/file/d/1Xl5WOtWsJzfbC-Y8nCxkp4Y4Mozirc_L/view?usp=drive_link | W13: 2024 | X13: https://drive.google.com/file/d/12MjGV739OVxdOUym7sn516wQM4dv51MR/view?usp=drive_link | Y13: 100 | Z13: 2024 | AA13: 83.07 | AB13: 10 | AC13: 2.5 | AD13: 6 | AE13: 7.8 | AF13: 0 | AG13: - | AH13: Small Commercial | AI13: 0 | AJ13: Rooftop, Fixed | AK13: 335.4 | AL13: 10.7 | AM13: 0 | AN13: No MACRS | AO13: 0 | AP13: 0 | AQ13: 0 | AR13: 0 | AS13: 200 | AT13: 200 | AU13: =0.7*AP13 -> 0 | AV13: =0.7*AQ13 -> 0 | AW13: =0.7*AR13 -> 0 | AX13: 50 | AY13: 50 | AZ13: 0 | BA13: No MACRS | BB13: 0 | BC13: 0 | BD13: https://drive.google.com/file/d/1ierMR5pp-9e4Oh1RndrdR-TIpi-DdJ91/view?usp=drive_link | BE13: 1 | BF13: 10 | BG13: No MACRS | BH13: 0 | BI13: Electric boiler, net billing, 4 hour battery, free capital | REopt Web Tool | REopt Energy Integration & Optimization | NLR | BJ13: 80 | BK13: 26 | BL13: 50;200 | BM13: -142063 | BN13: 199787 | BO13: 1100 | BP13: 200887 | BQ13: 34099 | BR13: 16318 | BS13: 14224 | BT13: 0 | BU13: 64641 | BV13: 15708 | BW13: 44197 | BX13: 200887 | BY13: =BX13-BW13 -> 156690 | BZ13: 0.25 | CA13: 469 | CB13: 8394 | CC13: 34623 | CD13: =CC13-CB13 -> 26229 | CE13: 101431 | CF13: 418393 | CG13: =CF13-CE13 -> 316962 | CH13: 297130 | CI13: 439193 | CJ13: =CI13-CH13 -> 142063 | CK13: =-CJ13 -> -142063 | CL13: 0
A15: Peak demand: 100.5 kW

Sheet Heating Scenario Results Summar
A1: Full cost (25 years):
B2: # of Heating Equipment | C2: Heating Equipment Cost | D2: FCU scale factor | E2: # of new FCU | F2: FCU Cost | G2: Total heating CAPEX | H2: Fuel cost | I2: Electricity cost (no PV) | J2: OPEX (no PV): | K2: OPEX savings (no PV): | L2: CAPEX (no PV): | M2: CAPEX savings (no PV): | N2: Life cycle cost (no PV): | O2: Life cycle savings (no PV): | P2: PV CAPEX (net metering): | Q2: PV OPEX (net metering): | R2: Electricity cost (net metering) | S2: OPEX (net metering): | T2: OPEX savings (net metering): | U2: CAPEX (net metering): | V2: CAPEX savings (net metering): | W2: Life cycle cost (net metering): | X2: Life cycle savings (net metering): | Y2: PV CAPEX (net billing): | Z2: PV OPEX (net billing): | AA2: Electricity cost (net billing) | AB2: OPEX (net billing): | AC2: OPEX savings (net billing): | AD2: CAPEX (net billing): | AE2: CAPEX savings (net billing): | AF2: Life cycle cost (net billing): | AG2: Life cycle savings (net billing):
A3: Broken controls | B3: 1 | C3: =B3*28000 -> 28000 | D3: 1 | E3: =ROUNDUP((D3 - 1)*4,0) -> 0 | F3: =E3*3000 -> 0 | G3: =F3+C3 -> 28000 | H3: ='Propane Boiler BAU ReOPT'!BF2-'Propane Boiler BAU ReOPT'!AZ2 -> 561315 | I3: ='Propane Boiler BAU ReOPT'!AZ2 -> 355438 | J3: =I3+H3 -> 916753 | K3: =$J$3-J3 -> 0 | L3: =G3 -> 28000 | M3: =$L$3-L3 -> 0 | N3: =J3+L3 -> 944753 | O3: =$N$3-N3 -> 0 | P3: - | Q3: - | R3: - | S3: - | T3: - | U3: - | V3: - | W3: - | X3: - | Y3: - | Z3: - | AA3: - | AB3: - | AC3: - | AD3: - | AE3: - | AF3: - | AG3: -
A4: Fixed controls | B4: 1 | C4: =B4*28000 -> 28000 | D4: 1 | E4: =ROUNDUP((D4 - 1)*4,0) -> 0 | F4: =E4*3000 -> 0 | G4: =F4+C4 -> 28000 | H4: ='Propane Boiler BAU ReOPT'!BF5-'Propane Boiler BAU ReOPT'!AZ5 -> 526480 | I4: ='Propane Boiler BAU ReOPT'!AZ5 -> 355438 | J4: =I4+H4 -> 881918 | K4: =$J$3-J4 -> 34835 | L4: =G4 -> 28000 | M4: =$L$3-L4 -> 0 | N4: =J4+L4 -> 909918 | O4: =$N$3-N4 -> 34835 | P4: - | Q4: - | R4: - | S4: - | T4: - | U4: - | V4: - | W4: - | X4: - | Y4: - | Z4: - | AA4: - | AB4: - | AC4: - | AD4: - | AE4: - | AF4: - | AG4: -
A5: LT-ASHP (Schedule 25) | B5: 4 | C5: =31000+45000 -> 76000 | D5: 1.5 | E5: =ROUNDUP((D5 - 1)*4,0) -> 2 | F5: =E5*3000 -> 6000 | G5: =(F5*E5)+C5 -> 88000 | H5: 0 | I5: ='LT Heat Pumps'!CE2 -> 946792 | J5: =I5+H5 -> 946792 | K5: =$J$3-J5 -> -30039 | L5: =G5 -> 88000 | M5: =$L$3-L5 -> -60000 | N5: =J5+L5 -> 1034792 | O5: =$N$3-N5 -> -90039 | P5: 177600 | Q5: 52000 | R5: ='LT Heat Pumps'!CE4 -> 557095 | S5: =R5+Q5 -> 609095 | T5: =$J$3-S5 -> 307658 | U5: =$G5 + P5 -> 265600 | V5: =$L$3-U5 -> -237600 | W5: =S5+U5 -> 874695 | X5: =$N$3-W5 -> 70058 | Y5: 122048 | Z5: 35735 | AA5: ='LT Heat Pumps'!CE6 -> 736908 | AB5: =AA5+Z5 -> 772643 | AC5: =$J$3-AB5 -> 144110 | AD5: =$G5 + Y5 -> 210048 | AE5: =$L$3-AD5 -> -182048 | AF5: =AB5+AD5 -> 982691 | AG5: =$N$3-AF5 -> -37938
A6: LT-ASHP (Schedule 24) | B6: 4 | C6: =31000+45000 -> 76000 | D6: 1.5 | E6: =ROUNDUP((D6 - 1)*4,0) -> 2 | F6: =E6*3000 -> 6000 | G6: =(F6*E6)+C6 -> 88000 | H6: 0 | I6: ='LT Heat Pumps Schedule 24'!CE2 -> 1040295 | J6: =I6+H6 -> 1040295 | K6: =$J$3-J6 -> -123542 | L6: =G6 -> 88000 | M6: =$L$3-L6 -> -60000 | N6: =J6+L6 -> 1128295 | O6: =$N$3-N6 -> -183542 | P6: 177600 | Q6: 52000 | R6: ='LT Heat Pumps Schedule 24'!CE4 -> 558241 | S6: =R6+Q6 -> 610241 | T6: =$J$3-S6 -> 306512 | U6: =$G6 + P6 -> 265600 | V6: =$L$3-U6 -> -237600 | W6: =S6+U6 -> 875841 | X6: =$N$3-W6 -> 68912 | Y6: 156589 | Z6: 45848 | AA6: ='LT Heat Pumps Schedule 24'!CE6 -> 759711 | AB6: =AA6+Z6 -> 805559 | AC6: =$J$3-AB6 -> 111194 | AD6: =$G6 + Y6 -> 244589 | AE6: =$L$3-AD6 -> -216589 | AF6: =AB6+AD6 -> 1050148 | AG6: =$N$3-AF6 -> -105395
